[
  {
    "title": "中华人民共和国行政许可法",
    "law_type": "法律",
    "publish_office": "全国人民代表大会常务委员会",
    "publish_date": "2019-04-23",
    "effective_date": "2019-04-23",
    "status": "现行有效",
    "bbbs": "ff8080816f135f46016f216bf96b1ae6",
    "url": "https://flk.npc.gov.cn/detail2.html?ff8080816f135f46016f216bf96b1ae6",
    "content": "中华人民共和国行政许可法\n（2003年8月27日第十届全国人民代表大会常务委员会第四次会议通过　根据2019年4月23日第十三届全国人民代表大会常务委员会第十次会议《关于修改〈中华人民共和国建筑法〉等八部法律的决定》修正）\n目　　录\n第一章　总　　则\n第二章　行政许可的设定\n第三章　行政许可的实施机关\n第四章　行政许可的实施程序\n第一节　申请与受理\n第二节　审查与决定\n第三节　期　　限\n第四节　听　　证\n第五节　变更与延续\n第六节　特别规定\n第五章　行政许可的费用\n第六章　监督检查\n第七章　法律责任\n第八章　附　　则\n第一章　总　　则\n第一条　为了规范行政许可的设定和实施，保护公民、法人和其他组织的合法权益，维护公共利益和社会秩序，保障和监督行政机关有效实施行政管理，根据宪法，制定本法。\n第二条　本法所称行政许可，是指行政机关根据公民、法人或者其他组织的申请，经依法审查，准予其从事特定活动的行为。\n第三条　行政许可的设定和实施，适用本法。\n有关行政机关对其他机关或者对其直接管理的事业单位的人事、财务、外事等事项的审批，不适用本法。\n第四条　设定和实施行政许可，应当依照法定的权限、范围、条件和程序。\n第五条　设定和实施行政许可，应当遵循公开、公平、公正、非歧视的原则。\n有关行政许可的规定应当公布；未经公布的，不得作为实施行政许可的依据。行政许可的实施和结果，除涉及国家秘密、商业秘密或者个人隐私的外，应当公开。未经申请人同意，行政机关及其工作人员、参与专家评审等的人员不得披露申请人提交的商业秘密、未披露信息或者保密商务信息，法律另有规定或者涉及国家安全、重大社会公共利益的除外；行政机关依法公开申请人前述信息的，允许申请人在合理期限内提出异议。\n符合法定条件、标准的，申请人有依法取得行政许可的平等权利，行政机关不得歧视任何人。\n第六条　实施行政许可，应当遵循便民的原则，提高办事效率，提供优质服务。\n第七条　公民、法人或者其他组织对行政机关实施行政许可，享有陈述权、申辩权；有权依法申请行政复议或者提起行政诉讼；其合法权益因行政机关违法实施行政许可受到损害的，有权依法要求赔偿。\n第八条　公民、法人或者其他组织依法取得的行政许可受法律保护，行政机关不得擅自改变已经生效的行政许可。\n行政许可所依据的法律、法规、规章修改或者废止，或者准予行政许可所依据的客观情况发生重大变化的，为了公共利益的需要，行政机关可以依法变更或者撤回已经生效的行政许可。由此给公民、法人或者其他组织造成财产损失的，行政机关应当依法给予补偿。\n第九条　依法取得的行政许可，除法律、法规规定依照法定条件和程序可以转让的外，不得转让。\n第十条　县级以上人民政府应当建立健全对行政机关实施行政许可的监督制度，加强对行政机关实施行政许可的监督检查。\n行政机关应当对公民、法人或者其他组织从事行政许可事项的活动实施有效监督。\n第二章　行政许可的设定\n第十一条　设定行政许可，应当遵循经济和社会发展规律，有利于发挥公民、法人或者其他组织的积极性、主动性，维护公共利益和社会秩序，促进经济、社会和生态环境协调发展。\n第十二条　下列事项可以设定行政许可：\n（一）直接涉及国家安全、公共安全、经济宏观调控、生态环境保护以及直接关系人身健康、生命财产安全等特定活动，需要按照法定条件予以批准的事项；\n（二）有限自然资源开发利用、公共资源配置以及直接关系公共利益的特定行业的市场准入等，需要赋予特定权利的事项；\n（三）提供公众服务并且直接关系公共利益的职业、行业，需要确定具备特殊信誉、特殊条件或者特殊技能等资格、资质的事项；\n（四）直接关系公共安全、人身健康、生命财产安全的重要设备、设施、产品、物品，需要按照技术标准、技术规范，通过检验、检测、检疫等方式进行审定的事项；\n（五）企业或者其他组织的设立等，需要确定主体资格的事项；\n（六）法律、行政法规规定可以设定行政许可的其他事项。\n第十三条　本法第十二条所列事项，通过下列方式能够予以规范的，可以不设行政许可：\n（一）公民、法人或者其他组织能够自主决定的；\n（二）市场竞争机制能够有效调节的；\n（三）行业组织或者中介机构能够自律管理的；\n（四）行政机关采用事后监督等其他行政管理方式能够解决的。\n第十四条　本法第十二条所列事项，法律可以设定行政许可。尚未制定法律的，行政法规可以设定行政许可。\n必要时，国务院可以采用发布决定的方式设定行政许可。实施后，除临时性行政许可事项外，国务院应当及时提请全国人民代表大会及其常务委员会制定法律，或者自行制定行政法规。\n第十五条　本法第十二条所列事项，尚未制定法律、行政法规的，地方性法规可以设定行政许可；尚未制定法律、行政法规和地方性法规的，因行政管理的需要，确需立即实施行政许可的，省、自治区、直辖市人民政府规章可以设定临时性的行政许可。临时性的行政许可实施满一年需要继续实施的，应当提请本级人民代表大会及其常务委员会制定地方性法规。\n地方性法规和省、自治区、直辖市人民政府规章，不得设定应当由国家统一确定的公民、法人或者其他组织的资格、资质的行政许可；不得设定企业或者其他组织的设立登记及其前置性行政许可。其设定的行政许可，不得限制其他地区的个人或者企业到本地区从事生产经营和提供服务，不得限制其他地区的商品进入本地区市场。\n第十六条　行政法规可以在法律设定的行政许可事项范围内，对实施该行政许可作出具体规定。\n地方性法规可以在法律、行政法规设定的行政许可事项范围内，对实施该行政许可作出具体规定。\n规章可以在上位法设定的行政许可事项范围内，对实施该行政许可作出具体规定。\n法规、规章对实施上位法设定的行政许可作出的具体规定，不得增设行政许可；对行政许可条件作出的具体规定，不得增设违反上位法的其他条件。\n第十七条　除本法第十四条、第十五条规定的外，其他规范性文件一律不得设定行政许可。\n第十八条　设定行政许可，应当规定行政许可的实施机关、条件、程序、期限。\n第十九条　起草法律草案、法规草案和省、自治区、直辖市人民政府规章草案，拟设定行政许可的，起草单位应当采取听证会、论证会等形式听取意见，并向制定机关说明设定该行政许可的必要性、对经济和社会可能产生的影响以及听取和采纳意见的情况。\n第二十条　行政许可的设定机关应当定期对其设定的行政许可进行评价；对已设定的行政许可，认为通过本法第十三条所列方式能够解决的，应当对设定该行政许可的规定及时予以修改或者废止。\n行政许可的实施机关可以对已设定的行政许可的实施情况及存在的必要性适时进行评价，并将意见报告该行政许可的设定机关。\n公民、法人或者其他组织可以向行政许可的设定机关和实施机关就行政许可的设定和实施提出意见和建议。\n第二十一条　省、自治区、直辖市人民政府对行政法规设定的有关经济事务的行政许可，根据本行政区域经济和社会发展情况，认为通过本法第十三条所列方式能够解决的，报国务院批准后，可以在本行政区域内停止实施该行政许可。\n第三章　行政许可的实施机关\n第二十二条　行政许可由具有行政许可权的行政机关在其法定职权范围内实施。\n第二十三条　法律、法规授权的具有管理公共事务职能的组织，在法定授权范围内，以自己的名义实施行政许可。被授权的组织适用本法有关行政机关的规定。\n第二十四条　行政机关在其法定职权范围内，依照法律、法规、规章的规定，可以委托其他行政机关实施行政许可。委托机关应当将受委托行政机关和受委托实施行政许可的内容予以公告。\n委托行政机关对受委托行政机关实施行政许可的行为应当负责监督，并对该行为的后果承担法律责任。\n受委托行政机关在委托范围内，以委托行政机关名义实施行政许可；不得再委托其他组织或者个人实施行政许可。\n第二十五条　经国务院批准，省、自治区、直辖市人民政府根据精简、统一、效能的原则，可以决定一个行政机关行使有关行政机关的行政许可权。\n第二十六条　行政许可需要行政机关内设的多个机构办理的，该行政机关应当确定一个机构统一受理行政许可申请，统一送达行政许可决定。\n行政许可依法由地方人民政府两个以上部门分别实施的，本级人民政府可以确定一个部门受理行政许可申请并转告有关部门分别提出意见后统一办理，或者组织有关部门联合办理、集中办理。\n第二十七条　行政机关实施行政许可，不得向申请人提出购买指定商品、接受有偿服务等不正当要求。\n行政机关工作人员办理行政许可，不得索取或者收受申请人的财物，不得谋取其他利益。\n第二十八条　对直接关系公共安全、人身健康、生命财产安全的设备、设施、产品、物品的检验、检测、检疫，除法律、行政法规规定由行政机关实施的外，应当逐步由符合法定条件的专业技术组织实施。专业技术组织及其有关人员对所实施的检验、检测、检疫结论承担法律责任。\n第四章　行政许可的实施程序\n第一节　申请与受理\n第二十九条　公民、法人或者其他组织从事特定活动，依法需要取得行政许可的，应当向行政机关提出申请。申请书需要采用格式文本的，行政机关应当向申请人提供行政许可申请书格式文本。申请书格式文本中不得包含与申请行政许可事项没有直接关系的内容。\n申请人可以委托代理人提出行政许可申请。但是，依法应当由申请人到行政机关办公场所提出行政许可申请的除外。\n行政许可申请可以通过信函、电报、电传、传真、电子数据交换和电子邮件等方式提出。\n第三十条　行政机关应当将法律、法规、规章规定的有关行政许可的事项、依据、条件、数量、程序、期限以及需要提交的全部材料的目录和申请书示范文本等在办公场所公示。\n申请人要求行政机关对公示内容予以说明、解释的，行政机关应当说明、解释，提供准确、可靠的信息。\n第三十一条　申请人申请行政许可，应当如实向行政机关提交有关材料和反映真实情况，并对其申请材料实质内容的真实性负责。行政机关不得要求申请人提交与其申请的行政许可事项无关的技术资料和其他材料。\n行政机关及其工作人员不得以转让技术作为取得行政许可的条件；不得在实施行政许可的过程中，直接或者间接地要求转让技术。\n第三十二条　行政机关对申请人提出的行政许可申请，应当根据下列情况分别作出处理：\n（一）申请事项依法不需要取得行政许可的，应当即时告知申请人不受理；\n（二）申请事项依法不属于本行政机关职权范围的，应当即时作出不予受理的决定，并告知申请人向有关行政机关申请；\n（三）申请材料存在可以当场更正的错误的，应当允许申请人当场更正；\n（四）申请材料不齐全或者不符合法定形式的，应当当场或者在五日内一次告知申请人需要补正的全部内容，逾期不告知的，自收到申请材料之日起即为受理；\n（五）申请事项属于本行政机关职权范围，申请材料齐全、符合法定形式，或者申请人按照本行政机关的要求提交全部补正申请材料的，应当受理行政许可申请。\n行政机关受理或者不予受理行政许可申请，应当出具加盖本行政机关专用印章和注明日期的书面凭证。\n第三十三条　行政机关应当建立和完善有关制度，推行电子政务，在行政机关的网站上公布行政许可事项，方便申请人采取数据电文等方式提出行政许可申请；应当与其他行政机关共享有关行政许可信息，提高办事效率。\n第二节　审查与决定\n第三十四条　行政机关应当对申请人提交的申请材料进行审查。\n申请人提交的申请材料齐全、符合法定形式，行政机关能够当场作出决定的，应当当场作出书面的行政许可决定。\n根据法定条件和程序，需要对申请材料的实质内容进行核实的，行政机关应当指派两名以上工作人员进行核查。\n第三十五条　依法应当先经下级行政机关审查后报上级行政机关决定的行政许可，下级行政机关应当在法定期限内将初步审查意见和全部申请材料直接报送上级行政机关。上级行政机关不得要求申请人重复提供申请材料。\n第三十六条　行政机关对行政许可申请进行审查时，发现行政许可事项直接关系他人重大利益的，应当告知该利害关系人。申请人、利害关系人有权进行陈述和申辩。行政机关应当听取申请人、利害关系人的意见。\n第三十七条　行政机关对行政许可申请进行审查后，除当场作出行政许可决定的外，应当在法定期限内按照规定程序作出行政许可决定。\n第三十八条　申请人的申请符合法定条件、标准的，行政机关应当依法作出准予行政许可的书面决定。\n行政机关依法作出不予行政许可的书面决定的，应当说明理由，并告知申请人享有依法申请行政复议或者提起行政诉讼的权利。\n第三十九条　行政机关作出准予行政许可的决定，需要颁发行政许可证件的，应当向申请人颁发加盖本行政机关印章的下列行政许可证件：\n（一）许可证、执照或者其他许可证书；\n（二）资格证、资质证或者其他合格证书；\n（三）行政机关的批准文件或者证明文件；\n（四）法律、法规规定的其他行政许可证件。\n行政机关实施检验、检测、检疫的，可以在检验、检测、检疫合格的设备、设施、产品、物品上加贴标签或者加盖检验、检测、检疫印章。\n第四十条　行政机关作出的准予行政许可决定，应当予以公开，公众有权查阅。\n第四十一条　法律、行政法规设定的行政许可，其适用范围没有地域限制的，申请人取得的行政许可在全国范围内有效。\n第三节　期　　限\n第四十二条　除可以当场作出行政许可决定的外，行政机关应当自受理行政许可申请之日起二十日内作出行政许可决定。二十日内不能作出决定的，经本行政机关负责人批准，可以延长十日，并应当将延长期限的理由告知申请人。但是，法律、法规另有规定的，依照其规定。\n依照本法第二十六条的规定，行政许可采取统一办理或者联合办理、集中办理的，办理的时间不得超过四十五日；四十五日内不能办结的，经本级人民政府负责人批准，可以延长十五日，并应当将延长期限的理由告知申请人。\n第四十三条　依法应当先经下级行政机关审查后报上级行政机关决定的行政许可，下级行政机关应当自其受理行政许可申请之日起二十日内审查完毕。但是，法律、法规另有规定的，依照其规定。\n第四十四条　行政机关作出准予行政许可的决定，应当自作出决定之日起十日内向申请人颁发、送达行政许可证件，或者加贴标签、加盖检验、检测、检疫印章。\n第四十五条　行政机关作出行政许可决定，依法需要听证、招标、拍卖、检验、检测、检疫、鉴定和专家评审的，所需时间不计算在本节规定的期限内。行政机关应当将所需时间书面告知申请人。\n第四节　听　　证\n第四十六条　法律、法规、规章规定实施行政许可应当听证的事项，或者行政机关认为需要听证的其他涉及公共利益的重大行政许可事项，行政机关应当向社会公告，并举行听证。\n第四十七条　行政许可直接涉及申请人与他人之间重大利益关系的，行政机关在作出行政许可决定前，应当告知申请人、利害关系人享有要求听证的权利；申请人、利害关系人在被告知听证权利之日起五日内提出听证申请的，行政机关应当在二十日内组织听证。\n申请人、利害关系人不承担行政机关组织听证的费用。\n第四十八条　听证按照下列程序进行：\n（一）行政机关应当于举行听证的七日前将举行听证的时间、地点通知申请人、利害关系人，必要时予以公告；\n（二）听证应当公开举行；\n（三）行政机关应当指定审查该行政许可申请的工作人员以外的人员为听证主持人，申请人、利害关系人认为主持人与该行政许可事项有直接利害关系的，有权申请回避；\n（四）举行听证时，审查该行政许可申请的工作人员应当提供审查意见的证据、理由，申请人、利害关系人可以提出证据，并进行申辩和质证；\n（五）听证应当制作笔录，听证笔录应当交听证参加人确认无误后签字或者盖章。\n行政机关应当根据听证笔录，作出行政许可决定。\n第五节　变更与延续\n第四十九条　被许可人要求变更行政许可事项的，应当向作出行政许可决定的行政机关提出申请；符合法定条件、标准的，行政机关应当依法办理变更手续。\n第五十条　被许可人需要延续依法取得的行政许可的有效期的，应当在该行政许可有效期届满三十日前向作出行政许可决定的行政机关提出申请。但是，法律、法规、规章另有规定的，依照其规定。\n行政机关应当根据被许可人的申请，在该行政许可有效期届满前作出是否准予延续的决定；逾期未作决定的，视为准予延续。\n第六节　特别规定\n第五十一条　实施行政许可的程序，本节有规定的，适用本节规定；本节没有规定的，适用本章其他有关规定。\n第五十二条　国务院实施行政许可的程序，适用有关法律、行政法规的规定。\n第五十三条　实施本法第十二条第二项所列事项的行政许可的，行政机关应当通过招标、拍卖等公平竞争的方式作出决定。但是，法律、行政法规另有规定的，依照其规定。\n行政机关通过招标、拍卖等方式作出行政许可决定的具体程序，依照有关法律、行政法规的规定。\n行政机关按照招标、拍卖程序确定中标人、买受人后，应当作出准予行政许可的决定，并依法向中标人、买受人颁发行政许可证件。\n行政机关违反本条规定，不采用招标、拍卖方式，或者违反招标、拍卖程序，损害申请人合法权益的，申请人可以依法申请行政复议或者提起行政诉讼。\n第五十四条　实施本法第十二条第三项所列事项的行政许可，赋予公民特定资格，依法应当举行国家考试的，行政机关根据考试成绩和其他法定条件作出行政许可决定；赋予法人或者其他组织特定的资格、资质的，行政机关根据申请人的专业人员构成、技术条件、经营业绩和管理水平等的考核结果作出行政许可决定。但是，法律、行政法规另有规定的，依照其规定。\n公民特定资格的考试依法由行政机关或者行业组织实施，公开举行。行政机关或者行业组织应当事先公布资格考试的报名条件、报考办法、考试科目以及考试大纲。但是，不得组织强制性的资格考试的考前培训，不得指定教材或者其他助考材料。\n第五十五条　实施本法第十二条第四项所列事项的行政许可的，应当按照技术标准、技术规范依法进行检验、检测、检疫，行政机关根据检验、检测、检疫的结果作出行政许可决定。\n行政机关实施检验、检测、检疫，应当自受理申请之日起五日内指派两名以上工作人员按照技术标准、技术规范进行检验、检测、检疫。不需要对检验、检测、检疫结果作进一步技术分析即可认定设备、设施、产品、物品是否符合技术标准、技术规范的，行政机关应当当场作出行政许可决定。\n行政机关根据检验、检测、检疫结果，作出不予行政许可决定的，应当书面说明不予行政许可所依据的技术标准、技术规范。\n第五十六条　实施本法第十二条第五项所列事项的行政许可，申请人提交的申请材料齐全、符合法定形式的，行政机关应当当场予以登记。需要对申请材料的实质内容进行核实的，行政机关依照本法第三十四条第三款的规定办理。\n第五十七条　有数量限制的行政许可，两个或者两个以上申请人的申请均符合法定条件、标准的，行政机关应当根据受理行政许可申请的先后顺序作出准予行政许可的决定。但是，法律、行政法规另有规定的，依照其规定。\n第五章　行政许可的费用\n第五十八条　行政机关实施行政许可和对行政许可事项进行监督检查，不得收取任何费用。但是，法律、行政法规另有规定的，依照其规定。\n行政机关提供行政许可申请书格式文本，不得收费。\n行政机关实施行政许可所需经费应当列入本行政机关的预算，由本级财政予以保障，按照批准的预算予以核拨。\n第五十九条　行政机关实施行政许可，依照法律、行政法规收取费用的，应当按照公布的法定项目和标准收费；所收取的费用必须全部上缴国库，任何机关或者个人不得以任何形式截留、挪用、私分或者变相私分。财政部门不得以任何形式向行政机关返还或者变相返还实施行政许可所收取的费用。\n第六章　监督检查\n第六十条　上级行政机关应当加强对下级行政机关实施行政许可的监督检查，及时纠正行政许可实施中的违法行为。\n第六十一条　行政机关应当建立健全监督制度，通过核查反映被许可人从事行政许可事项活动情况的有关材料，履行监督责任。\n行政机关依法对被许可人从事行政许可事项的活动进行监督检查时，应当将监督检查的情况和处理结果予以记录，由监督检查人员签字后归档。公众有权查阅行政机关监督检查记录。\n行政机关应当创造条件，实现与被许可人、其他有关行政机关的计算机档案系统互联，核查被许可人从事行政许可事项活动情况。\n第六十二条　行政机关可以对被许可人生产经营的产品依法进行抽样检查、检验、检测，对其生产经营场所依法进行实地检查。检查时，行政机关可以依法查阅或者要求被许可人报送有关材料；被许可人应当如实提供有关情况和材料。\n行政机关根据法律、行政法规的规定，对直接关系公共安全、人身健康、生命财产安全的重要设备、设施进行定期检验。对检验合格的，行政机关应当发给相应的证明文件。\n第六十三条　行政机关实施监督检查，不得妨碍被许可人正常的生产经营活动，不得索取或者收受被许可人的财物，不得谋取其他利益。\n第六十四条　被许可人在作出行政许可决定的行政机关管辖区域外违法从事行政许可事项活动的，违法行为发生地的行政机关应当依法将被许可人的违法事实、处理结果抄告作出行政许可决定的行政机关。\n第六十五条　个人和组织发现违法从事行政许可事项的活动，有权向行政机关举报，行政机关应当及时核实、处理。\n第六十六条　被许可人未依法履行开发利用自然资源义务或者未依法履行利用公共资源义务的，行政机关应当责令限期改正；被许可人在规定期限内不改正的，行政机关应当依照有关法律、行政法规的规定予以处理。\n第六十七条　取得直接关系公共利益的特定行业的市场准入行政许可的被许可人，应当按照国家规定的服务标准、资费标准和行政机关依法规定的条件，向用户提供安全、方便、稳定和价格合理的服务，并履行普遍服务的义务；未经作出行政许可决定的行政机关批准，不得擅自停业、歇业。\n被许可人不履行前款规定的义务的，行政机关应当责令限期改正，或者依法采取有效措施督促其履行义务。\n第六十八条　对直接关系公共安全、人身健康、生命财产安全的重要设备、设施，行政机关应当督促设计、建造、安装和使用单位建立相应的自检制度。\n行政机关在监督检查时，发现直接关系公共安全、人身健康、生命财产安全的重要设备、设施存在安全隐患的，应当责令停止建造、安装和使用，并责令设计、建造、安装和使用单位立即改正。\n第六十九条　有下列情形之一的，作出行政许可决定的行政机关或者其上级行政机关，根据利害关系人的请求或者依据职权，可以撤销行政许可：\n（一）行政机关工作人员滥用职权、玩忽职守作出准予行政许可决定的；\n（二）超越法定职权作出准予行政许可决定的；\n（三）违反法定程序作出准予行政许可决定的；\n（四）对不具备申请资格或者不符合法定条件的申请人准予行政许可的；\n（五）依法可以撤销行政许可的其他情形。\n被许可人以欺骗、贿赂等不正当手段取得行政许可的，应当予以撤销。\n依照前两款的规定撤销行政许可，可能对公共利益造成重大损害的，不予撤销。\n依照本条第一款的规定撤销行政许可，被许可人的合法权益受到损害的，行政机关应当依法给予赔偿。依照本条第二款的规定撤销行政许可的，被许可人基于行政许可取得的利益不受保护。\n第七十条　有下列情形之一的，行政机关应当依法办理有关行政许可的注销手续：\n（一）行政许可有效期届满未延续的；\n（二）赋予公民特定资格的行政许可，该公民死亡或者丧失行为能力的；\n（三）法人或者其他组织依法终止的；\n（四）行政许可依法被撤销、撤回，或者行政许可证件依法被吊销的；\n（五）因不可抗力导致行政许可事项无法实施的；\n（六）法律、法规规定的应当注销行政许可的其他情形。\n第七章　法律责任\n第七十一条　违反本法第十七条规定设定的行政许可，有关机关应当责令设定该行政许可的机关改正，或者依法予以撤销。\n第七十二条　行政机关及其工作人员违反本法的规定，有下列情形之一的，由其上级行政机关或者监察机关责令改正；情节严重的，对直接负责的主管人员和其他直接责任人员依法给予行政处分：\n（一）对符合法定条件的行政许可申请不予受理的；\n（二）不在办公场所公示依法应当公示的材料的；\n（三）在受理、审查、决定行政许可过程中，未向申请人、利害关系人履行法定告知义务的；\n（四）申请人提交的申请材料不齐全、不符合法定形式，不一次告知申请人必须补正的全部内容的；\n（五）违法披露申请人提交的商业秘密、未披露信息或者保密商务信息的；\n（六）以转让技术作为取得行政许可的条件，或者在实施行政许可的过程中直接或者间接地要求转让技术的；\n（七）未依法说明不受理行政许可申请或者不予行政许可的理由的；\n（八）依法应当举行听证而不举行听证的。\n第七十三条　行政机关工作人员办理行政许可、实施监督检查，索取或者收受他人财物或者谋取其他利益，构成犯罪的，依法追究刑事责任；尚不构成犯罪的，依法给予行政处分。\n第七十四条　行政机关实施行政许可，有下列情形之一的，由其上级行政机关或者监察机关责令改正，对直接负责的主管人员和其他直接责任人员依法给予行政处分；构成犯罪的，依法追究刑事责任：\n（一）对不符合法定条件的申请人准予行政许可或者超越法定职权作出准予行政许可决定的；\n（二）对符合法定条件的申请人不予行政许可或者不在法定期限内作出准予行政许可决定的；\n（三）依法应当根据招标、拍卖结果或者考试成绩择优作出准予行政许可决定，未经招标、拍卖或者考试，或者不根据招标、拍卖结果或者考试成绩择优作出准予行政许可决定的。\n第七十五条　行政机关实施行政许可，擅自收费或者不按照法定项目和标准收费的，由其上级行政机关或者监察机关责令退还非法收取的费用；对直接负责的主管人员和其他直接责任人员依法给予行政处分。\n截留、挪用、私分或者变相私分实施行政许可依法收取的费用的，予以追缴；对直接负责的主管人员和其他直接责任人员依法给予行政处分；构成犯罪的，依法追究刑事责任。\n第七十六条　行政机关违法实施行政许可，给当事人的合法权益造成损害的，应当依照国家赔偿法的规定给予赔偿。\n第七十七条　行政机关不依法履行监督职责或者监督不力，造成严重后果的，由其上级行政机关或者监察机关责令改正，对直接负责的主管人员和其他直接责任人员依法给予行政处分；构成犯罪的，依法追究刑事责任。\n第七十八条　行政许可申请人隐瞒有关情况或者提供虚假材料申请行政许可的，行政机关不予受理或者不予行政许可，并给予警告；行政许可申请属于直接关系公共安全、人身健康、生命财产安全事项的，申请人在一年内不得再次申请该行政许可。\n第七十九条　被许可人以欺骗、贿赂等不正当手段取得行政许可的，行政机关应当依法给予行政处罚；取得的行政许可属于直接关系公共安全、人身健康、生命财产安全事项的，申请人在三年内不得再次申请该行政许可；构成犯罪的，依法追究刑事责任。\n第八十条　被许可人有下列行为之一的，行政机关应当依法给予行政处罚；构成犯罪的，依法追究刑事责任：\n（一）涂改、倒卖、出租、出借行政许可证件，或者以其他形式非法转让行政许可的；\n（二）超越行政许可范围进行活动的；\n（三）向负责监督检查的行政机关隐瞒有关情况、提供虚假材料或者拒绝提供反映其活动情况的真实材料的；\n（四）法律、法规、规章规定的其他违法行为。\n第八十一条　公民、法人或者其他组织未经行政许可，擅自从事依法应当取得行政许可的活动的，行政机关应当依法采取措施予以制止，并依法给予行政处罚；构成犯罪的，依法追究刑事责任。\n第八章　附　　则\n第八十二条　本法规定的行政机关实施行政许可的期限以工作日计算，不含法定节假日。\n第八十三条　本法自2004年7月1日起施行。\n本法施行前有关行政许可的规定，制定机关应当依照本法规定予以清理；不符合本法规定的，自本法施行之日起停止执行。",
    "source": "npc"
  },
  {
    "title": "中华人民共和国行政强制法",
    "law_type": "法律",
    "publish_office": "全国人民代表大会常务委员会",
    "publish_date": "2011-06-30",
    "effective_date": "2012-01-01",
    "status": "现行有效",
    "bbbs": "2c909fdd678bf17901678bf72f7a0613",
    "url": "https://flk.npc.gov.cn/detail2.html?2c909fdd678bf17901678bf72f7a0613",
    "content": "中华人民共和国行政强制法\n（2011年6月30日第十一届全国人民代表大会常务委员会第二十一次会议通过）\n目　　录\n第一章　总　　则\n第二章　行政强制的种类和设定\n第三章　行政强制措施实施程序\n第一节　一般规定\n第二节　查封、扣押\n第三节　冻　　结\n第四章　行政机关强制执行程序\n第一节　一般规定\n第二节　金钱给付义务的执行\n第三节　代履行\n第五章　申请人民法院强制执行\n第六章　法律责任\n第七章　附　　则\n第一章　总　　则\n第一条　为了规范行政强制的设定和实施，保障和监督行政机关依法履行职责，维护公共利益和社会秩序，保护公民、法人和其他组织的合法权益，根据宪法，制定本法。\n第二条　本法所称行政强制，包括行政强制措施和行政强制执行。\n行政强制措施，是指行政机关在行政管理过程中，为制止违法行为、防止证据损毁、避免危害发生、控制危险扩大等情形，依法对公民的人身自由实施暂时性限制，或者对公民、法人或者其他组织的财物实施暂时性控制的行为。\n行政强制执行，是指行政机关或者行政机关申请人民法院，对不履行行政决定的公民、法人或者其他组织，依法强制履行义务的行为。\n第三条　行政强制的设定和实施，适用本法。\n发生或者即将发生自然灾害、事故灾难、公共卫生事件或者社会安全事件等突发事件，行政机关采取应急措施或者临时措施，依照有关法律、行政法规的规定执行。\n行政机关采取金融业审慎监管措施、进出境货物强制性技术监控措施，依照有关法律、行政法规的规定执行。\n第四条　行政强制的设定和实施，应当依照法定的权限、范围、条件和程序。\n第五条　行政强制的设定和实施，应当适当。采用非强制手段可以达到行政管理目的的，不得设定和实施行政强制。\n第六条　实施行政强制，应当坚持教育与强制相结合。\n第七条　行政机关及其工作人员不得利用行政强制权为单位或者个人谋取利益。\n第八条　公民、法人或者其他组织对行政机关实施行政强制，享有陈述权、申辩权；有权依法申请行政复议或者提起行政诉讼；因行政机关违法实施行政强制受到损害的，有权依法要求赔偿。\n公民、法人或者其他组织因人民法院在强制执行中有违法行为或者扩大强制执行范围受到损害的，有权依法要求赔偿。\n第二章　行政强制的种类和设定\n第九条　行政强制措施的种类：\n（一）限制公民人身自由；\n（二）查封场所、设施或者财物；\n（三）扣押财物；\n（四）冻结存款、汇款；\n（五）其他行政强制措施。\n第十条　行政强制措施由法律设定。\n尚未制定法律，且属于国务院行政管理职权事项的，行政法规可以设定除本法第九条第一项、第四项和应当由法律规定的行政强制措施以外的其他行政强制措施。\n尚未制定法律、行政法规，且属于地方性事务的，地方性法规可以设定本法第九条第二项、第三项的行政强制措施。\n法律、法规以外的其他规范性文件不得设定行政强制措施。\n第十一条　法律对行政强制措施的对象、条件、种类作了规定的，行政法规、地方性法规不得作出扩大规定。\n法律中未设定行政强制措施的，行政法规、地方性法规不得设定行政强制措施。但是，法律规定特定事项由行政法规规定具体管理措施的，行政法规可以设定除本法第九条第一项、第四项和应当由法律规定的行政强制措施以外的其他行政强制措施。\n第十二条　行政强制执行的方式：\n（一）加处罚款或者滞纳金；\n（二）划拨存款、汇款；\n（三）拍卖或者依法处理查封、扣押的场所、设施或者财物；\n（四）排除妨碍、恢复原状；\n（五）代履行；\n（六）其他强制执行方式。\n第十三条　行政强制执行由法律设定。\n法律没有规定行政机关强制执行的，作出行政决定的行政机关应当申请人民法院强制执行。\n第十四条　起草法律草案、法规草案，拟设定行政强制的，起草单位应当采取听证会、论证会等形式听取意见，并向制定机关说明设定该行政强制的必要性、可能产生的影响以及听取和采纳意见的情况。\n第十五条　行政强制的设定机关应当定期对其设定的行政强制进行评价，并对不适当的行政强制及时予以修改或者废止。\n行政强制的实施机关可以对已设定的行政强制的实施情况及存在的必要性适时进行评价，并将意见报告该行政强制的设定机关。\n公民、法人或者其他组织可以向行政强制的设定机关和实施机关就行政强制的设定和实施提出意见和建议。有关机关应当认真研究论证，并以适当方式予以反馈。\n第三章　行政强制措施实施程序\n第一节　一般规定\n第十六条　行政机关履行行政管理职责，依照法律、法规的规定，实施行政强制措施。\n违法行为情节显著轻微或者没有明显社会危害的，可以不采取行政强制措施。\n第十七条　行政强制措施由法律、法规规定的行政机关在法定职权范围内实施。行政强制措施权不得委托。\n依据《中华人民共和国行政处罚法》的规定行使相对集中行政处罚权的行政机关，可以实施法律、法规规定的与行政处罚权有关的行政强制措施。\n行政强制措施应当由行政机关具备资格的行政执法人员实施，其他人员不得实施。\n第十八条　行政机关实施行政强制措施应当遵守下列规定：\n（一）实施前须向行政机关负责人报告并经批准；\n（二）由两名以上行政执法人员实施；\n（三）出示执法身份证件；\n（四）通知当事人到场；\n（五）当场告知当事人采取行政强制措施的理由、依据以及当事人依法享有的权利、救济途径；\n（六）听取当事人的陈述和申辩；\n（七）制作现场笔录；\n（八）现场笔录由当事人和行政执法人员签名或者盖章，当事人拒绝的，在笔录中予以注明；\n（九）当事人不到场的，邀请见证人到场，由见证人和行政执法人员在现场笔录上签名或者盖章；\n（十）法律、法规规定的其他程序。\n第十九条　情况紧急，需要当场实施行政强制措施的，行政执法人员应当在二十四小时内向行政机关负责人报告，并补办批准手续。行政机关负责人认为不应当采取行政强制措施的，应当立即解除。\n第二十条　依照法律规定实施限制公民人身自由的行政强制措施，除应当履行本法第十八条规定的程序外，还应当遵守下列规定：\n（一）当场告知或者实施行政强制措施后立即通知当事人家属实施行政强制措施的行政机关、地点和期限；\n（二）在紧急情况下当场实施行政强制措施的，在返回行政机关后，立即向行政机关负责人报告并补办批准手续；\n（三）法律规定的其他程序。\n实施限制人身自由的行政强制措施不得超过法定期限。实施行政强制措施的目的已经达到或者条件已经消失，应当立即解除。\n第二十一条　违法行为涉嫌犯罪应当移送司法机关的，行政机关应当将查封、扣押、冻结的财物一并移送，并书面告知当事人。\n第二节　查封、扣押\n第二十二条　查封、扣押应当由法律、法规规定的行政机关实施，其他任何行政机关或者组织不得实施。\n第二十三条　查封、扣押限于涉案的场所、设施或者财物，不得查封、扣押与违法行为无关的场所、设施或者财物；不得查封、扣押公民个人及其所扶养家属的生活必需品。\n当事人的场所、设施或者财物已被其他国家机关依法查封的，不得重复查封。\n第二十四条　行政机关决定实施查封、扣押的，应当履行本法第十八条规定的程序，制作并当场交付查封、扣押决定书和清单。\n查封、扣押决定书应当载明下列事项：\n（一）当事人的姓名或者名称、地址；\n（二）查封、扣押的理由、依据和期限；\n（三）查封、扣押场所、设施或者财物的名称、数量等；\n（四）申请行政复议或者提起行政诉讼的途径和期限；\n（五）行政机关的名称、印章和日期。\n查封、扣押清单一式二份，由当事人和行政机关分别保存。\n第二十五条　查封、扣押的期限不得超过三十日；情况复杂的，经行政机关负责人批准，可以延长，但是延长期限不得超过三十日。法律、行政法规另有规定的除外。\n延长查封、扣押的决定应当及时书面告知当事人，并说明理由。\n对物品需要进行检测、检验、检疫或者技术鉴定的，查封、扣押的期间不包括检测、检验、检疫或者技术鉴定的期间。检测、检验、检疫或者技术鉴定的期间应当明确，并书面告知当事人。检测、检验、检疫或者技术鉴定的费用由行政机关承担。\n第二十六条　对查封、扣押的场所、设施或者财物，行政机关应当妥善保管，不得使用或者损毁；造成损失的，应当承担赔偿责任。\n对查封的场所、设施或者财物，行政机关可以委托第三人保管，第三人不得损毁或者擅自转移、处置。因第三人的原因造成的损失，行政机关先行赔付后，有权向第三人追偿。\n因查封、扣押发生的保管费用由行政机关承担。\n第二十七条　行政机关采取查封、扣押措施后，应当及时查清事实，在本法第二十五条规定的期限内作出处理决定。对违法事实清楚，依法应当没收的非法财物予以没收；法律、行政法规规定应当销毁的，依法销毁；应当解除查封、扣押的，作出解除查封、扣押的决定。\n第二十八条　有下列情形之一的，行政机关应当及时作出解除查封、扣押决定：\n（一）当事人没有违法行为；\n（二）查封、扣押的场所、设施或者财物与违法行为无关；\n（三）行政机关对违法行为已经作出处理决定，不再需要查封、扣押；\n（四）查封、扣押期限已经届满；\n（五）其他不再需要采取查封、扣押措施的情形。\n解除查封、扣押应当立即退还财物；已将鲜活物品或者其他不易保管的财物拍卖或者变卖的，退还拍卖或者变卖所得款项。变卖价格明显低于市场价格，给当事人造成损失的，应当给予补偿。\n第三节　冻　　结\n第二十九条　冻结存款、汇款应当由法律规定的行政机关实施，不得委托给其他行政机关或者组织；其他任何行政机关或者组织不得冻结存款、汇款。\n冻结存款、汇款的数额应当与违法行为涉及的金额相当；已被其他国家机关依法冻结的，不得重复冻结。\n第三十条　行政机关依照法律规定决定实施冻结存款、汇款的，应当履行本法第十八条第一项、第二项、第三项、第七项规定的程序，并向金融机构交付冻结通知书。\n金融机构接到行政机关依法作出的冻结通知书后，应当立即予以冻结，不得拖延，不得在冻结前向当事人泄露信息。\n法律规定以外的行政机关或者组织要求冻结当事人存款、汇款的，金融机构应当拒绝。\n第三十一条　依照法律规定冻结存款、汇款的，作出决定的行政机关应当在三日内向当事人交付冻结决定书。冻结决定书应当载明下列事项：\n（一）当事人的姓名或者名称、地址；\n（二）冻结的理由、依据和期限；\n（三）冻结的账号和数额；\n（四）申请行政复议或者提起行政诉讼的途径和期限；\n（五）行政机关的名称、印章和日期。\n第三十二条　自冻结存款、汇款之日起三十日内，行政机关应当作出处理决定或者作出解除冻结决定；情况复杂的，经行政机关负责人批准，可以延长，但是延长期限不得超过三十日。法律另有规定的除外。\n延长冻结的决定应当及时书面告知当事人，并说明理由。\n第三十三条　有下列情形之一的，行政机关应当及时作出解除冻结决定：\n（一）当事人没有违法行为；\n（二）冻结的存款、汇款与违法行为无关；\n（三）行政机关对违法行为已经作出处理决定，不再需要冻结；\n（四）冻结期限已经届满；\n（五）其他不再需要采取冻结措施的情形。\n行政机关作出解除冻结决定的，应当及时通知金融机构和当事人。金融机构接到通知后，应当立即解除冻结。\n行政机关逾期未作出处理决定或者解除冻结决定的，金融机构应当自冻结期满之日起解除冻结。\n第四章　行政机关强制执行程序\n第一节　一般规定\n第三十四条　行政机关依法作出行政决定后，当事人在行政机关决定的期限内不履行义务的，具有行政强制执行权的行政机关依照本章规定强制执行。\n第三十五条　行政机关作出强制执行决定前，应当事先催告当事人履行义务。催告应当以书面形式作出，并载明下列事项：\n（一）履行义务的期限；\n（二）履行义务的方式；\n（三）涉及金钱给付的，应当有明确的金额和给付方式；\n（四）当事人依法享有的陈述权和申辩权。\n第三十六条　当事人收到催告书后有权进行陈述和申辩。行政机关应当充分听取当事人的意见，对当事人提出的事实、理由和证据，应当进行记录、复核。当事人提出的事实、理由或者证据成立的，行政机关应当采纳。\n第三十七条　经催告，当事人逾期仍不履行行政决定，且无正当理由的，行政机关可以作出强制执行决定。\n强制执行决定应当以书面形式作出，并载明下列事项：\n（一）当事人的姓名或者名称、地址；\n（二）强制执行的理由和依据；\n（三）强制执行的方式和时间；\n（四）申请行政复议或者提起行政诉讼的途径和期限；\n（五）行政机关的名称、印章和日期。\n在催告期间，对有证据证明有转移或者隐匿财物迹象的，行政机关可以作出立即强制执行决定。\n第三十八条　催告书、行政强制执行决定书应当直接送达当事人。当事人拒绝接收或者无法直接送达当事人的，应当依照《中华人民共和国民事诉讼法》的有关规定送达。\n第三十九条　有下列情形之一的，中止执行：\n（一）当事人履行行政决定确有困难或者暂无履行能力的；\n（二）第三人对执行标的主张权利，确有理由的；\n（三）执行可能造成难以弥补的损失，且中止执行不损害公共利益的；\n（四）行政机关认为需要中止执行的其他情形。\n中止执行的情形消失后，行政机关应当恢复执行。对没有明显社会危害，当事人确无能力履行，中止执行满三年未恢复执行的，行政机关不再执行。\n第四十条　有下列情形之一的，终结执行：\n（一）公民死亡，无遗产可供执行，又无义务承受人的；\n（二）法人或者其他组织终止，无财产可供执行，又无义务承受人的；\n（三）执行标的灭失的；\n（四）据以执行的行政决定被撤销的；\n（五）行政机关认为需要终结执行的其他情形。\n第四十一条　在执行中或者执行完毕后，据以执行的行政决定被撤销、变更，或者执行错误的，应当恢复原状或者退还财物；不能恢复原状或者退还财物的，依法给予赔偿。\n第四十二条　实施行政强制执行，行政机关可以在不损害公共利益和他人合法权益的情况下，与当事人达成执行协议。执行协议可以约定分阶段履行；当事人采取补救措施的，可以减免加处的罚款或者滞纳金。\n执行协议应当履行。当事人不履行执行协议的，行政机关应当恢复强制执行。\n第四十三条　行政机关不得在夜间或者法定节假日实施行政强制执行。但是，情况紧急的除外。\n行政机关不得对居民生活采取停止供水、供电、供热、供燃气等方式迫使当事人履行相关行政决定。\n第四十四条　对违法的建筑物、构筑物、设施等需要强制拆除的，应当由行政机关予以公告，限期当事人自行拆除。当事人在法定期限内不申请行政复议或者提起行政诉讼，又不拆除的，行政机关可以依法强制拆除。\n第二节　金钱给付义务的执行\n第四十五条　行政机关依法作出金钱给付义务的行政决定，当事人逾期不履行的，行政机关可以依法加处罚款或者滞纳金。加处罚款或者滞纳金的标准应当告知当事人。\n加处罚款或者滞纳金的数额不得超出金钱给付义务的数额。\n第四十六条　行政机关依照本法第四十五条规定实施加处罚款或者滞纳金超过三十日，经催告当事人仍不履行的，具有行政强制执行权的行政机关可以强制执行。\n行政机关实施强制执行前，需要采取查封、扣押、冻结措施的，依照本法第三章规定办理。\n没有行政强制执行权的行政机关应当申请人民法院强制执行。但是，当事人在法定期限内不申请行政复议或者提起行政诉讼，经催告仍不履行的，在实施行政管理过程中已经采取查封、扣押措施的行政机关，可以将查封、扣押的财物依法拍卖抵缴罚款。\n第四十七条　划拨存款、汇款应当由法律规定的行政机关决定，并书面通知金融机构。金融机构接到行政机关依法作出划拨存款、汇款的决定后，应当立即划拨。\n法律规定以外的行政机关或者组织要求划拨当事人存款、汇款的，金融机构应当拒绝。\n第四十八条　依法拍卖财物，由行政机关委托拍卖机构依照《中华人民共和国拍卖法》的规定办理。\n第四十九条　划拨的存款、汇款以及拍卖和依法处理所得的款项应当上缴国库或者划入财政专户。任何行政机关或者个人不得以任何形式截留、私分或者变相私分。\n第三节　代履行\n第五十条　行政机关依法作出要求当事人履行排除妨碍、恢复原状等义务的行政决定，当事人逾期不履行，经催告仍不履行，其后果已经或者将危害交通安全、造成环境污染或者破坏自然资源的，行政机关可以代履行，或者委托没有利害关系的第三人代履行。\n第五十一条　代履行应当遵守下列规定：\n（一）代履行前送达决定书，代履行决定书应当载明当事人的姓名或者名称、地址，代履行的理由和依据、方式和时间、标的、费用预算以及代履行人；\n（二）代履行三日前，催告当事人履行，当事人履行的，停止代履行；\n（三）代履行时，作出决定的行政机关应当派员到场监督；\n（四）代履行完毕，行政机关到场监督的工作人员、代履行人和当事人或者见证人应当在执行文书上签名或者盖章。\n代履行的费用按照成本合理确定，由当事人承担。但是，法律另有规定的除外。\n代履行不得采用暴力、胁迫以及其他非法方式。\n第五十二条　需要立即清除道路、河道、航道或者公共场所的遗洒物、障碍物或者污染物，当事人不能清除的，行政机关可以决定立即实施代履行；当事人不在场的，行政机关应当在事后立即通知当事人，并依法作出处理。\n第五章　申请人民法院强制执行\n第五十三条　当事人在法定期限内不申请行政复议或者提起行政诉讼，又不履行行政决定的，没有行政强制执行权的行政机关可以自期限届满之日起三个月内，依照本章规定申请人民法院强制执行。\n第五十四条　行政机关申请人民法院强制执行前，应当催告当事人履行义务。催告书送达十日后当事人仍未履行义务的，行政机关可以向所在地有管辖权的人民法院申请强制执行；执行对象是不动产的，向不动产所在地有管辖权的人民法院申请强制执行。\n第五十五条　行政机关向人民法院申请强制执行，应当提供下列材料：\n（一）强制执行申请书；\n（二）行政决定书及作出决定的事实、理由和依据；\n（三）当事人的意见及行政机关催告情况；\n（四）申请强制执行标的情况；\n（五）法律、行政法规规定的其他材料。\n强制执行申请书应当由行政机关负责人签名，加盖行政机关的印章，并注明日期。\n第五十六条　人民法院接到行政机关强制执行的申请，应当在五日内受理。\n行政机关对人民法院不予受理的裁定有异议的，可以在十五日内向上一级人民法院申请复议，上一级人民法院应当自收到复议申请之日起十五日内作出是否受理的裁定。\n第五十七条　人民法院对行政机关强制执行的申请进行书面审查，对符合本法第五十五条规定，且行政决定具备法定执行效力的，除本法第五十八条规定的情形外，人民法院应当自受理之日起七日内作出执行裁定。\n第五十八条　人民法院发现有下列情形之一的，在作出裁定前可以听取被执行人和行政机关的意见：\n（一）明显缺乏事实根据的；\n（二）明显缺乏法律、法规依据的；\n（三）其他明显违法并损害被执行人合法权益的。\n人民法院应当自受理之日起三十日内作出是否执行的裁定。裁定不予执行的，应当说明理由，并在五日内将不予执行的裁定送达行政机关。\n行政机关对人民法院不予执行的裁定有异议的，可以自收到裁定之日起十五日内向上一级人民法院申请复议，上一级人民法院应当自收到复议申请之日起三十日内作出是否执行的裁定。\n第五十九条　因情况紧急，为保障公共安全，行政机关可以申请人民法院立即执行。经人民法院院长批准，人民法院应当自作出执行裁定之日起五日内执行。\n第六十条　行政机关申请人民法院强制执行，不缴纳申请费。强制执行的费用由被执行人承担。\n人民法院以划拨、拍卖方式强制执行的，可以在划拨、拍卖后将强制执行的费用扣除。\n依法拍卖财物，由人民法院委托拍卖机构依照《中华人民共和国拍卖法》的规定办理。\n划拨的存款、汇款以及拍卖和依法处理所得的款项应当上缴国库或者划入财政专户，不得以任何形式截留、私分或者变相私分。\n第六章　法律责任\n第六十一条　行政机关实施行政强制，有下列情形之一的，由上级行政机关或者有关部门责令改正，对直接负责的主管人员和其他直接责任人员依法给予处分：\n（一）没有法律、法规依据的；\n（二）改变行政强制对象、条件、方式的；\n（三）违反法定程序实施行政强制的；\n（四）违反本法规定，在夜间或者法定节假日实施行政强制执行的；\n（五）对居民生活采取停止供水、供电、供热、供燃气等方式迫使当事人履行相关行政决定的；\n（六）有其他违法实施行政强制情形的。\n第六十二条　违反本法规定，行政机关有下列情形之一的，由上级行政机关或者有关部门责令改正，对直接负责的主管人员和其他直接责任人员依法给予处分：\n（一）扩大查封、扣押、冻结范围的；\n（二）使用或者损毁查封、扣押场所、设施或者财物的；\n（三）在查封、扣押法定期间不作出处理决定或者未依法及时解除查封、扣押的；\n（四）在冻结存款、汇款法定期间不作出处理决定或者未依法及时解除冻结的。\n第六十三条　行政机关将查封、扣押的财物或者划拨的存款、汇款以及拍卖和依法处理所得的款项，截留、私分或者变相私分的，由财政部门或者有关部门予以追缴；对直接负责的主管人员和其他直接责任人员依法给予记大过、降级、撤职或者开除的处分。\n行政机关工作人员利用职务上的便利，将查封、扣押的场所、设施或者财物据为己有的，由上级行政机关或者有关部门责令改正，依法给予记大过、降级、撤职或者开除的处分。\n第六十四条　行政机关及其工作人员利用行政强制权为单位或者个人谋取利益的，由上级行政机关或者有关部门责令改正，对直接负责的主管人员和其他直接责任人员依法给予处分。\n第六十五条　违反本法规定，金融机构有下列行为之一的，由金融业监督管理机构责令改正，对直接负责的主管人员和其他直接责任人员依法给予处分：\n（一）在冻结前向当事人泄露信息的；\n（二）对应当立即冻结、划拨的存款、汇款不冻结或者不划拨，致使存款、汇款转移的；\n（三）将不应当冻结、划拨的存款、汇款予以冻结或者划拨的；\n（四）未及时解除冻结存款、汇款的。\n第六十六条　违反本法规定，金融机构将款项划入国库或者财政专户以外的其他账户的，由金融业监督管理机构责令改正，并处以违法划拨款项二倍的罚款；对直接负责的主管人员和其他直接责任人员依法给予处分。\n违反本法规定，行政机关、人民法院指令金融机构将款项划入国库或者财政专户以外的其他账户的，对直接负责的主管人员和其他直接责任人员依法给予处分。\n第六十七条　人民法院及其工作人员在强制执行中有违法行为或者扩大强制执行范围的，对直接负责的主管人员和其他直接责任人员依法给予处分。\n第六十八条　违反本法规定，给公民、法人或者其他组织造成损失的，依法给予赔偿。\n违反本法规定，构成犯罪的，依法追究刑事责任。\n第七章　附　　则\n第六十九条　本法中十日以内期限的规定是指工作日，不含法定节假日。\n第七十条　法律、行政法规授权的具有管理公共事务职能的组织在法定授权范围内，以自己的名义实施行政强制，适用本法有关行政机关的规定。\n第七十一条　本法自2012年1月1日起施行。",
    "source": "npc"
  },
  {
    "title": "中华人民共和国国家赔偿法",
    "law_type": "法律",
    "publish_office": "全国人民代表大会常务委员会",
    "publish_date": "2012-10-26",
    "effective_date": "2013-01-01",
    "status": "现行有效",
    "bbbs": "2c909fdd678bf17901678bf74c26069f",
    "url": "https://flk.npc.gov.cn/detail2.html?2c909fdd678bf17901678bf74c26069f",
    "content": "中华人民共和国国家赔偿法\n（1994年5月12日第八届全国人民代表大会常务委员会第七次会议通过　根据2010年4月29日第十一届全国人民代表大会常务委员会第十四次会议《关于修改〈中华人民共和国国家赔偿法〉的决定》第一次修正　根据2012年10月26日第十一届全国人民代表大会常务委员会第二十九次会议《关于修改〈中华人民共和国国家赔偿法〉的决定》第二次修正）\n目　　录\n第一章　总　　则\n第二章　行政赔偿\n第一节　赔偿范围\n第二节　赔偿请求人和赔偿义务机关\n第三节　赔偿程序\n第三章　刑事赔偿\n第一节　赔偿范围\n第二节　赔偿请求人和赔偿义务机关\n第三节　赔偿程序\n第四章　赔偿方式和计算标准\n第五章　其他规定\n第六章　附　　则\n第一章　总　　则\n第一条　为保障公民、法人和其他组织享有依法取得国家赔偿的权利，促进国家机关依法行使职权，根据宪法，制定本法。\n第二条　国家机关和国家机关工作人员行使职权，有本法规定的侵犯公民、法人和其他组织合法权益的情形，造成损害的，受害人有依照本法取得国家赔偿的权利。\n本法规定的赔偿义务机关，应当依照本法及时履行赔偿义务。\n第二章　行政赔偿\n第一节　赔偿范围\n第三条　行政机关及其工作人员在行使行政职权时有下列侵犯人身权情形之一的，受害人有取得赔偿的权利：\n（一）违法拘留或者违法采取限制公民人身自由的行政强制措施的；\n（二）非法拘禁或者以其他方法非法剥夺公民人身自由的；\n（三）以殴打、虐待等行为或者唆使、放纵他人以殴打、虐待等行为造成公民身体伤害或者死亡的；\n（四）违法使用武器、警械造成公民身体伤害或者死亡的；\n（五）造成公民身体伤害或者死亡的其他违法行为。\n第四条　行政机关及其工作人员在行使行政职权时有下列侵犯财产权情形之一的，受害人有取得赔偿的权利：\n（一）违法实施罚款、吊销许可证和执照、责令停产停业、没收财物等行政处罚的；\n（二）违法对财产采取查封、扣押、冻结等行政强制措施的；\n（三）违法征收、征用财产的；\n（四）造成财产损害的其他违法行为。\n第五条　属于下列情形之一的，国家不承担赔偿责任：\n（一）行政机关工作人员与行使职权无关的个人行为；\n（二）因公民、法人和其他组织自己的行为致使损害发生的；\n（三）法律规定的其他情形。\n第二节　赔偿请求人和赔偿义务机关\n第六条　受害的公民、法人和其他组织有权要求赔偿。\n受害的公民死亡，其继承人和其他有扶养关系的亲属有权要求赔偿。\n受害的法人或者其他组织终止的，其权利承受人有权要求赔偿。\n第七条　行政机关及其工作人员行使行政职权侵犯公民、法人和其他组织的合法权益造成损害的，该行政机关为赔偿义务机关。\n两个以上行政机关共同行使行政职权时侵犯公民、法人和其他组织的合法权益造成损害的，共同行使行政职权的行政机关为共同赔偿义务机关。\n法律、法规授权的组织在行使授予的行政权力时侵犯公民、法人和其他组织的合法权益造成损害的，被授权的组织为赔偿义务机关。\n受行政机关委托的组织或者个人在行使受委托的行政权力时侵犯公民、法人和其他组织的合法权益造成损害的，委托的行政机关为赔偿义务机关。\n赔偿义务机关被撤销的，继续行使其职权的行政机关为赔偿义务机关；没有继续行使其职权的行政机关的，撤销该赔偿义务机关的行政机关为赔偿义务机关。\n第八条　经复议机关复议的，最初造成侵权行为的行政机关为赔偿义务机关，但复议机关的复议决定加重损害的，复议机关对加重的部分履行赔偿义务。\n第三节　赔偿程序\n第九条　赔偿义务机关有本法第三条、第四条规定情形之一的，应当给予赔偿。\n赔偿请求人要求赔偿，应当先向赔偿义务机关提出，也可以在申请行政复议或者提起行政诉讼时一并提出。\n第十条　赔偿请求人可以向共同赔偿义务机关中的任何一个赔偿义务机关要求赔偿，该赔偿义务机关应当先予赔偿。\n第十一条　赔偿请求人根据受到的不同损害，可以同时提出数项赔偿要求。\n第十二条　要求赔偿应当递交申请书，申请书应当载明下列事项：\n（一）受害人的姓名、性别、年龄、工作单位和住所，法人或者其他组织的名称、住所和法定代表人或者主要负责人的姓名、职务；\n（二）具体的要求、事实根据和理由；\n（三）申请的年、月、日。\n赔偿请求人书写申请书确有困难的，可以委托他人代书；也可以口头申请，由赔偿义务机关记入笔录。\n赔偿请求人不是受害人本人的，应当说明与受害人的关系，并提供相应证明。\n赔偿请求人当面递交申请书的，赔偿义务机关应当当场出具加盖本行政机关专用印章并注明收讫日期的书面凭证。申请材料不齐全的，赔偿义务机关应当当场或者在五日内一次性告知赔偿请求人需要补正的全部内容。\n第十三条　赔偿义务机关应当自收到申请之日起两个月内，作出是否赔偿的决定，赔偿义务机关作出赔偿决定，应当充分听取赔偿请求人的意见，并可以与赔偿请求人就赔偿方式、赔偿项目和赔偿数额依照本法第四章的规定进行协商。\n赔偿义务机关决定赔偿的，应当制作赔偿决定书，并自作出决定之日起十日内送达赔偿请求人。\n赔偿义务机关决定不予赔偿的，应当自作出决定之日起十日内书面通知赔偿请求人，并说明不予赔偿的理由。\n第十四条　赔偿义务机关在规定期限内未作出是否赔偿的决定，赔偿请求人可以自期限届满之日起三个月内，向人民法院提起诉讼。\n赔偿请求人对赔偿的方式、项目、数额有异议的，或者赔偿义务机关作出不予赔偿决定的，赔偿请求人可以自赔偿义务机关作出赔偿或者不予赔偿决定之日起三个月内，向人民法院提起诉讼。\n第十五条　人民法院审理行政赔偿案件，赔偿请求人和赔偿义务机关对自己提出的主张，应当提供证据。\n赔偿义务机关采取行政拘留或者限制人身自由的强制措施期间，被限制人身自由的人死亡或者丧失行为能力的，赔偿义务机关的行为与被限制人身自由的人的死亡或者丧失行为能力是否存在因果关系，赔偿义务机关应当提供证据。\n第十六条　赔偿义务机关赔偿损失后，应当责令有故意或者重大过失的工作人员或者受委托的组织或者个人承担部分或者全部赔偿费用。\n对有故意或者重大过失的责任人员，有关机关应当依法给予处分；构成犯罪的，应当依法追究刑事责任。\n第三章　刑事赔偿\n第一节　赔偿范围\n第十七条　行使侦查、检察、审判职权的机关以及看守所、监狱管理机关及其工作人员在行使职权时有下列侵犯人身权情形之一的，受害人有取得赔偿的权利：\n（一）违反刑事诉讼法的规定对公民采取拘留措施的，或者依照刑事诉讼法规定的条件和程序对公民采取拘留措施，但是拘留时间超过刑事诉讼法规定的时限，其后决定撤销案件、不起诉或者判决宣告无罪终止追究刑事责任的；\n（二）对公民采取逮捕措施后，决定撤销案件、不起诉或者判决宣告无罪终止追究刑事责任的；\n（三）依照审判监督程序再审改判无罪，原判刑罚已经执行的；\n（四）刑讯逼供或者以殴打、虐待等行为或者唆使、放纵他人以殴打、虐待等行为造成公民身体伤害或者死亡的；\n（五）违法使用武器、警械造成公民身体伤害或者死亡的。\n第十八条　行使侦查、检察、审判职权的机关以及看守所、监狱管理机关及其工作人员在行使职权时有下列侵犯财产权情形之一的，受害人有取得赔偿的权利：\n（一）违法对财产采取查封、扣押、冻结、追缴等措施的；\n（二）依照审判监督程序再审改判无罪，原判罚金、没收财产已经执行的。\n第十九条　属于下列情形之一的，国家不承担赔偿责任：\n（一）因公民自己故意作虚伪供述，或者伪造其他有罪证据被羁押或者被判处刑罚的；\n（二）依照刑法第十七条、第十八条规定不负刑事责任的人被羁押的；\n（三）依照刑事诉讼法第十五条、第一百七十三条第二款、第二百七十三条第二款、第二百七十九条规定不追究刑事责任的人被羁押的；\n（四）行使侦查、检察、审判职权的机关以及看守所、监狱管理机关的工作人员与行使职权无关的个人行为；\n（五）因公民自伤、自残等故意行为致使损害发生的；\n（六）法律规定的其他情形。\n第二节　赔偿请求人和赔偿义务机关\n第二十条　赔偿请求人的确定依照本法第六条的规定。\n第二十一条　行使侦查、检察、审判职权的机关以及看守所、监狱管理机关及其工作人员在行使职权时侵犯公民、法人和其他组织的合法权益造成损害的，该机关为赔偿义务机关。\n对公民采取拘留措施，依照本法的规定应当给予国家赔偿的，作出拘留决定的机关为赔偿义务机关。\n对公民采取逮捕措施后决定撤销案件、不起诉或者判决宣告无罪的，作出逮捕决定的机关为赔偿义务机关。\n再审改判无罪的，作出原生效判决的人民法院为赔偿义务机关。二审改判无罪，以及二审发回重审后作无罪处理的，作出一审有罪判决的人民法院为赔偿义务机关。\n第三节　赔偿程序\n第二十二条　赔偿义务机关有本法第十七条、第十八条规定情形之一的，应当给予赔偿。\n赔偿请求人要求赔偿，应当先向赔偿义务机关提出。\n赔偿请求人提出赔偿请求，适用本法第十一条、第十二条的规定。\n第二十三条　赔偿义务机关应当自收到申请之日起两个月内，作出是否赔偿的决定。赔偿义务机关作出赔偿决定，应当充分听取赔偿请求人的意见，并可以与赔偿请求人就赔偿方式、赔偿项目和赔偿数额依照本法第四章的规定进行协商。\n赔偿义务机关决定赔偿的，应当制作赔偿决定书，并自作出决定之日起十日内送达赔偿请求人。\n赔偿义务机关决定不予赔偿的，应当自作出决定之日起十日内书面通知赔偿请求人，并说明不予赔偿的理由。\n第二十四条　赔偿义务机关在规定期限内未作出是否赔偿的决定，赔偿请求人可以自期限届满之日起三十日内向赔偿义务机关的上一级机关申请复议。\n赔偿请求人对赔偿的方式、项目、数额有异议的，或者赔偿义务机关作出不予赔偿决定的，赔偿请求人可以自赔偿义务机关作出赔偿或者不予赔偿决定之日起三十日内，向赔偿义务机关的上一级机关申请复议。\n赔偿义务机关是人民法院的，赔偿请求人可以依照本条规定向其上一级人民法院赔偿委员会申请作出赔偿决定。\n第二十五条　复议机关应当自收到申请之日起两个月内作出决定。\n赔偿请求人不服复议决定的，可以在收到复议决定之日起三十日内向复议机关所在地的同级人民法院赔偿委员会申请作出赔偿决定；复议机关逾期不作决定的，赔偿请求人可以自期限届满之日起三十日内向复议机关所在地的同级人民法院赔偿委员会申请作出赔偿决定。\n第二十六条　人民法院赔偿委员会处理赔偿请求，赔偿请求人和赔偿义务机关对自己提出的主张，应当提供证据。\n被羁押人在羁押期间死亡或者丧失行为能力的，赔偿义务机关的行为与被羁押人的死亡或者丧失行为能力是否存在因果关系，赔偿义务机关应当提供证据。\n第二十七条　人民法院赔偿委员会处理赔偿请求，采取书面审查的办法。必要时，可以向有关单位和人员调查情况、收集证据。赔偿请求人与赔偿义务机关对损害事实及因果关系有争议的，赔偿委员会可以听取赔偿请求人和赔偿义务机关的陈述和申辩，并可以进行质证。\n第二十八条　人民法院赔偿委员会应当自收到赔偿申请之日起三个月内作出决定；属于疑难、复杂、重大案件的，经本院院长批准，可以延长三个月。\n第二十九条　中级以上的人民法院设立赔偿委员会，由人民法院三名以上审判员组成，组成人员的人数应当为单数。\n赔偿委员会作赔偿决定，实行少数服从多数的原则。\n赔偿委员会作出的赔偿决定，是发生法律效力的决定，必须执行。\n第三十条　赔偿请求人或者赔偿义务机关对赔偿委员会作出的决定，认为确有错误的，可以向上一级人民法院赔偿委员会提出申诉。\n赔偿委员会作出的赔偿决定生效后，如发现赔偿决定违反本法规定的，经本院院长决定或者上级人民法院指令，赔偿委员会应当在两个月内重新审查并依法作出决定，上一级人民法院赔偿委员会也可以直接审查并作出决定。\n最高人民检察院对各级人民法院赔偿委员会作出的决定，上级人民检察院对下级人民法院赔偿委员会作出的决定，发现违反本法规定的，应当向同级人民法院赔偿委员会提出意见，同级人民法院赔偿委员会应当在两个月内重新审查并依法作出决定。\n第三十一条　赔偿义务机关赔偿后，应当向有下列情形之一的工作人员追偿部分或者全部赔偿费用：\n（一）有本法第十七条第四项、第五项规定情形的；\n（二）在处理案件中有贪污受贿，徇私舞弊，枉法裁判行为的。\n对有前款规定情形的责任人员，有关机关应当依法给予处分；构成犯罪的，应当依法追究刑事责任。\n第四章　赔偿方式和计算标准\n第三十二条　国家赔偿以支付赔偿金为主要方式。\n能够返还财产或者恢复原状的，予以返还财产或者恢复原状。\n第三十三条　侵犯公民人身自由的，每日赔偿金按照国家上年度职工日平均工资计算。\n第三十四条　侵犯公民生命健康权的，赔偿金按照下列规定计算：\n（一）造成身体伤害的，应当支付医疗费、护理费，以及赔偿因误工减少的收入。减少的收入每日的赔偿金按照国家上年度职工日平均工资计算，最高额为国家上年度职工年平均工资的五倍；\n（二）造成部分或者全部丧失劳动能力的，应当支付医疗费、护理费、残疾生活辅助具费、康复费等因残疾而增加的必要支出和继续治疗所必需的费用，以及残疾赔偿金。残疾赔偿金根据丧失劳动能力的程度，按照国家规定的伤残等级确定，最高不超过国家上年度职工年平均工资的二十倍。造成全部丧失劳动能力的，对其扶养的无劳动能力的人，还应当支付生活费；\n（三）造成死亡的，应当支付死亡赔偿金、丧葬费，总额为国家上年度职工年平均工资的二十倍。对死者生前扶养的无劳动能力的人，还应当支付生活费。\n前款第二项、第三项规定的生活费的发放标准，参照当地最低生活保障标准执行。被扶养的人是未成年人的，生活费给付至十八周岁止；其他无劳动能力的人，生活费给付至死亡时止。\n第三十五条　有本法第三条或者第十七条规定情形之一，致人精神损害的，应当在侵权行为影响的范围内，为受害人消除影响，恢复名誉，赔礼道歉；造成严重后果的，应当支付相应的精神损害抚慰金。\n第三十六条　侵犯公民、法人和其他组织的财产权造成损害的，按照下列规定处理：\n（一）处罚款、罚金、追缴、没收财产或者违法征收、征用财产的，返还财产；\n（二）查封、扣押、冻结财产的，解除对财产的查封、扣押、冻结，造成财产损坏或者灭失的，依照本条第三项、第四项的规定赔偿；\n（三）应当返还的财产损坏的，能够恢复原状的恢复原状，不能恢复原状的，按照损害程度给付相应的赔偿金；\n（四）应当返还的财产灭失的，给付相应的赔偿金；\n（五）财产已经拍卖或者变卖的，给付拍卖或者变卖所得的价款；变卖的价款明显低于财产价值的，应当支付相应的赔偿金；\n（六）吊销许可证和执照、责令停产停业的，赔偿停产停业期间必要的经常性费用开支；\n（七）返还执行的罚款或者罚金、追缴或者没收的金钱，解除冻结的存款或者汇款的，应当支付银行同期存款利息；\n（八）对财产权造成其他损害的，按照直接损失给予赔偿。\n第三十七条　赔偿费用列入各级财政预算。\n赔偿请求人凭生效的判决书、复议决定书、赔偿决定书或者调解书，向赔偿义务机关申请支付赔偿金。\n赔偿义务机关应当自收到支付赔偿金申请之日起七日内，依照预算管理权限向有关的财政部门提出支付申请，财政部门应当自收到支付申请之日起十五日内支付赔偿金。\n赔偿费用预算与支付管理的具体办法由国务院规定。\n第五章　其他规定\n第三十八条　人民法院在民事诉讼、行政诉讼过程中，违法采取对妨害诉讼的强制措施、保全措施或者对判决、裁定及其他生效法律文书执行错误，造成损害的，赔偿请求人要求赔偿的程序，适用本法刑事赔偿程序的规定。\n第三十九条　赔偿请求人请求国家赔偿的时效为两年，自其知道或者应当知道国家机关及其工作人员行使职权时的行为侵犯其人身权、财产权之日起计算，但被羁押等限制人身自由期间不计算在内。在申请行政复议或者提起行政诉讼时一并提出赔偿请求的，适用行政复议法、行政诉讼法有关时效的规定。\n赔偿请求人在赔偿请求时效的最后六个月内，因不可抗力或者其他障碍不能行使请求权的，时效中止。从中止时效的原因消除之日起，赔偿请求时效期间继续计算。\n第四十条　外国人、外国企业和组织在中华人民共和国领域内要求中华人民共和国国家赔偿的，适用本法。\n外国人、外国企业和组织的所属国对中华人民共和国公民、法人和其他组织要求该国国家赔偿的权利不予保护或者限制的，中华人民共和国与该外国人、外国企业和组织的所属国实行对等原则。\n第六章　附　　则\n第四十一条　赔偿请求人要求国家赔偿的，赔偿义务机关、复议机关和人民法院不得向赔偿请求人收取任何费用。\n对赔偿请求人取得的赔偿金不予征税。\n第四十二条　本法自1995年1月1日起施行。",
    "source": "npc"
  },
  {
    "title": "中华人民共和国专利法",
    "law_type": "法律",
    "publish_office": "全国人民代表大会常务委员会",
    "publish_date": "2020-10-17",
    "effective_date": "2021-06-01",
    "status": "现行有效",
    "bbbs": "ff808081752b7d430175e4651cbd1547",
    "url": "https://flk.npc.gov.cn/detail2.html?ff808081752b7d430175e4651cbd1547",
    "content": "中华人民共和国专利法\n（1984年3月12日第六届全国人民代表大会常务委员会第四次会议通过　根据1992年9月4日第七届全国人民代表大会常务委员会第二十七次会议《关于修改〈中华人民共和国专利法〉的决定》第一次修正　根据2000年8月25日第九届全国人民代表大会常务委员会第十七次会议《关于修改〈中华人民共和国专利法〉的决定》第二次修正　根据2008年12月27日第十一届全国人民代表大会常务委员会第六次会议《关于修改〈中华人民共和国专利法〉的决定》第三次修正　根据2020年10月17日第十三届全国人民代表大会常务委员会第二十二次会议《关于修改〈中华人民共和国专利法〉的决定》第四次修正）\n目　　录\n第一章　总　　则\n第二章　授予专利权的条件\n第三章　专利的申请\n第四章　专利申请的审查和批准\n第五章　专利权的期限、终止和无效\n第六章　专利实施的特别许可\n第七章　专利权的保护\n第八章　附　　则\n第一章　总　　则\n第一条　为了保护专利权人的合法权益，鼓励发明创造，推动发明创造的应用，提高创新能力，促进科学技术进步和经济社会发展，制定本法。\n第二条　本法所称的发明创造是指发明、实用新型和外观设计。\n发明，是指对产品、方法或者其改进所提出的新的技术方案。\n实用新型，是指对产品的形状、构造或者其结合所提出的适于实用的新的技术方案。\n外观设计，是指对产品的整体或者局部的形状、图案或者其结合以及色彩与形状、图案的结合所作出的富有美感并适于工业应用的新设计。\n第三条　国务院专利行政部门负责管理全国的专利工作；统一受理和审查专利申请，依法授予专利权。\n省、自治区、直辖市人民政府管理专利工作的部门负责本行政区域内的专利管理工作。\n第四条　申请专利的发明创造涉及国家安全或者重大利益需要保密的，按照国家有关规定办理。\n第五条　对违反法律、社会公德或者妨害公共利益的发明创造，不授予专利权。\n对违反法律、行政法规的规定获取或者利用遗传资源，并依赖该遗传资源完成的发明创造，不授予专利权。\n第六条　执行本单位的任务或者主要是利用本单位的物质技术条件所完成的发明创造为职务发明创造。职务发明创造申请专利的权利属于该单位，申请被批准后，该单位为专利权人。该单位可以依法处置其职务发明创造申请专利的权利和专利权，促进相关发明创造的实施和运用。\n非职务发明创造，申请专利的权利属于发明人或者设计人；申请被批准后，该发明人或者设计人为专利权人。\n利用本单位的物质技术条件所完成的发明创造，单位与发明人或者设计人订有合同，对申请专利的权利和专利权的归属作出约定的，从其约定。\n第七条　对发明人或者设计人的非职务发明创造专利申请，任何单位或者个人不得压制。\n第八条　两个以上单位或者个人合作完成的发明创造、一个单位或者个人接受其他单位或者个人委托所完成的发明创造，除另有协议的以外，申请专利的权利属于完成或者共同完成的单位或者个人；申请被批准后，申请的单位或者个人为专利权人。\n第九条　同样的发明创造只能授予一项专利权。但是，同一申请人同日对同样的发明创造既申请实用新型专利又申请发明专利，先获得的实用新型专利权尚未终止，且申请人声明放弃该实用新型专利权的，可以授予发明专利权。\n两个以上的申请人分别就同样的发明创造申请专利的，专利权授予最先申请的人。\n第十条　专利申请权和专利权可以转让。\n中国单位或者个人向外国人、外国企业或者外国其他组织转让专利申请权或者专利权的，应当依照有关法律、行政法规的规定办理手续。\n转让专利申请权或者专利权的，当事人应当订立书面合同，并向国务院专利行政部门登记，由国务院专利行政部门予以公告。专利申请权或者专利权的转让自登记之日起生效。\n第十一条　发明和实用新型专利权被授予后，除本法另有规定的以外，任何单位或者个人未经专利权人许可，都不得实施其专利，即不得为生产经营目的制造、使用、许诺销售、销售、进口其专利产品，或者使用其专利方法以及使用、许诺销售、销售、进口依照该专利方法直接获得的产品。\n外观设计专利权被授予后，任何单位或者个人未经专利权人许可，都不得实施其专利，即不得为生产经营目的制造、许诺销售、销售、进口其外观设计专利产品。\n第十二条　任何单位或者个人实施他人专利的，应当与专利权人订立实施许可合同，向专利权人支付专利使用费。被许可人无权允许合同规定以外的任何单位或者个人实施该专利。\n第十三条　发明专利申请公布后，申请人可以要求实施其发明的单位或者个人支付适当的费用。\n第十四条　专利申请权或者专利权的共有人对权利的行使有约定的，从其约定。没有约定的，共有人可以单独实施或者以普通许可方式许可他人实施该专利；许可他人实施该专利的，收取的使用费应当在共有人之间分配。\n除前款规定的情形外，行使共有的专利申请权或者专利权应当取得全体共有人的同意。\n第十五条　被授予专利权的单位应当对职务发明创造的发明人或者设计人给予奖励；发明创造专利实施后，根据其推广应用的范围和取得的经济效益，对发明人或者设计人给予合理的报酬。\n国家鼓励被授予专利权的单位实行产权激励，采取股权、期权、分红等方式，使发明人或者设计人合理分享创新收益。\n第十六条　发明人或者设计人有权在专利文件中写明自己是发明人或者设计人。\n专利权人有权在其专利产品或者该产品的包装上标明专利标识。\n第十七条　在中国没有经常居所或者营业所的外国人、外国企业或者外国其他组织在中国申请专利的，依照其所属国同中国签订的协议或者共同参加的国际条约，或者依照互惠原则，根据本法办理。\n第十八条　在中国没有经常居所或者营业所的外国人、外国企业或者外国其他组织在中国申请专利和办理其他专利事务的，应当委托依法设立的专利代理机构办理。\n中国单位或者个人在国内申请专利和办理其他专利事务的，可以委托依法设立的专利代理机构办理。\n专利代理机构应当遵守法律、行政法规，按照被代理人的委托办理专利申请或者其他专利事务；对被代理人发明创造的内容，除专利申请已经公布或者公告的以外，负有保密责任。专利代理机构的具体管理办法由国务院规定。\n第十九条　任何单位或者个人将在中国完成的发明或者实用新型向外国申请专利的，应当事先报经国务院专利行政部门进行保密审查。保密审查的程序、期限等按照国务院的规定执行。\n中国单位或者个人可以根据中华人民共和国参加的有关国际条约提出专利国际申请。申请人提出专利国际申请的，应当遵守前款规定。\n国务院专利行政部门依照中华人民共和国参加的有关国际条约、本法和国务院有关规定处理专利国际申请。\n对违反本条第一款规定向外国申请专利的发明或者实用新型，在中国申请专利的，不授予专利权。\n第二十条　申请专利和行使专利权应当遵循诚实信用原则。不得滥用专利权损害公共利益或者他人合法权益。\n滥用专利权，排除或者限制竞争，构成垄断行为的，依照《中华人民共和国反垄断法》处理。\n第二十一条　国务院专利行政部门应当按照客观、公正、准确、及时的要求，依法处理有关专利的申请和请求。\n国务院专利行政部门应当加强专利信息公共服务体系建设，完整、准确、及时发布专利信息，提供专利基础数据，定期出版专利公报，促进专利信息传播与利用。\n在专利申请公布或者公告前，国务院专利行政部门的工作人员及有关人员对其内容负有保密责任。\n第二章　授予专利权的条件\n第二十二条　授予专利权的发明和实用新型，应当具备新颖性、创造性和实用性。\n新颖性，是指该发明或者实用新型不属于现有技术；也没有任何单位或者个人就同样的发明或者实用新型在申请日以前向国务院专利行政部门提出过申请，并记载在申请日以后公布的专利申请文件或者公告的专利文件中。\n创造性，是指与现有技术相比，该发明具有突出的实质性特点和显著的进步，该实用新型具有实质性特点和进步。\n实用性，是指该发明或者实用新型能够制造或者使用，并且能够产生积极效果。\n本法所称现有技术，是指申请日以前在国内外为公众所知的技术。\n第二十三条　授予专利权的外观设计，应当不属于现有设计；也没有任何单位或者个人就同样的外观设计在申请日以前向国务院专利行政部门提出过申请，并记载在申请日以后公告的专利文件中。\n授予专利权的外观设计与现有设计或者现有设计特征的组合相比，应当具有明显区别。\n授予专利权的外观设计不得与他人在申请日以前已经取得的合法权利相冲突。\n本法所称现有设计，是指申请日以前在国内外为公众所知的设计。\n第二十四条　申请专利的发明创造在申请日以前六个月内，有下列情形之一的，不丧失新颖性：\n（一）在国家出现紧急状态或者非常情况时，为公共利益目的首次公开的；\n（二）在中国政府主办或者承认的国际展览会上首次展出的；\n（三）在规定的学术会议或者技术会议上首次发表的；\n（四）他人未经申请人同意而泄露其内容的。\n第二十五条　对下列各项，不授予专利权：\n（一）科学发现；\n（二）智力活动的规则和方法；\n（三）疾病的诊断和治疗方法；\n（四）动物和植物品种；\n（五）原子核变换方法以及用原子核变换方法获得的物质；\n（六）对平面印刷品的图案、色彩或者二者的结合作出的主要起标识作用的设计。\n对前款第（四）项所列产品的生产方法，可以依照本法规定授予专利权。\n第三章　专利的申请\n第二十六条　申请发明或者实用新型专利的，应当提交请求书、说明书及其摘要和权利要求书等文件。\n请求书应当写明发明或者实用新型的名称，发明人的姓名，申请人姓名或者名称、地址，以及其他事项。\n说明书应当对发明或者实用新型作出清楚、完整的说明，以所属技术领域的技术人员能够实现为准；必要的时候，应当有附图。摘要应当简要说明发明或者实用新型的技术要点。\n权利要求书应当以说明书为依据，清楚、简要地限定要求专利保护的范围。\n依赖遗传资源完成的发明创造，申请人应当在专利申请文件中说明该遗传资源的直接来源和原始来源；申请人无法说明原始来源的，应当陈述理由。\n第二十七条　申请外观设计专利的，应当提交请求书、该外观设计的图片或者照片以及对该外观设计的简要说明等文件。\n申请人提交的有关图片或者照片应当清楚地显示要求专利保护的产品的外观设计。\n第二十八条　国务院专利行政部门收到专利申请文件之日为申请日。如果申请文件是邮寄的，以寄出的邮戳日为申请日。\n第二十九条　申请人自发明或者实用新型在外国第一次提出专利申请之日起十二个月内，或者自外观设计在外国第一次提出专利申请之日起六个月内，又在中国就相同主题提出专利申请的，依照该外国同中国签订的协议或者共同参加的国际条约，或者依照相互承认优先权的原则，可以享有优先权。\n申请人自发明或者实用新型在中国第一次提出专利申请之日起十二个月内，或者自外观设计在中国第一次提出专利申请之日起六个月内，又向国务院专利行政部门就相同主题提出专利申请的，可以享有优先权。\n第三十条　申请人要求发明、实用新型专利优先权的，应当在申请的时候提出书面声明，并且在第一次提出申请之日起十六个月内，提交第一次提出的专利申请文件的副本。\n申请人要求外观设计专利优先权的，应当在申请的时候提出书面声明，并且在三个月内提交第一次提出的专利申请文件的副本。\n申请人未提出书面声明或者逾期未提交专利申请文件副本的，视为未要求优先权。\n第三十一条　一件发明或者实用新型专利申请应当限于一项发明或者实用新型。属于一个总的发明构思的两项以上的发明或者实用新型，可以作为一件申请提出。\n一件外观设计专利申请应当限于一项外观设计。同一产品两项以上的相似外观设计，或者用于同一类别并且成套出售或者使用的产品的两项以上外观设计，可以作为一件申请提出。\n第三十二条　申请人可以在被授予专利权之前随时撤回其专利申请。\n第三十三条　申请人可以对其专利申请文件进行修改，但是，对发明和实用新型专利申请文件的修改不得超出原说明书和权利要求书记载的范围，对外观设计专利申请文件的修改不得超出原图片或者照片表示的范围。\n第四章　专利申请的审查和批准\n第三十四条　国务院专利行政部门收到发明专利申请后，经初步审查认为符合本法要求的，自申请日起满十八个月，即行公布。国务院专利行政部门可以根据申请人的请求早日公布其申请。\n第三十五条　发明专利申请自申请日起三年内，国务院专利行政部门可以根据申请人随时提出的请求，对其申请进行实质审查；申请人无正当理由逾期不请求实质审查的，该申请即被视为撤回。\n国务院专利行政部门认为必要的时候，可以自行对发明专利申请进行实质审查。\n第三十六条　发明专利的申请人请求实质审查的时候，应当提交在申请日前与其发明有关的参考资料。\n发明专利已经在外国提出过申请的，国务院专利行政部门可以要求申请人在指定期限内提交该国为审查其申请进行检索的资料或者审查结果的资料；无正当理由逾期不提交的，该申请即被视为撤回。\n第三十七条　国务院专利行政部门对发明专利申请进行实质审查后，认为不符合本法规定的，应当通知申请人，要求其在指定的期限内陈述意见，或者对其申请进行修改；无正当理由逾期不答复的，该申请即被视为撤回。\n第三十八条　发明专利申请经申请人陈述意见或者进行修改后，国务院专利行政部门仍然认为不符合本法规定的，应当予以驳回。\n第三十九条　发明专利申请经实质审查没有发现驳回理由的，由国务院专利行政部门作出授予发明专利权的决定，发给发明专利证书，同时予以登记和公告。发明专利权自公告之日起生效。\n第四十条　实用新型和外观设计专利申请经初步审查没有发现驳回理由的，由国务院专利行政部门作出授予实用新型专利权或者外观设计专利权的决定，发给相应的专利证书，同时予以登记和公告。实用新型专利权和外观设计专利权自公告之日起生效。\n第四十一条　专利申请人对国务院专利行政部门驳回申请的决定不服的，可以自收到通知之日起三个月内向国务院专利行政部门请求复审。国务院专利行政部门复审后，作出决定，并通知专利申请人。\n专利申请人对国务院专利行政部门的复审决定不服的，可以自收到通知之日起三个月内向人民法院起诉。\n第五章　专利权的期限、终止和无效\n第四十二条　发明专利权的期限为二十年，实用新型专利权的期限为十年，外观设计专利权的期限为十五年，均自申请日起计算。\n自发明专利申请日起满四年，且自实质审查请求之日起满三年后授予发明专利权的，国务院专利行政部门应专利权人的请求，就发明专利在授权过程中的不合理延迟给予专利权期限补偿，但由申请人引起的不合理延迟除外。\n为补偿新药上市审评审批占用的时间，对在中国获得上市许可的新药相关发明专利，国务院专利行政部门应专利权人的请求给予专利权期限补偿。补偿期限不超过五年，新药批准上市后总有效专利权期限不超过十四年。\n第四十三条　专利权人应当自被授予专利权的当年开始缴纳年费。\n第四十四条　有下列情形之一的，专利权在期限届满前终止：\n（一）没有按照规定缴纳年费的；\n（二）专利权人以书面声明放弃其专利权的。\n专利权在期限届满前终止的，由国务院专利行政部门登记和公告。\n第四十五条　自国务院专利行政部门公告授予专利权之日起，任何单位或者个人认为该专利权的授予不符合本法有关规定的，可以请求国务院专利行政部门宣告该专利权无效。\n第四十六条　国务院专利行政部门对宣告专利权无效的请求应当及时审查和作出决定，并通知请求人和专利权人。宣告专利权无效的决定，由国务院专利行政部门登记和公告。\n对国务院专利行政部门宣告专利权无效或者维持专利权的决定不服的，可以自收到通知之日起三个月内向人民法院起诉。人民法院应当通知无效宣告请求程序的对方当事人作为第三人参加诉讼。\n第四十七条　宣告无效的专利权视为自始即不存在。\n宣告专利权无效的决定，对在宣告专利权无效前人民法院作出并已执行的专利侵权的判决、调解书，已经履行或者强制执行的专利侵权纠纷处理决定，以及已经履行的专利实施许可合同和专利权转让合同，不具有追溯力。但是因专利权人的恶意给他人造成的损失，应当给予赔偿。\n依照前款规定不返还专利侵权赔偿金、专利使用费、专利权转让费，明显违反公平原则的，应当全部或者部分返还。\n第六章　专利实施的特别许可\n第四十八条　国务院专利行政部门、地方人民政府管理专利工作的部门应当会同同级相关部门采取措施，加强专利公共服务，促进专利实施和运用。\n第四十九条　国有企业事业单位的发明专利，对国家利益或者公共利益具有重大意义的，国务院有关主管部门和省、自治区、直辖市人民政府报经国务院批准，可以决定在批准的范围内推广应用，允许指定的单位实施，由实施单位按照国家规定向专利权人支付使用费。\n第五十条　专利权人自愿以书面方式向国务院专利行政部门声明愿意许可任何单位或者个人实施其专利，并明确许可使用费支付方式、标准的，由国务院专利行政部门予以公告，实行开放许可。就实用新型、外观设计专利提出开放许可声明的，应当提供专利权评价报告。\n专利权人撤回开放许可声明的，应当以书面方式提出，并由国务院专利行政部门予以公告。开放许可声明被公告撤回的，不影响在先给予的开放许可的效力。\n第五十一条　任何单位或者个人有意愿实施开放许可的专利的，以书面方式通知专利权人，并依照公告的许可使用费支付方式、标准支付许可使用费后，即获得专利实施许可。\n开放许可实施期间，对专利权人缴纳专利年费相应给予减免。\n实行开放许可的专利权人可以与被许可人就许可使用费进行协商后给予普通许可，但不得就该专利给予独占或者排他许可。\n第五十二条　当事人就实施开放许可发生纠纷的，由当事人协商解决；不愿协商或者协商不成的，可以请求国务院专利行政部门进行调解，也可以向人民法院起诉。\n第五十三条　有下列情形之一的，国务院专利行政部门根据具备实施条件的单位或者个人的申请，可以给予实施发明专利或者实用新型专利的强制许可：\n（一）专利权人自专利权被授予之日起满三年，且自提出专利申请之日起满四年，无正当理由未实施或者未充分实施其专利的；\n（二）专利权人行使专利权的行为被依法认定为垄断行为，为消除或者减少该行为对竞争产生的不利影响的。\n第五十四条　在国家出现紧急状态或者非常情况时，或者为了公共利益的目的，国务院专利行政部门可以给予实施发明专利或者实用新型专利的强制许可。\n第五十五条　为了公共健康目的，对取得专利权的药品，国务院专利行政部门可以给予制造并将其出口到符合中华人民共和国参加的有关国际条约规定的国家或者地区的强制许可。\n第五十六条　一项取得专利权的发明或者实用新型比前已经取得专利权的发明或者实用新型具有显著经济意义的重大技术进步，其实施又有赖于前一发明或者实用新型的实施的，国务院专利行政部门根据后一专利权人的申请，可以给予实施前一发明或者实用新型的强制许可。\n在依照前款规定给予实施强制许可的情形下，国务院专利行政部门根据前一专利权人的申请，也可以给予实施后一发明或者实用新型的强制许可。\n第五十七条　强制许可涉及的发明创造为半导体技术的，其实施限于公共利益的目的和本法第五十三条第（二）项规定的情形。\n第五十八条　除依照本法第五十三条第（二）项、第五十五条规定给予的强制许可外，强制许可的实施应当主要为了供应国内市场。\n第五十九条　依照本法第五十三条第（一）项、第五十六条规定申请强制许可的单位或者个人应当提供证据，证明其以合理的条件请求专利权人许可其实施专利，但未能在合理的时间内获得许可。\n第六十条　国务院专利行政部门作出的给予实施强制许可的决定，应当及时通知专利权人，并予以登记和公告。\n给予实施强制许可的决定，应当根据强制许可的理由规定实施的范围和时间。强制许可的理由消除并不再发生时，国务院专利行政部门应当根据专利权人的请求，经审查后作出终止实施强制许可的决定。\n第六十一条　取得实施强制许可的单位或者个人不享有独占的实施权，并且无权允许他人实施。\n第六十二条　取得实施强制许可的单位或者个人应当付给专利权人合理的使用费，或者依照中华人民共和国参加的有关国际条约的规定处理使用费问题。付给使用费的，其数额由双方协商；双方不能达成协议的，由国务院专利行政部门裁决。\n第六十三条　专利权人对国务院专利行政部门关于实施强制许可的决定不服的，专利权人和取得实施强制许可的单位或者个人对国务院专利行政部门关于实施强制许可的使用费的裁决不服的，可以自收到通知之日起三个月内向人民法院起诉。\n第七章　专利权的保护\n第六十四条　发明或者实用新型专利权的保护范围以其权利要求的内容为准，说明书及附图可以用于解释权利要求的内容。\n外观设计专利权的保护范围以表示在图片或者照片中的该产品的外观设计为准，简要说明可以用于解释图片或者照片所表示的该产品的外观设计。\n第六十五条　未经专利权人许可，实施其专利，即侵犯其专利权，引起纠纷的，由当事人协商解决；不愿协商或者协商不成的，专利权人或者利害关系人可以向人民法院起诉，也可以请求管理专利工作的部门处理。管理专利工作的部门处理时，认定侵权行为成立的，可以责令侵权人立即停止侵权行为，当事人不服的，可以自收到处理通知之日起十五日内依照《中华人民共和国行政诉讼法》向人民法院起诉；侵权人期满不起诉又不停止侵权行为的，管理专利工作的部门可以申请人民法院强制执行。进行处理的管理专利工作的部门应当事人的请求，可以就侵犯专利权的赔偿数额进行调解；调解不成的，当事人可以依照《中华人民共和国民事诉讼法》向人民法院起诉。\n第六十六条　专利侵权纠纷涉及新产品制造方法的发明专利的，制造同样产品的单位或者个人应当提供其产品制造方法不同于专利方法的证明。\n专利侵权纠纷涉及实用新型专利或者外观设计专利的，人民法院或者管理专利工作的部门可以要求专利权人或者利害关系人出具由国务院专利行政部门对相关实用新型或者外观设计进行检索、分析和评价后作出的专利权评价报告，作为审理、处理专利侵权纠纷的证据；专利权人、利害关系人或者被控侵权人也可以主动出具专利权评价报告。\n第六十七条　在专利侵权纠纷中，被控侵权人有证据证明其实施的技术或者设计属于现有技术或者现有设计的，不构成侵犯专利权。\n第六十八条　假冒专利的，除依法承担民事责任外，由负责专利执法的部门责令改正并予公告，没收违法所得，可以处违法所得五倍以下的罚款；没有违法所得或者违法所得在五万元以下的，可以处二十五万元以下的罚款；构成犯罪的，依法追究刑事责任。\n第六十九条　负责专利执法的部门根据已经取得的证据，对涉嫌假冒专利行为进行查处时，有权采取下列措施：\n（一）询问有关当事人，调查与涉嫌违法行为有关的情况；\n（二）对当事人涉嫌违法行为的场所实施现场检查；\n（三）查阅、复制与涉嫌违法行为有关的合同、发票、账簿以及其他有关资料；\n（四）检查与涉嫌违法行为有关的产品；\n（五）对有证据证明是假冒专利的产品，可以查封或者扣押。\n管理专利工作的部门应专利权人或者利害关系人的请求处理专利侵权纠纷时，可以采取前款第（一）项、第（二）项、第（四）项所列措施。\n负责专利执法的部门、管理专利工作的部门依法行使前两款规定的职权时，当事人应当予以协助、配合，不得拒绝、阻挠。\n第七十条　国务院专利行政部门可以应专利权人或者利害关系人的请求处理在全国有重大影响的专利侵权纠纷。\n地方人民政府管理专利工作的部门应专利权人或者利害关系人请求处理专利侵权纠纷，对在本行政区域内侵犯其同一专利权的案件可以合并处理；对跨区域侵犯其同一专利权的案件可以请求上级地方人民政府管理专利工作的部门处理。\n第七十一条　侵犯专利权的赔偿数额按照权利人因被侵权所受到的实际损失或者侵权人因侵权所获得的利益确定；权利人的损失或者侵权人获得的利益难以确定的，参照该专利许可使用费的倍数合理确定。对故意侵犯专利权，情节严重的，可以在按照上述方法确定数额的一倍以上五倍以下确定赔偿数额。\n权利人的损失、侵权人获得的利益和专利许可使用费均难以确定的，人民法院可以根据专利权的类型、侵权行为的性质和情节等因素，确定给予三万元以上五百万元以下的赔偿。\n赔偿数额还应当包括权利人为制止侵权行为所支付的合理开支。\n人民法院为确定赔偿数额，在权利人已经尽力举证，而与侵权行为相关的账簿、资料主要由侵权人掌握的情况下，可以责令侵权人提供与侵权行为相关的账簿、资料；侵权人不提供或者提供虚假的账簿、资料的，人民法院可以参考权利人的主张和提供的证据判定赔偿数额。\n第七十二条　专利权人或者利害关系人有证据证明他人正在实施或者即将实施侵犯专利权、妨碍其实现权利的行为，如不及时制止将会使其合法权益受到难以弥补的损害的，可以在起诉前依法向人民法院申请采取财产保全、责令作出一定行为或者禁止作出一定行为的措施。\n第七十三条　为了制止专利侵权行为，在证据可能灭失或者以后难以取得的情况下，专利权人或者利害关系人可以在起诉前依法向人民法院申请保全证据。\n第七十四条　侵犯专利权的诉讼时效为三年，自专利权人或者利害关系人知道或者应当知道侵权行为以及侵权人之日起计算。\n发明专利申请公布后至专利权授予前使用该发明未支付适当使用费的，专利权人要求支付使用费的诉讼时效为三年，自专利权人知道或者应当知道他人使用其发明之日起计算，但是，专利权人于专利权授予之日前即已知道或者应当知道的，自专利权授予之日起计算。\n第七十五条　有下列情形之一的，不视为侵犯专利权：\n（一）专利产品或者依照专利方法直接获得的产品，由专利权人或者经其许可的单位、个人售出后，使用、许诺销售、销售、进口该产品的；\n（二）在专利申请日前已经制造相同产品、使用相同方法或者已经作好制造、使用的必要准备，并且仅在原有范围内继续制造、使用的；\n（三）临时通过中国领陆、领水、领空的外国运输工具，依照其所属国同中国签订的协议或者共同参加的国际条约，或者依照互惠原则，为运输工具自身需要而在其装置和设备中使用有关专利的；\n（四）专为科学研究和实验而使用有关专利的；\n（五）为提供行政审批所需要的信息，制造、使用、进口专利药品或者专利医疗器械的，以及专门为其制造、进口专利药品或者专利医疗器械的。\n第七十六条　药品上市审评审批过程中，药品上市许可申请人与有关专利权人或者利害关系人，因申请注册的药品相关的专利权产生纠纷的，相关当事人可以向人民法院起诉，请求就申请注册的药品相关技术方案是否落入他人药品专利权保护范围作出判决。国务院药品监督管理部门在规定的期限内，可以根据人民法院生效裁判作出是否暂停批准相关药品上市的决定。\n药品上市许可申请人与有关专利权人或者利害关系人也可以就申请注册的药品相关的专利权纠纷，向国务院专利行政部门请求行政裁决。\n国务院药品监督管理部门会同国务院专利行政部门制定药品上市许可审批与药品上市许可申请阶段专利权纠纷解决的具体衔接办法，报国务院同意后实施。\n第七十七条　为生产经营目的使用、许诺销售或者销售不知道是未经专利权人许可而制造并售出的专利侵权产品，能证明该产品合法来源的，不承担赔偿责任。\n第七十八条　违反本法第十九条规定向外国申请专利，泄露国家秘密的，由所在单位或者上级主管机关给予行政处分；构成犯罪的，依法追究刑事责任。\n第七十九条　管理专利工作的部门不得参与向社会推荐专利产品等经营活动。\n管理专利工作的部门违反前款规定的，由其上级机关或者监察机关责令改正，消除影响，有违法收入的予以没收；情节严重的，对直接负责的主管人员和其他直接责任人员依法给予处分。\n第八十条　从事专利管理工作的国家机关工作人员以及其他有关国家机关工作人员玩忽职守、滥用职权、徇私舞弊，构成犯罪的，依法追究刑事责任；尚不构成犯罪的，依法给予处分。\n第八章　附　　则\n第八十一条　向国务院专利行政部门申请专利和办理其他手续，应当按照规定缴纳费用。\n第八十二条　本法自1985年4月1日起施行。",
    "source": "npc"
  },
  {
    "title": "中华人民共和国商标法",
    "law_type": "法律",
    "publish_office": "全国人民代表大会常务委员会",
    "publish_date": "2019-04-23",
    "effective_date": "2019-11-01",
    "status": "现行有效",
    "bbbs": "ff8080816f135f46016f217645451b35",
    "url": "https://flk.npc.gov.cn/detail2.html?ff8080816f135f46016f217645451b35",
    "content": "中华人民共和国商标法\n（1982年8月23日第五届全国人民代表大会常务委员会第二十四次会议通过　根据1993年2月22日第七届全国人民代表大会常务委员会第三十次会议《关于修改〈中华人民共和国商标法〉的决定》第一次修正　根据2001年10月27日第九届全国人民代表大会常务委员会第二十四次会议《关于修改〈中华人民共和国商标法〉的决定》第二次修正　根据2013年8月30日第十二届全国人民代表大会常务委员会第四次会议《关于修改〈中华人民共和国商标法〉的决定》第三次修正　根据2019年4月23日第十三届全国人民代表大会常务委员会第十次会议《关于修改〈中华人民共和国建筑法〉等八部法律的决定》第四次修正）\n目　　录\n第一章　总　　则\n第二章　商标注册的申请\n第三章　商标注册的审查和核准\n第四章　注册商标的续展、变更、转让和使用许可\n第五章　注册商标的无效宣告\n第六章　商标使用的管理\n第七章　注册商标专用权的保护\n第八章　附　　则\n第一章　总　　则\n第一条　为了加强商标管理，保护商标专用权，促使生产、经营者保证商品和服务质量，维护商标信誉，以保障消费者和生产、经营者的利益，促进社会主义市场经济的发展，特制定本法。\n第二条　国务院工商行政管理部门商标局主管全国商标注册和管理的工作。\n国务院工商行政管理部门设立商标评审委员会，负责处理商标争议事宜。\n第三条　经商标局核准注册的商标为注册商标，包括商品商标、服务商标和集体商标、证明商标；商标注册人享有商标专用权，受法律保护。\n本法所称集体商标，是指以团体、协会或者其他组织名义注册，供该组织成员在商事活动中使用，以表明使用者在该组织中的成员资格的标志。\n本法所称证明商标，是指由对某种商品或者服务具有监督能力的组织所控制，而由该组织以外的单位或者个人使用于其商品或者服务，用以证明该商品或者服务的原产地、原料、制造方法、质量或者其他特定品质的标志。\n集体商标、证明商标注册和管理的特殊事项，由国务院工商行政管理部门规定。\n第四条　自然人、法人或者其他组织在生产经营活动中，对其商品或者服务需要取得商标专用权的，应当向商标局申请商标注册。不以使用为目的的恶意商标注册申请，应当予以驳回。\n本法有关商品商标的规定，适用于服务商标。\n第五条　两个以上的自然人、法人或者其他组织可以共同向商标局申请注册同一商标，共同享有和行使该商标专用权。\n第六条　法律、行政法规规定必须使用注册商标的商品，必须申请商标注册，未经核准注册的，不得在市场销售。\n第七条　申请注册和使用商标，应当遵循诚实信用原则。\n商标使用人应当对其使用商标的商品质量负责。各级工商行政管理部门应当通过商标管理，制止欺骗消费者的行为。\n第八条　任何能够将自然人、法人或者其他组织的商品与他人的商品区别开的标志，包括文字、图形、字母、数字、三维标志、颜色组合和声音等，以及上述要素的组合，均可以作为商标申请注册。\n第九条　申请注册的商标，应当有显著特征，便于识别，并不得与他人在先取得的合法权利相冲突。\n商标注册人有权标明“注册商标”或者注册标记。\n第十条　下列标志不得作为商标使用：\n（一）同中华人民共和国的国家名称、国旗、国徽、国歌、军旗、军徽、军歌、勋章等相同或者近似的，以及同中央国家机关的名称、标志、所在地特定地点的名称或者标志性建筑物的名称、图形相同的；\n（二）同外国的国家名称、国旗、国徽、军旗等相同或者近似的，但经该国政府同意的除外；\n（三）同政府间国际组织的名称、旗帜、徽记等相同或者近似的，但经该组织同意或者不易误导公众的除外；\n（四）与表明实施控制、予以保证的官方标志、检验印记相同或者近似的，但经授权的除外；\n（五）同“红十字”、“红新月”的名称、标志相同或者近似的；\n（六）带有民族歧视性的；\n（七）带有欺骗性，容易使公众对商品的质量等特点或者产地产生误认的；\n（八）有害于社会主义道德风尚或者有其他不良影响的。\n县级以上行政区划的地名或者公众知晓的外国地名，不得作为商标。但是，地名具有其他含义或者作为集体商标、证明商标组成部分的除外；已经注册的使用地名的商标继续有效。\n第十一条　下列标志不得作为商标注册：\n（一）仅有本商品的通用名称、图形、型号的；\n（二）仅直接表示商品的质量、主要原料、功能、用途、重量、数量及其他特点的；\n（三）其他缺乏显著特征的。\n前款所列标志经过使用取得显著特征，并便于识别的，可以作为商标注册。\n第十二条　以三维标志申请注册商标的，仅由商品自身的性质产生的形状、为获得技术效果而需有的商品形状或者使商品具有实质性价值的形状，不得注册。\n第十三条　为相关公众所熟知的商标，持有人认为其权利受到侵害时，可以依照本法规定请求驰名商标保护。\n就相同或者类似商品申请注册的商标是复制、摹仿或者翻译他人未在中国注册的驰名商标，容易导致混淆的，不予注册并禁止使用。\n就不相同或者不相类似商品申请注册的商标是复制、摹仿或者翻译他人已经在中国注册的驰名商标，误导公众，致使该驰名商标注册人的利益可能受到损害的，不予注册并禁止使用。\n第十四条　驰名商标应当根据当事人的请求，作为处理涉及商标案件需要认定的事实进行认定。认定驰名商标应当考虑下列因素：\n（一）相关公众对该商标的知晓程度；\n（二）该商标使用的持续时间；\n（三）该商标的任何宣传工作的持续时间、程度和地理范围；\n（四）该商标作为驰名商标受保护的记录；\n（五）该商标驰名的其他因素。\n在商标注册审查、工商行政管理部门查处商标违法案件过程中，当事人依照本法第十三条规定主张权利的，商标局根据审查、处理案件的需要，可以对商标驰名情况作出认定。\n在商标争议处理过程中，当事人依照本法第十三条规定主张权利的，商标评审委员会根据处理案件的需要，可以对商标驰名情况作出认定。\n在商标民事、行政案件审理过程中，当事人依照本法第十三条规定主张权利的，最高人民法院指定的人民法院根据审理案件的需要，可以对商标驰名情况作出认定。\n生产、经营者不得将“驰名商标”字样用于商品、商品包装或者容器上，或者用于广告宣传、展览以及其他商业活动中。\n第十五条　未经授权，代理人或者代表人以自己的名义将被代理人或者被代表人的商标进行注册，被代理人或者被代表人提出异议的，不予注册并禁止使用。\n就同一种商品或者类似商品申请注册的商标与他人在先使用的未注册商标相同或者近似，申请人与该他人具有前款规定以外的合同、业务往来关系或者其他关系而明知该他人商标存在，该他人提出异议的，不予注册。\n第十六条　商标中有商品的地理标志，而该商品并非来源于该标志所标示的地区，误导公众的，不予注册并禁止使用；但是，已经善意取得注册的继续有效。\n前款所称地理标志，是指标示某商品来源于某地区，该商品的特定质量、信誉或者其他特征，主要由该地区的自然因素或者人文因素所决定的标志。\n第十七条　外国人或者外国企业在中国申请商标注册的，应当按其所属国和中华人民共和国签订的协议或者共同参加的国际条约办理，或者按对等原则办理。\n第十八条　申请商标注册或者办理其他商标事宜，可以自行办理，也可以委托依法设立的商标代理机构办理。\n外国人或者外国企业在中国申请商标注册和办理其他商标事宜的，应当委托依法设立的商标代理机构办理。\n第十九条　商标代理机构应当遵循诚实信用原则，遵守法律、行政法规，按照被代理人的委托办理商标注册申请或者其他商标事宜；对在代理过程中知悉的被代理人的商业秘密，负有保密义务。\n委托人申请注册的商标可能存在本法规定不得注册情形的，商标代理机构应当明确告知委托人。\n商标代理机构知道或者应当知道委托人申请注册的商标属于本法第四条、第十五条和第三十二条规定情形的，不得接受其委托。\n商标代理机构除对其代理服务申请商标注册外，不得申请注册其他商标。\n第二十条　商标代理行业组织应当按照章程规定，严格执行吸纳会员的条件，对违反行业自律规范的会员实行惩戒。商标代理行业组织对其吸纳的会员和对会员的惩戒情况，应当及时向社会公布。\n第二十一条　商标国际注册遵循中华人民共和国缔结或者参加的有关国际条约确立的制度，具体办法由国务院规定。\n第二章　商标注册的申请\n第二十二条　商标注册申请人应当按规定的商品分类表填报使用商标的商品类别和商品名称，提出注册申请。\n商标注册申请人可以通过一份申请就多个类别的商品申请注册同一商标。\n商标注册申请等有关文件，可以以书面方式或者数据电文方式提出。\n第二十三条　注册商标需要在核定使用范围之外的商品上取得商标专用权的，应当另行提出注册申请。\n第二十四条　注册商标需要改变其标志的，应当重新提出注册申请。\n第二十五条　商标注册申请人自其商标在外国第一次提出商标注册申请之日起六个月内，又在中国就相同商品以同一商标提出商标注册申请的，依照该外国同中国签订的协议或者共同参加的国际条约，或者按照相互承认优先权的原则，可以享有优先权。\n依照前款要求优先权的，应当在提出商标注册申请的时候提出书面声明，并且在三个月内提交第一次提出的商标注册申请文件的副本；未提出书面声明或者逾期未提交商标注册申请文件副本的，视为未要求优先权。\n第二十六条　商标在中国政府主办的或者承认的国际展览会展出的商品上首次使用的，自该商品展出之日起六个月内，该商标的注册申请人可以享有优先权。\n依照前款要求优先权的，应当在提出商标注册申请的时候提出书面声明，并且在三个月内提交展出其商品的展览会名称、在展出商品上使用该商标的证据、展出日期等证明文件；未提出书面声明或者逾期未提交证明文件的，视为未要求优先权。\n第二十七条　为申请商标注册所申报的事项和所提供的材料应当真实、准确、完整。\n第三章　商标注册的审查和核准\n第二十八条　对申请注册的商标，商标局应当自收到商标注册申请文件之日起九个月内审查完毕，符合本法有关规定的，予以初步审定公告。\n第二十九条　在审查过程中，商标局认为商标注册申请内容需要说明或者修正的，可以要求申请人做出说明或者修正。申请人未做出说明或者修正的，不影响商标局做出审查决定。\n第三十条　申请注册的商标，凡不符合本法有关规定或者同他人在同一种商品或者类似商品上已经注册的或者初步审定的商标相同或者近似的，由商标局驳回申请，不予公告。\n第三十一条　两个或者两个以上的商标注册申请人，在同一种商品或者类似商品上，以相同或者近似的商标申请注册的，初步审定并公告申请在先的商标；同一天申请的，初步审定并公告使用在先的商标，驳回其他人的申请，不予公告。\n第三十二条　申请商标注册不得损害他人现有的在先权利，也不得以不正当手段抢先注册他人已经使用并有一定影响的商标。\n第三十三条　对初步审定公告的商标，自公告之日起三个月内，在先权利人、利害关系人认为违反本法第十三条第二款和第三款、第十五条、第十六条第一款、第三十条、第三十一条、第三十二条规定的，或者任何人认为违反本法第四条、第十条、第十一条、第十二条、第十九条第四款规定的，可以向商标局提出异议。公告期满无异议的，予以核准注册，发给商标注册证，并予公告。\n第三十四条　对驳回申请、不予公告的商标，商标局应当书面通知商标注册申请人。商标注册申请人不服的，可以自收到通知之日起十五日内向商标评审委员会申请复审。商标评审委员会应当自收到申请之日起九个月内做出决定，并书面通知申请人。有特殊情况需要延长的，经国务院工商行政管理部门批准，可以延长三个月。当事人对商标评审委员会的决定不服的，可以自收到通知之日起三十日内向人民法院起诉。\n第三十五条　对初步审定公告的商标提出异议的，商标局应当听取异议人和被异议人陈述事实和理由，经调查核实后，自公告期满之日起十二个月内做出是否准予注册的决定，并书面通知异议人和被异议人。有特殊情况需要延长的，经国务院工商行政管理部门批准，可以延长六个月。\n商标局做出准予注册决定的，发给商标注册证，并予公告。异议人不服的，可以依照本法第四十四条、第四十五条的规定向商标评审委员会请求宣告该注册商标无效。\n商标局做出不予注册决定，被异议人不服的，可以自收到通知之日起十五日内向商标评审委员会申请复审。商标评审委员会应当自收到申请之日起十二个月内做出复审决定，并书面通知异议人和被异议人。有特殊情况需要延长的，经国务院工商行政管理部门批准，可以延长六个月。被异议人对商标评审委员会的决定不服的，可以自收到通知之日起三十日内向人民法院起诉。人民法院应当通知异议人作为第三人参加诉讼。\n商标评审委员会在依照前款规定进行复审的过程中，所涉及的在先权利的确定必须以人民法院正在审理或者行政机关正在处理的另一案件的结果为依据的，可以中止审查。中止原因消除后，应当恢复审查程序。\n第三十六条　法定期限届满，当事人对商标局做出的驳回申请决定、不予注册决定不申请复审或者对商标评审委员会做出的复审决定不向人民法院起诉的，驳回申请决定、不予注册决定或者复审决定生效。\n经审查异议不成立而准予注册的商标，商标注册申请人取得商标专用权的时间自初步审定公告三个月期满之日起计算。自该商标公告期满之日起至准予注册决定做出前，对他人在同一种或者类似商品上使用与该商标相同或者近似的标志的行为不具有追溯力；但是，因该使用人的恶意给商标注册人造成的损失，应当给予赔偿。\n第三十七条　对商标注册申请和商标复审申请应当及时进行审查。\n第三十八条　商标注册申请人或者注册人发现商标申请文件或者注册文件有明显错误的，可以申请更正。商标局依法在其职权范围内作出更正，并通知当事人。\n前款所称更正错误不涉及商标申请文件或者注册文件的实质性内容。\n第四章　注册商标的续展、变更、转让和使用许可\n第三十九条　注册商标的有效期为十年，自核准注册之日起计算。\n第四十条　注册商标有效期满，需要继续使用的，商标注册人应当在期满前十二个月内按照规定办理续展手续；在此期间未能办理的，可以给予六个月的宽展期。每次续展注册的有效期为十年，自该商标上一届有效期满次日起计算。期满未办理续展手续的，注销其注册商标。\n商标局应当对续展注册的商标予以公告。\n第四十一条　注册商标需要变更注册人的名义、地址或者其他注册事项的，应当提出变更申请。\n第四十二条　转让注册商标的，转让人和受让人应当签订转让协议，并共同向商标局提出申请。受让人应当保证使用该注册商标的商品质量。\n转让注册商标的，商标注册人对其在同一种商品上注册的近似的商标，或者在类似商品上注册的相同或者近似的商标，应当一并转让。\n对容易导致混淆或者有其他不良影响的转让，商标局不予核准，书面通知申请人并说明理由。\n转让注册商标经核准后，予以公告。受让人自公告之日起享有商标专用权。\n第四十三条　商标注册人可以通过签订商标使用许可合同，许可他人使用其注册商标。许可人应当监督被许可人使用其注册商标的商品质量。被许可人应当保证使用该注册商标的商品质量。\n经许可使用他人注册商标的，必须在使用该注册商标的商品上标明被许可人的名称和商品产地。\n许可他人使用其注册商标的，许可人应当将其商标使用许可报商标局备案，由商标局公告。商标使用许可未经备案不得对抗善意第三人。\n第五章　注册商标的无效宣告\n第四十四条　已经注册的商标，违反本法第四条、第十条、第十一条、第十二条、第十九条第四款规定的，或者是以欺骗手段或者其他不正当手段取得注册的，由商标局宣告该注册商标无效；其他单位或者个人可以请求商标评审委员会宣告该注册商标无效。\n商标局做出宣告注册商标无效的决定，应当书面通知当事人。当事人对商标局的决定不服的，可以自收到通知之日起十五日内向商标评审委员会申请复审。商标评审委员会应当自收到申请之日起九个月内做出决定，并书面通知当事人。有特殊情况需要延长的，经国务院工商行政管理部门批准，可以延长三个月。当事人对商标评审委员会的决定不服的，可以自收到通知之日起三十日内向人民法院起诉。\n其他单位或者个人请求商标评审委员会宣告注册商标无效的，商标评审委员会收到申请后，应当书面通知有关当事人，并限期提出答辩。商标评审委员会应当自收到申请之日起九个月内做出维持注册商标或者宣告注册商标无效的裁定，并书面通知当事人。有特殊情况需要延长的，经国务院工商行政管理部门批准，可以延长三个月。当事人对商标评审委员会的裁定不服的，可以自收到通知之日起三十日内向人民法院起诉。人民法院应当通知商标裁定程序的对方当事人作为第三人参加诉讼。\n第四十五条　已经注册的商标，违反本法第十三条第二款和第三款、第十五条、第十六条第一款、第三十条、第三十一条、第三十二条规定的，自商标注册之日起五年内，在先权利人或者利害关系人可以请求商标评审委员会宣告该注册商标无效。对恶意注册的，驰名商标所有人不受五年的时间限制。\n商标评审委员会收到宣告注册商标无效的申请后，应当书面通知有关当事人，并限期提出答辩。商标评审委员会应当自收到申请之日起十二个月内做出维持注册商标或者宣告注册商标无效的裁定，并书面通知当事人。有特殊情况需要延长的，经国务院工商行政管理部门批准，可以延长六个月。当事人对商标评审委员会的裁定不服的，可以自收到通知之日起三十日内向人民法院起诉。人民法院应当通知商标裁定程序的对方当事人作为第三人参加诉讼。\n商标评审委员会在依照前款规定对无效宣告请求进行审查的过程中，所涉及的在先权利的确定必须以人民法院正在审理或者行政机关正在处理的另一案件的结果为依据的，可以中止审查。中止原因消除后，应当恢复审查程序。\n第四十六条　法定期限届满，当事人对商标局宣告注册商标无效的决定不申请复审或者对商标评审委员会的复审决定、维持注册商标或者宣告注册商标无效的裁定不向人民法院起诉的，商标局的决定或者商标评审委员会的复审决定、裁定生效。\n第四十七条　依照本法第四十四条、第四十五条的规定宣告无效的注册商标，由商标局予以公告，该注册商标专用权视为自始即不存在。\n宣告注册商标无效的决定或者裁定，对宣告无效前人民法院做出并已执行的商标侵权案件的判决、裁定、调解书和工商行政管理部门做出并已执行的商标侵权案件的处理决定以及已经履行的商标转让或者使用许可合同不具有追溯力。但是，因商标注册人的恶意给他人造成的损失，应当给予赔偿。\n依照前款规定不返还商标侵权赔偿金、商标转让费、商标使用费，明显违反公平原则的，应当全部或者部分返还。\n第六章　商标使用的管理\n第四十八条　本法所称商标的使用，是指将商标用于商品、商品包装或者容器以及商品交易文书上，或者将商标用于广告宣传、展览以及其他商业活动中，用于识别商品来源的行为。\n第四十九条　商标注册人在使用注册商标的过程中，自行改变注册商标、注册人名义、地址或者其他注册事项的，由地方工商行政管理部门责令限期改正；期满不改正的，由商标局撤销其注册商标。\n注册商标成为其核定使用的商品的通用名称或者没有正当理由连续三年不使用的，任何单位或者个人可以向商标局申请撤销该注册商标。商标局应当自收到申请之日起九个月内做出决定。有特殊情况需要延长的，经国务院工商行政管理部门批准，可以延长三个月。\n第五十条　注册商标被撤销、被宣告无效或者期满不再续展的，自撤销、宣告无效或者注销之日起一年内，商标局对与该商标相同或者近似的商标注册申请，不予核准。\n第五十一条　违反本法第六条规定的，由地方工商行政管理部门责令限期申请注册，违法经营额五万元以上的，可以处违法经营额百分之二十以下的罚款，没有违法经营额或者违法经营额不足五万元的，可以处一万元以下的罚款。\n第五十二条　将未注册商标冒充注册商标使用的，或者使用未注册商标违反本法第十条规定的，由地方工商行政管理部门予以制止，限期改正，并可以予以通报，违法经营额五万元以上的，可以处违法经营额百分之二十以下的罚款，没有违法经营额或者违法经营额不足五万元的，可以处一万元以下的罚款。\n第五十三条　违反本法第十四条第五款规定的，由地方工商行政管理部门责令改正，处十万元罚款。\n第五十四条　对商标局撤销或者不予撤销注册商标的决定，当事人不服的，可以自收到通知之日起十五日内向商标评审委员会申请复审。商标评审委员会应当自收到申请之日起九个月内做出决定，并书面通知当事人。有特殊情况需要延长的，经国务院工商行政管理部门批准，可以延长三个月。当事人对商标评审委员会的决定不服的，可以自收到通知之日起三十日内向人民法院起诉。\n第五十五条　法定期限届满，当事人对商标局做出的撤销注册商标的决定不申请复审或者对商标评审委员会做出的复审决定不向人民法院起诉的，撤销注册商标的决定、复审决定生效。\n被撤销的注册商标，由商标局予以公告，该注册商标专用权自公告之日起终止。\n第七章　注册商标专用权的保护\n第五十六条　注册商标的专用权，以核准注册的商标和核定使用的商品为限。\n第五十七条　有下列行为之一的，均属侵犯注册商标专用权：\n（一）未经商标注册人的许可，在同一种商品上使用与其注册商标相同的商标的；\n（二）未经商标注册人的许可，在同一种商品上使用与其注册商标近似的商标，或者在类似商品上使用与其注册商标相同或者近似的商标，容易导致混淆的；\n（三）销售侵犯注册商标专用权的商品的；\n（四）伪造、擅自制造他人注册商标标识或者销售伪造、擅自制造的注册商标标识的；\n（五）未经商标注册人同意，更换其注册商标并将该更换商标的商品又投入市场的；\n（六）故意为侵犯他人商标专用权行为提供便利条件，帮助他人实施侵犯商标专用权行为的；\n（七）给他人的注册商标专用权造成其他损害的。\n第五十八条　将他人注册商标、未注册的驰名商标作为企业名称中的字号使用，误导公众，构成不正当竞争行为的，依照《中华人民共和国反不正当竞争法》处理。\n第五十九条　注册商标中含有的本商品的通用名称、图形、型号，或者直接表示商品的质量、主要原料、功能、用途、重量、数量及其他特点，或者含有的地名，注册商标专用权人无权禁止他人正当使用。\n三维标志注册商标中含有的商品自身的性质产生的形状、为获得技术效果而需有的商品形状或者使商品具有实质性价值的形状，注册商标专用权人无权禁止他人正当使用。\n商标注册人申请商标注册前，他人已经在同一种商品或者类似商品上先于商标注册人使用与注册商标相同或者近似并有一定影响的商标的，注册商标专用权人无权禁止该使用人在原使用范围内继续使用该商标，但可以要求其附加适当区别标识。\n第六十条　有本法第五十七条所列侵犯注册商标专用权行为之一，引起纠纷的，由当事人协商解决；不愿协商或者协商不成的，商标注册人或者利害关系人可以向人民法院起诉，也可以请求工商行政管理部门处理。\n工商行政管理部门处理时，认定侵权行为成立的，责令立即停止侵权行为，没收、销毁侵权商品和主要用于制造侵权商品、伪造注册商标标识的工具，违法经营额五万元以上的，可以处违法经营额五倍以下的罚款，没有违法经营额或者违法经营额不足五万元的，可以处二十五万元以下的罚款。对五年内实施两次以上商标侵权行为或者有其他严重情节的，应当从重处罚。销售不知道是侵犯注册商标专用权的商品，能证明该商品是自己合法取得并说明提供者的，由工商行政管理部门责令停止销售。\n对侵犯商标专用权的赔偿数额的争议，当事人可以请求进行处理的工商行政管理部门调解，也可以依照《中华人民共和国民事诉讼法》向人民法院起诉。经工商行政管理部门调解，当事人未达成协议或者调解书生效后不履行的，当事人可以依照《中华人民共和国民事诉讼法》向人民法院起诉。\n第六十一条　对侵犯注册商标专用权的行为，工商行政管理部门有权依法查处；涉嫌犯罪的，应当及时移送司法机关依法处理。\n第六十二条　县级以上工商行政管理部门根据已经取得的违法嫌疑证据或者举报，对涉嫌侵犯他人注册商标专用权的行为进行查处时，可以行使下列职权：\n（一）询问有关当事人，调查与侵犯他人注册商标专用权有关的情况；\n（二）查阅、复制当事人与侵权活动有关的合同、发票、账簿以及其他有关资料；\n（三）对当事人涉嫌从事侵犯他人注册商标专用权活动的场所实施现场检查；\n（四）检查与侵权活动有关的物品；对有证据证明是侵犯他人注册商标专用权的物品，可以查封或者扣押。\n工商行政管理部门依法行使前款规定的职权时，当事人应当予以协助、配合，不得拒绝、阻挠。\n在查处商标侵权案件过程中，对商标权属存在争议或者权利人同时向人民法院提起商标侵权诉讼的，工商行政管理部门可以中止案件的查处。中止原因消除后，应当恢复或者终结案件查处程序。\n第六十三条　侵犯商标专用权的赔偿数额，按照权利人因被侵权所受到的实际损失确定；实际损失难以确定的，可以按照侵权人因侵权所获得的利益确定；权利人的损失或者侵权人获得的利益难以确定的，参照该商标许可使用费的倍数合理确定。对恶意侵犯商标专用权，情节严重的，可以在按照上述方法确定数额的一倍以上五倍以下确定赔偿数额。赔偿数额应当包括权利人为制止侵权行为所支付的合理开支。\n人民法院为确定赔偿数额，在权利人已经尽力举证，而与侵权行为相关的账簿、资料主要由侵权人掌握的情况下，可以责令侵权人提供与侵权行为相关的账簿、资料；侵权人不提供或者提供虚假的账簿、资料的，人民法院可以参考权利人的主张和提供的证据判定赔偿数额。\n权利人因被侵权所受到的实际损失、侵权人因侵权所获得的利益、注册商标许可使用费难以确定的，由人民法院根据侵权行为的情节判决给予五百万元以下的赔偿。\n人民法院审理商标纠纷案件，应权利人请求，对属于假冒注册商标的商品，除特殊情况外，责令销毁；对主要用于制造假冒注册商标的商品的材料、工具，责令销毁，且不予补偿；或者在特殊情况下，责令禁止前述材料、工具进入商业渠道，且不予补偿。\n假冒注册商标的商品不得在仅去除假冒注册商标后进入商业渠道。\n第六十四条　注册商标专用权人请求赔偿，被控侵权人以注册商标专用权人未使用注册商标提出抗辩的，人民法院可以要求注册商标专用权人提供此前三年内实际使用该注册商标的证据。注册商标专用权人不能证明此前三年内实际使用过该注册商标，也不能证明因侵权行为受到其他损失的，被控侵权人不承担赔偿责任。\n销售不知道是侵犯注册商标专用权的商品，能证明该商品是自己合法取得并说明提供者的，不承担赔偿责任。\n第六十五条　商标注册人或者利害关系人有证据证明他人正在实施或者即将实施侵犯其注册商标专用权的行为，如不及时制止将会使其合法权益受到难以弥补的损害的，可以依法在起诉前向人民法院申请采取责令停止有关行为和财产保全的措施。\n第六十六条　为制止侵权行为，在证据可能灭失或者以后难以取得的情况下，商标注册人或者利害关系人可以依法在起诉前向人民法院申请保全证据。\n第六十七条　未经商标注册人许可，在同一种商品上使用与其注册商标相同的商标，构成犯罪的，除赔偿被侵权人的损失外，依法追究刑事责任。\n伪造、擅自制造他人注册商标标识或者销售伪造、擅自制造的注册商标标识，构成犯罪的，除赔偿被侵权人的损失外，依法追究刑事责任。\n销售明知是假冒注册商标的商品，构成犯罪的，除赔偿被侵权人的损失外，依法追究刑事责任。\n第六十八条　商标代理机构有下列行为之一的，由工商行政管理部门责令限期改正，给予警告，处一万元以上十万元以下的罚款；对直接负责的主管人员和其他直接责任人员给予警告，处五千元以上五万元以下的罚款；构成犯罪的，依法追究刑事责任：\n（一）办理商标事宜过程中，伪造、变造或者使用伪造、变造的法律文件、印章、签名的；\n（二）以诋毁其他商标代理机构等手段招徕商标代理业务或者以其他不正当手段扰乱商标代理市场秩序的；\n（三）违反本法第四条、第十九条第三款和第四款规定的。\n商标代理机构有前款规定行为的，由工商行政管理部门记入信用档案；情节严重的，商标局、商标评审委员会并可以决定停止受理其办理商标代理业务，予以公告。\n商标代理机构违反诚实信用原则，侵害委托人合法利益的，应当依法承担民事责任，并由商标代理行业组织按照章程规定予以惩戒。\n对恶意申请商标注册的，根据情节给予警告、罚款等行政处罚；对恶意提起商标诉讼的，由人民法院依法给予处罚。\n第六十九条　从事商标注册、管理和复审工作的国家机关工作人员必须秉公执法，廉洁自律，忠于职守，文明服务。\n商标局、商标评审委员会以及从事商标注册、管理和复审工作的国家机关工作人员不得从事商标代理业务和商品生产经营活动。\n第七十条　工商行政管理部门应当建立健全内部监督制度，对负责商标注册、管理和复审工作的国家机关工作人员执行法律、行政法规和遵守纪律的情况，进行监督检查。\n第七十一条　从事商标注册、管理和复审工作的国家机关工作人员玩忽职守、滥用职权、徇私舞弊，违法办理商标注册、管理和复审事项，收受当事人财物，牟取不正当利益，构成犯罪的，依法追究刑事责任；尚不构成犯罪的，依法给予处分。\n第八章　附　　则\n第七十二条　申请商标注册和办理其他商标事宜的，应当缴纳费用，具体收费标准另定。\n第七十三条　本法自1983年3月1日起施行。1963年4月10日国务院公布的《商标管理条例》同时废止；其他有关商标管理的规定，凡与本法抵触的，同时失效。\n本法施行前已经注册的商标继续有效。",
    "source": "npc"
  },
  {
    "title": "中华人民共和国著作权法",
    "law_type": "法律",
    "publish_office": "全国人民代表大会常务委员会",
    "publish_date": "2020-11-11",
    "effective_date": "2021-06-01",
    "status": "现行有效",
    "bbbs": "ff808081752b7d430175e4766bab1557",
    "url": "https://flk.npc.gov.cn/detail2.html?ff808081752b7d430175e4766bab1557",
    "content": "中华人民共和国著作权法\n（1990年9月7日第七届全国人民代表大会常务委员会第十五次会议通过　根据2001年10月27日第九届全国人民代表大会常务委员会第二十四次会议《关于修改〈中华人民共和国著作权法〉的决定》第一次修正　根据2010年2月26日第十一届全国人民代表大会常务委员会第十三次会议《关于修改〈中华人民共和国著作权法〉的决定》第二次修正　根据2020年11月11日第十三届全国人民代表大会常务委员会第二十三次会议《关于修改〈中华人民共和国著作权法〉的决定》第三次修正）\n目　　录\n第一章　总　　则\n第二章　著作权\n第一节　著作权人及其权利\n第二节　著作权归属\n第三节　权利的保护期\n第四节　权利的限制\n第三章　著作权许可使用和转让合同\n第四章　与著作权有关的权利\n第一节　图书、报刊的出版\n第二节　表　　演\n第三节　录音录像\n第四节　广播电台、电视台播放\n第五章　著作权和与著作权有关的权利的保护\n第六章　附　　则\n第一章　总　　则\n第一条　为保护文学、艺术和科学作品作者的著作权，以及与著作权有关的权益，鼓励有益于社会主义精神文明、物质文明建设的作品的创作和传播，促进社会主义文化和科学事业的发展与繁荣，根据宪法制定本法。\n第二条　中国公民、法人或者非法人组织的作品，不论是否发表，依照本法享有著作权。\n外国人、无国籍人的作品根据其作者所属国或者经常居住地国同中国签订的协议或者共同参加的国际条约享有的著作权，受本法保护。\n外国人、无国籍人的作品首先在中国境内出版的，依照本法享有著作权。\n未与中国签订协议或者共同参加国际条约的国家的作者以及无国籍人的作品首次在中国参加的国际条约的成员国出版的，或者在成员国和非成员国同时出版的，受本法保护。\n第三条　本法所称的作品，是指文学、艺术和科学领域内具有独创性并能以一定形式表现的智力成果，包括：\n（一）文字作品；\n（二）口述作品；\n（三）音乐、戏剧、曲艺、舞蹈、杂技艺术作品；\n（四）美术、建筑作品；\n（五）摄影作品；\n（六）视听作品；\n（七）工程设计图、产品设计图、地图、示意图等图形作品和模型作品；\n（八）计算机软件；\n（九）符合作品特征的其他智力成果。\n第四条　著作权人和与著作权有关的权利人行使权利，不得违反宪法和法律，不得损害公共利益。国家对作品的出版、传播依法进行监督管理。\n第五条　本法不适用于：\n（一）法律、法规，国家机关的决议、决定、命令和其他具有立法、行政、司法性质的文件，及其官方正式译文；\n（二）单纯事实消息；\n（三）历法、通用数表、通用表格和公式。\n第六条　民间文学艺术作品的著作权保护办法由国务院另行规定。\n第七条　国家著作权主管部门负责全国的著作权管理工作；县级以上地方主管著作权的部门负责本行政区域的著作权管理工作。\n第八条　著作权人和与著作权有关的权利人可以授权著作权集体管理组织行使著作权或者与著作权有关的权利。依法设立的著作权集体管理组织是非营利法人，被授权后可以以自己的名义为著作权人和与著作权有关的权利人主张权利，并可以作为当事人进行涉及著作权或者与著作权有关的权利的诉讼、仲裁、调解活动。\n著作权集体管理组织根据授权向使用者收取使用费。使用费的收取标准由著作权集体管理组织和使用者代表协商确定，协商不成的，可以向国家著作权主管部门申请裁决，对裁决不服的，可以向人民法院提起诉讼；当事人也可以直接向人民法院提起诉讼。\n著作权集体管理组织应当将使用费的收取和转付、管理费的提取和使用、使用费的未分配部分等总体情况定期向社会公布，并应当建立权利信息查询系统，供权利人和使用者查询。国家著作权主管部门应当依法对著作权集体管理组织进行监督、管理。\n著作权集体管理组织的设立方式、权利义务、使用费的收取和分配，以及对其监督和管理等由国务院另行规定。\n第二章　著作权\n第一节　著作权人及其权利\n第九条　著作权人包括：\n（一）作者；\n（二）其他依照本法享有著作权的自然人、法人或者非法人组织。\n第十条　著作权包括下列人身权和财产权：\n（一）发表权，即决定作品是否公之于众的权利；\n（二）署名权，即表明作者身份，在作品上署名的权利；\n（三）修改权，即修改或者授权他人修改作品的权利；\n（四）保护作品完整权，即保护作品不受歪曲、篡改的权利；\n（五）复制权，即以印刷、复印、拓印、录音、录像、翻录、翻拍、数字化等方式将作品制作一份或者多份的权利；\n（六）发行权，即以出售或者赠与方式向公众提供作品的原件或者复制件的权利；\n（七）出租权，即有偿许可他人临时使用视听作品、计算机软件的原件或者复制件的权利，计算机软件不是出租的主要标的的除外；\n（八）展览权，即公开陈列美术作品、摄影作品的原件或者复制件的权利；\n（九）表演权，即公开表演作品，以及用各种手段公开播送作品的表演的权利；\n（十）放映权，即通过放映机、幻灯机等技术设备公开再现美术、摄影、视听作品等的权利；\n（十一）广播权，即以有线或者无线方式公开传播或者转播作品，以及通过扩音器或者其他传送符号、声音、图像的类似工具向公众传播广播的作品的权利，但不包括本款第十二项规定的权利；\n（十二）信息网络传播权，即以有线或者无线方式向公众提供，使公众可以在其选定的时间和地点获得作品的权利；\n（十三）摄制权，即以摄制视听作品的方法将作品固定在载体上的权利；\n（十四）改编权，即改变作品，创作出具有独创性的新作品的权利；\n（十五）翻译权，即将作品从一种语言文字转换成另一种语言文字的权利；\n（十六）汇编权，即将作品或者作品的片段通过选择或者编排，汇集成新作品的权利；\n（十七）应当由著作权人享有的其他权利。\n著作权人可以许可他人行使前款第五项至第十七项规定的权利，并依照约定或者本法有关规定获得报酬。\n著作权人可以全部或者部分转让本条第一款第五项至第十七项规定的权利，并依照约定或者本法有关规定获得报酬。\n第二节　著作权归属\n第十一条　著作权属于作者，本法另有规定的除外。\n创作作品的自然人是作者。\n由法人或者非法人组织主持，代表法人或者非法人组织意志创作，并由法人或者非法人组织承担责任的作品，法人或者非法人组织视为作者。\n第十二条　在作品上署名的自然人、法人或者非法人组织为作者，且该作品上存在相应权利，但有相反证明的除外。\n作者等著作权人可以向国家著作权主管部门认定的登记机构办理作品登记。\n与著作权有关的权利参照适用前两款规定。\n第十三条　改编、翻译、注释、整理已有作品而产生的作品，其著作权由改编、翻译、注释、整理人享有，但行使著作权时不得侵犯原作品的著作权。\n第十四条　两人以上合作创作的作品，著作权由合作作者共同享有。没有参加创作的人，不能成为合作作者。\n合作作品的著作权由合作作者通过协商一致行使；不能协商一致，又无正当理由的，任何一方不得阻止他方行使除转让、许可他人专有使用、出质以外的其他权利，但是所得收益应当合理分配给所有合作作者。\n合作作品可以分割使用的，作者对各自创作的部分可以单独享有著作权，但行使著作权时不得侵犯合作作品整体的著作权。\n第十五条　汇编若干作品、作品的片段或者不构成作品的数据或者其他材料，对其内容的选择或者编排体现独创性的作品，为汇编作品，其著作权由汇编人享有，但行使著作权时，不得侵犯原作品的著作权。\n第十六条　使用改编、翻译、注释、整理、汇编已有作品而产生的作品进行出版、演出和制作录音录像制品，应当取得该作品的著作权人和原作品的著作权人许可，并支付报酬。\n第十七条　视听作品中的电影作品、电视剧作品的著作权由制作者享有，但编剧、导演、摄影、作词、作曲等作者享有署名权，并有权按照与制作者签订的合同获得报酬。\n前款规定以外的视听作品的著作权归属由当事人约定；没有约定或者约定不明确的，由制作者享有，但作者享有署名权和获得报酬的权利。\n视听作品中的剧本、音乐等可以单独使用的作品的作者有权单独行使其著作权。\n第十八条　自然人为完成法人或者非法人组织工作任务所创作的作品是职务作品，除本条第二款的规定以外，著作权由作者享有，但法人或者非法人组织有权在其业务范围内优先使用。作品完成两年内，未经单位同意，作者不得许可第三人以与单位使用的相同方式使用该作品。\n有下列情形之一的职务作品，作者享有署名权，著作权的其他权利由法人或者非法人组织享有，法人或者非法人组织可以给予作者奖励：\n（一）主要是利用法人或者非法人组织的物质技术条件创作，并由法人或者非法人组织承担责任的工程设计图、产品设计图、地图、示意图、计算机软件等职务作品；\n（二）报社、期刊社、通讯社、广播电台、电视台的工作人员创作的职务作品；\n（三）法律、行政法规规定或者合同约定著作权由法人或者非法人组织享有的职务作品。\n第十九条　受委托创作的作品，著作权的归属由委托人和受托人通过合同约定。合同未作明确约定或者没有订立合同的，著作权属于受托人。\n第二十条　作品原件所有权的转移，不改变作品著作权的归属，但美术、摄影作品原件的展览权由原件所有人享有。\n作者将未发表的美术、摄影作品的原件所有权转让给他人，受让人展览该原件不构成对作者发表权的侵犯。\n第二十一条　著作权属于自然人的，自然人死亡后，其本法第十条第一款第五项至第十七项规定的权利在本法规定的保护期内，依法转移。\n著作权属于法人或者非法人组织的，法人或者非法人组织变更、终止后，其本法第十条第一款第五项至第十七项规定的权利在本法规定的保护期内，由承受其权利义务的法人或者非法人组织享有；没有承受其权利义务的法人或者非法人组织的，由国家享有。\n第三节　权利的保护期\n第二十二条　作者的署名权、修改权、保护作品完整权的保护期不受限制。\n第二十三条　自然人的作品，其发表权、本法第十条第一款第五项至第十七项规定的权利的保护期为作者终生及其死亡后五十年，截止于作者死亡后第五十年的12月31日；如果是合作作品，截止于最后死亡的作者死亡后第五十年的12月31日。\n法人或者非法人组织的作品、著作权（署名权除外）由法人或者非法人组织享有的职务作品，其发表权的保护期为五十年，截止于作品创作完成后第五十年的12月31日；本法第十条第一款第五项至第十七项规定的权利的保护期为五十年，截止于作品首次发表后第五十年的12月31日，但作品自创作完成后五十年内未发表的，本法不再保护。\n视听作品，其发表权的保护期为五十年，截止于作品创作完成后第五十年的12月31日；本法第十条第一款第五项至第十七项规定的权利的保护期为五十年，截止于作品首次发表后第五十年的12月31日，但作品自创作完成后五十年内未发表的，本法不再保护。\n第四节　权利的限制\n第二十四条　在下列情况下使用作品，可以不经著作权人许可，不向其支付报酬，但应当指明作者姓名或者名称、作品名称，并且不得影响该作品的正常使用，也不得不合理地损害著作权人的合法权益：\n（一）为个人学习、研究或者欣赏，使用他人已经发表的作品；\n（二）为介绍、评论某一作品或者说明某一问题，在作品中适当引用他人已经发表的作品；\n（三）为报道新闻，在报纸、期刊、广播电台、电视台等媒体中不可避免地再现或者引用已经发表的作品；\n（四）报纸、期刊、广播电台、电视台等媒体刊登或者播放其他报纸、期刊、广播电台、电视台等媒体已经发表的关于政治、经济、宗教问题的时事性文章，但著作权人声明不许刊登、播放的除外；\n（五）报纸、期刊、广播电台、电视台等媒体刊登或者播放在公众集会上发表的讲话，但作者声明不许刊登、播放的除外；\n（六）为学校课堂教学或者科学研究，翻译、改编、汇编、播放或者少量复制已经发表的作品，供教学或者科研人员使用，但不得出版发行；\n（七）国家机关为执行公务在合理范围内使用已经发表的作品；\n（八）图书馆、档案馆、纪念馆、博物馆、美术馆、文化馆等为陈列或者保存版本的需要，复制本馆收藏的作品；\n（九）免费表演已经发表的作品，该表演未向公众收取费用，也未向表演者支付报酬，且不以营利为目的；\n（十）对设置或者陈列在公共场所的艺术作品进行临摹、绘画、摄影、录像；\n（十一）将中国公民、法人或者非法人组织已经发表的以国家通用语言文字创作的作品翻译成少数民族语言文字作品在国内出版发行；\n（十二）以阅读障碍者能够感知的无障碍方式向其提供已经发表的作品；\n（十三）法律、行政法规规定的其他情形。\n前款规定适用于对与著作权有关的权利的限制。\n第二十五条　为实施义务教育和国家教育规划而编写出版教科书，可以不经著作权人许可，在教科书中汇编已经发表的作品片段或者短小的文字作品、音乐作品或者单幅的美术作品、摄影作品、图形作品，但应当按照规定向著作权人支付报酬，指明作者姓名或者名称、作品名称，并且不得侵犯著作权人依照本法享有的其他权利。\n前款规定适用于对与著作权有关的权利的限制。\n第三章　著作权许可使用和转让合同\n第二十六条　使用他人作品应当同著作权人订立许可使用合同，本法规定可以不经许可的除外。\n许可使用合同包括下列主要内容：\n（一）许可使用的权利种类；\n（二）许可使用的权利是专有使用权或者非专有使用权；\n（三）许可使用的地域范围、期间；\n（四）付酬标准和办法；\n（五）违约责任；\n（六）双方认为需要约定的其他内容。\n第二十七条　转让本法第十条第一款第五项至第十七项规定的权利，应当订立书面合同。\n权利转让合同包括下列主要内容：\n（一）作品的名称；\n（二）转让的权利种类、地域范围；\n（三）转让价金；\n（四）交付转让价金的日期和方式；\n（五）违约责任；\n（六）双方认为需要约定的其他内容。\n第二十八条　以著作权中的财产权出质的，由出质人和质权人依法办理出质登记。\n第二十九条　许可使用合同和转让合同中著作权人未明确许可、转让的权利，未经著作权人同意，另一方当事人不得行使。\n第三十条　使用作品的付酬标准可以由当事人约定，也可以按照国家著作权主管部门会同有关部门制定的付酬标准支付报酬。当事人约定不明确的，按照国家著作权主管部门会同有关部门制定的付酬标准支付报酬。\n第三十一条　出版者、表演者、录音录像制作者、广播电台、电视台等依照本法有关规定使用他人作品的，不得侵犯作者的署名权、修改权、保护作品完整权和获得报酬的权利。\n第四章　与著作权有关的权利\n第一节　图书、报刊的出版\n第三十二条　图书出版者出版图书应当和著作权人订立出版合同，并支付报酬。\n第三十三条　图书出版者对著作权人交付出版的作品，按照合同约定享有的专有出版权受法律保护，他人不得出版该作品。\n第三十四条　著作权人应当按照合同约定期限交付作品。图书出版者应当按照合同约定的出版质量、期限出版图书。\n图书出版者不按照合同约定期限出版，应当依照本法第六十一条的规定承担民事责任。\n图书出版者重印、再版作品的，应当通知著作权人，并支付报酬。图书脱销后，图书出版者拒绝重印、再版的，著作权人有权终止合同。\n第三十五条　著作权人向报社、期刊社投稿的，自稿件发出之日起十五日内未收到报社通知决定刊登的，或者自稿件发出之日起三十日内未收到期刊社通知决定刊登的，可以将同一作品向其他报社、期刊社投稿。双方另有约定的除外。\n作品刊登后，除著作权人声明不得转载、摘编的外，其他报刊可以转载或者作为文摘、资料刊登，但应当按照规定向著作权人支付报酬。\n第三十六条　图书出版者经作者许可，可以对作品修改、删节。\n报社、期刊社可以对作品作文字性修改、删节。对内容的修改，应当经作者许可。\n第三十七条　出版者有权许可或者禁止他人使用其出版的图书、期刊的版式设计。\n前款规定的权利的保护期为十年，截止于使用该版式设计的图书、期刊首次出版后第十年的12月31日。\n第二节　表　　演\n第三十八条　使用他人作品演出，表演者应当取得著作权人许可，并支付报酬。演出组织者组织演出，由该组织者取得著作权人许可，并支付报酬。\n第三十九条　表演者对其表演享有下列权利：\n（一）表明表演者身份；\n（二）保护表演形象不受歪曲；\n（三）许可他人从现场直播和公开传送其现场表演，并获得报酬；\n（四）许可他人录音录像，并获得报酬；\n（五）许可他人复制、发行、出租录有其表演的录音录像制品，并获得报酬；\n（六）许可他人通过信息网络向公众传播其表演，并获得报酬。\n被许可人以前款第三项至第六项规定的方式使用作品，还应当取得著作权人许可，并支付报酬。\n第四十条　演员为完成本演出单位的演出任务进行的表演为职务表演，演员享有表明身份和保护表演形象不受歪曲的权利，其他权利归属由当事人约定。当事人没有约定或者约定不明确的，职务表演的权利由演出单位享有。\n职务表演的权利由演员享有的，演出单位可以在其业务范围内免费使用该表演。\n第四十一条　本法第三十九条第一款第一项、第二项规定的权利的保护期不受限制。\n本法第三十九条第一款第三项至第六项规定的权利的保护期为五十年，截止于该表演发生后第五十年的12月31日。\n第三节　录音录像\n第四十二条　录音录像制作者使用他人作品制作录音录像制品，应当取得著作权人许可，并支付报酬。\n录音制作者使用他人已经合法录制为录音制品的音乐作品制作录音制品，可以不经著作权人许可，但应当按照规定支付报酬；著作权人声明不许使用的不得使用。\n第四十三条　录音录像制作者制作录音录像制品，应当同表演者订立合同，并支付报酬。\n第四十四条　录音录像制作者对其制作的录音录像制品，享有许可他人复制、发行、出租、通过信息网络向公众传播并获得报酬的权利；权利的保护期为五十年，截止于该制品首次制作完成后第五十年的12月31日。\n被许可人复制、发行、通过信息网络向公众传播录音录像制品，应当同时取得著作权人、表演者许可，并支付报酬；被许可人出租录音录像制品，还应当取得表演者许可，并支付报酬。\n第四十五条　将录音制品用于有线或者无线公开传播，或者通过传送声音的技术设备向公众公开播送的，应当向录音制作者支付报酬。\n第四节　广播电台、电视台播放\n第四十六条　广播电台、电视台播放他人未发表的作品，应当取得著作权人许可，并支付报酬。\n广播电台、电视台播放他人已发表的作品，可以不经著作权人许可，但应当按照规定支付报酬。\n第四十七条　广播电台、电视台有权禁止未经其许可的下列行为：\n（一）将其播放的广播、电视以有线或者无线方式转播；\n（二）将其播放的广播、电视录制以及复制；\n（三）将其播放的广播、电视通过信息网络向公众传播。\n广播电台、电视台行使前款规定的权利，不得影响、限制或者侵害他人行使著作权或者与著作权有关的权利。\n本条第一款规定的权利的保护期为五十年，截止于该广播、电视首次播放后第五十年的12月31日。\n第四十八条　电视台播放他人的视听作品、录像制品，应当取得视听作品著作权人或者录像制作者许可，并支付报酬；播放他人的录像制品，还应当取得著作权人许可，并支付报酬。\n第五章　著作权和与著作权有关的权利的保护\n第四十九条　为保护著作权和与著作权有关的权利，权利人可以采取技术措施。\n未经权利人许可，任何组织或者个人不得故意避开或者破坏技术措施，不得以避开或者破坏技术措施为目的制造、进口或者向公众提供有关装置或者部件，不得故意为他人避开或者破坏技术措施提供技术服务。但是，法律、行政法规规定可以避开的情形除外。\n本法所称的技术措施，是指用于防止、限制未经权利人许可浏览、欣赏作品、表演、录音录像制品或者通过信息网络向公众提供作品、表演、录音录像制品的有效技术、装置或者部件。\n第五十条　下列情形可以避开技术措施，但不得向他人提供避开技术措施的技术、装置或者部件，不得侵犯权利人依法享有的其他权利：\n（一）为学校课堂教学或者科学研究，提供少量已经发表的作品，供教学或者科研人员使用，而该作品无法通过正常途径获取；\n（二）不以营利为目的，以阅读障碍者能够感知的无障碍方式向其提供已经发表的作品，而该作品无法通过正常途径获取；\n（三）国家机关依照行政、监察、司法程序执行公务；\n（四）对计算机及其系统或者网络的安全性能进行测试；\n（五）进行加密研究或者计算机软件反向工程研究。\n前款规定适用于对与著作权有关的权利的限制。\n第五十一条　未经权利人许可，不得进行下列行为：\n（一）故意删除或者改变作品、版式设计、表演、录音录像制品或者广播、电视上的权利管理信息，但由于技术上的原因无法避免的除外；\n（二）知道或者应当知道作品、版式设计、表演、录音录像制品或者广播、电视上的权利管理信息未经许可被删除或者改变，仍然向公众提供。\n第五十二条　有下列侵权行为的，应当根据情况，承担停止侵害、消除影响、赔礼道歉、赔偿损失等民事责任：\n（一）未经著作权人许可，发表其作品的；\n（二）未经合作作者许可，将与他人合作创作的作品当作自己单独创作的作品发表的；\n（三）没有参加创作，为谋取个人名利，在他人作品上署名的；\n（四）歪曲、篡改他人作品的；\n（五）剽窃他人作品的；\n（六）未经著作权人许可，以展览、摄制视听作品的方法使用作品，或者以改编、翻译、注释等方式使用作品的，本法另有规定的除外；\n（七）使用他人作品，应当支付报酬而未支付的；\n（八）未经视听作品、计算机软件、录音录像制品的著作权人、表演者或者录音录像制作者许可，出租其作品或者录音录像制品的原件或者复制件的，本法另有规定的除外；\n（九）未经出版者许可，使用其出版的图书、期刊的版式设计的；\n（十）未经表演者许可，从现场直播或者公开传送其现场表演，或者录制其表演的；\n（十一）其他侵犯著作权以及与著作权有关的权利的行为。\n第五十三条　有下列侵权行为的，应当根据情况，承担本法第五十二条规定的民事责任；侵权行为同时损害公共利益的，由主管著作权的部门责令停止侵权行为，予以警告，没收违法所得，没收、无害化销毁处理侵权复制品以及主要用于制作侵权复制品的材料、工具、设备等，违法经营额五万元以上的，可以并处违法经营额一倍以上五倍以下的罚款；没有违法经营额、违法经营额难以计算或者不足五万元的，可以并处二十五万元以下的罚款；构成犯罪的，依法追究刑事责任：\n（一）未经著作权人许可，复制、发行、表演、放映、广播、汇编、通过信息网络向公众传播其作品的，本法另有规定的除外；\n（二）出版他人享有专有出版权的图书的；\n（三）未经表演者许可，复制、发行录有其表演的录音录像制品，或者通过信息网络向公众传播其表演的，本法另有规定的除外；\n（四）未经录音录像制作者许可，复制、发行、通过信息网络向公众传播其制作的录音录像制品的，本法另有规定的除外；\n（五）未经许可，播放、复制或者通过信息网络向公众传播广播、电视的，本法另有规定的除外；\n（六）未经著作权人或者与著作权有关的权利人许可，故意避开或者破坏技术措施的，故意制造、进口或者向他人提供主要用于避开、破坏技术措施的装置或者部件的，或者故意为他人避开或者破坏技术措施提供技术服务的，法律、行政法规另有规定的除外；\n（七）未经著作权人或者与著作权有关的权利人许可，故意删除或者改变作品、版式设计、表演、录音录像制品或者广播、电视上的权利管理信息的，知道或者应当知道作品、版式设计、表演、录音录像制品或者广播、电视上的权利管理信息未经许可被删除或者改变，仍然向公众提供的，法律、行政法规另有规定的除外；\n（八）制作、出售假冒他人署名的作品的。\n第五十四条　侵犯著作权或者与著作权有关的权利的，侵权人应当按照权利人因此受到的实际损失或者侵权人的违法所得给予赔偿；权利人的实际损失或者侵权人的违法所得难以计算的，可以参照该权利使用费给予赔偿。对故意侵犯著作权或者与著作权有关的权利，情节严重的，可以在按照上述方法确定数额的一倍以上五倍以下给予赔偿。\n权利人的实际损失、侵权人的违法所得、权利使用费难以计算的，由人民法院根据侵权行为的情节，判决给予五百元以上五百万元以下的赔偿。\n赔偿数额还应当包括权利人为制止侵权行为所支付的合理开支。\n人民法院为确定赔偿数额，在权利人已经尽了必要举证责任，而与侵权行为相关的账簿、资料等主要由侵权人掌握的，可以责令侵权人提供与侵权行为相关的账簿、资料等；侵权人不提供，或者提供虚假的账簿、资料等的，人民法院可以参考权利人的主张和提供的证据确定赔偿数额。\n人民法院审理著作权纠纷案件，应权利人请求，对侵权复制品，除特殊情况外，责令销毁；对主要用于制造侵权复制品的材料、工具、设备等，责令销毁，且不予补偿；或者在特殊情况下，责令禁止前述材料、工具、设备等进入商业渠道，且不予补偿。\n第五十五条　主管著作权的部门对涉嫌侵犯著作权和与著作权有关的权利的行为进行查处时，可以询问有关当事人，调查与涉嫌违法行为有关的情况；对当事人涉嫌违法行为的场所和物品实施现场检查；查阅、复制与涉嫌违法行为有关的合同、发票、账簿以及其他有关资料；对于涉嫌违法行为的场所和物品，可以查封或者扣押。\n主管著作权的部门依法行使前款规定的职权时，当事人应当予以协助、配合，不得拒绝、阻挠。\n第五十六条　著作权人或者与著作权有关的权利人有证据证明他人正在实施或者即将实施侵犯其权利、妨碍其实现权利的行为，如不及时制止将会使其合法权益受到难以弥补的损害的，可以在起诉前依法向人民法院申请采取财产保全、责令作出一定行为或者禁止作出一定行为等措施。\n第五十七条　为制止侵权行为，在证据可能灭失或者以后难以取得的情况下，著作权人或者与著作权有关的权利人可以在起诉前依法向人民法院申请保全证据。\n第五十八条　人民法院审理案件，对于侵犯著作权或者与著作权有关的权利的，可以没收违法所得、侵权复制品以及进行违法活动的财物。\n第五十九条　复制品的出版者、制作者不能证明其出版、制作有合法授权的，复制品的发行者或者视听作品、计算机软件、录音录像制品的复制品的出租者不能证明其发行、出租的复制品有合法来源的，应当承担法律责任。\n在诉讼程序中，被诉侵权人主张其不承担侵权责任的，应当提供证据证明已经取得权利人的许可，或者具有本法规定的不经权利人许可而可以使用的情形。\n第六十条　著作权纠纷可以调解，也可以根据当事人达成的书面仲裁协议或者著作权合同中的仲裁条款，向仲裁机构申请仲裁。\n当事人没有书面仲裁协议，也没有在著作权合同中订立仲裁条款的，可以直接向人民法院起诉。\n第六十一条　当事人因不履行合同义务或者履行合同义务不符合约定而承担民事责任，以及当事人行使诉讼权利、申请保全等，适用有关法律的规定。\n第六章　附　　则\n第六十二条　本法所称的著作权即版权。\n第六十三条　本法第二条所称的出版，指作品的复制、发行。\n第六十四条　计算机软件、信息网络传播权的保护办法由国务院另行规定。\n第六十五条　摄影作品，其发表权、本法第十条第一款第五项至第十七项规定的权利的保护期在2021年6月1日前已经届满，但依据本法第二十三条第一款的规定仍在保护期内的，不再保护。\n第六十六条　本法规定的著作权人和出版者、表演者、录音录像制作者、广播电台、电视台的权利，在本法施行之日尚未超过本法规定的保护期的，依照本法予以保护。\n本法施行前发生的侵权或者违约行为，依照侵权或者违约行为发生时的有关规定处理。\n第六十七条　本法自1991年6月1日起施行。",
    "source": "npc"
  },
  {
    "title": "中华人民共和国企业破产法",
    "law_type": "法律",
    "publish_office": "全国人民代表大会常务委员会",
    "publish_date": "2006-08-27",
    "effective_date": "2007-06-01",
    "status": "现行有效",
    "bbbs": "2c909fdd678bf17901678bf63c7c0343",
    "url": "https://flk.npc.gov.cn/detail2.html?2c909fdd678bf17901678bf63c7c0343",
    "content": "中华人民共和国企业破产法\n（2006年8月27日第十届全国人民代表大会常务委员会第二十三次会议通过）\n目　　录\n第一章　总　　则\n第二章　申请和受理\n第一节　申　　请\n第二节　受　　理\n第三章　管理人\n第四章　债务人财产\n第五章　破产费用和共益债务\n第六章　债权申报\n第七章　债权人会议\n第一节　一般规定\n第二节　债权人委员会\n第八章　重　　整\n第一节　重整申请和重整期间\n第二节　重整计划的制定和批准\n第三节　重整计划的执行\n第九章　和　　解\n第十章　破产清算\n第一节　破产宣告\n第二节　变价和分配\n第三节　破产程序的终结\n第十一章　法律责任\n第十二章　附　　则\n第一章　总　　则\n第一条　为规范企业破产程序，公平清理债权债务，保护债权人和债务人的合法权益，维护社会主义市场经济秩序，制定本法。\n第二条　企业法人不能清偿到期债务，并且资产不足以清偿全部债务或者明显缺乏清偿能力的，依照本法规定清理债务。\n企业法人有前款规定情形，或者有明显丧失清偿能力可能的，可以依照本法规定进行重整。\n第三条　破产案件由债务人住所地人民法院管辖。\n第四条　破产案件审理程序，本法没有规定的，适用民事诉讼法的有关规定。\n第五条　依照本法开始的破产程序，对债务人在中华人民共和国领域外的财产发生效力。\n对外国法院作出的发生法律效力的破产案件的判决、裁定，涉及债务人在中华人民共和国领域内的财产，申请或者请求人民法院承认和执行的，人民法院依照中华人民共和国缔结或者参加的国际条约，或者按照互惠原则进行审查，认为不违反中华人民共和国法律的基本原则，不损害国家主权、安全和社会公共利益，不损害中华人民共和国领域内债权人的合法权益的，裁定承认和执行。\n第六条　人民法院审理破产案件，应当依法保障企业职工的合法权益，依法追究破产企业经营管理人员的法律责任。\n第二章　申请和受理\n第一节　申　　请\n第七条　债务人有本法第二条规定的情形，可以向人民法院提出重整、和解或者破产清算申请。\n债务人不能清偿到期债务，债权人可以向人民法院提出对债务人进行重整或者破产清算的申请。\n企业法人已解散但未清算或者未清算完毕，资产不足以清偿债务的，依法负有清算责任的人应当向人民法院申请破产清算。\n第八条　向人民法院提出破产申请，应当提交破产申请书和有关证据。\n破产申请书应当载明下列事项：\n（一）申请人、被申请人的基本情况；\n（二）申请目的；\n（三）申请的事实和理由；\n（四）人民法院认为应当载明的其他事项。\n债务人提出申请的，还应当向人民法院提交财产状况说明、债务清册、债权清册、有关财务会计报告、职工安置预案以及职工工资的支付和社会保险费用的缴纳情况。\n第九条　人民法院受理破产申请前，申请人可以请求撤回申请。\n第二节　受　　理\n第十条　债权人提出破产申请的，人民法院应当自收到申请之日起五日内通知债务人。债务人对申请有异议的，应当自收到人民法院的通知之日起七日内向人民法院提出。人民法院应当自异议期满之日起十日内裁定是否受理。\n除前款规定的情形外，人民法院应当自收到破产申请之日起十五日内裁定是否受理。\n有特殊情况需要延长前两款规定的裁定受理期限的，经上一级人民法院批准，可以延长十五日。\n第十一条　人民法院受理破产申请的，应当自裁定作出之日起五日内送达申请人。\n债权人提出申请的，人民法院应当自裁定作出之日起五日内送达债务人。债务人应当自裁定送达之日起十五日内，向人民法院提交财产状况说明、债务清册、债权清册、有关财务会计报告以及职工工资的支付和社会保险费用的缴纳情况。\n第十二条　人民法院裁定不受理破产申请的，应当自裁定作出之日起五日内送达申请人并说明理由。申请人对裁定不服的，可以自裁定送达之日起十日内向上一级人民法院提起上诉。\n人民法院受理破产申请后至破产宣告前，经审查发现债务人不符合本法第二条规定情形的，可以裁定驳回申请。申请人对裁定不服的，可以自裁定送达之日起十日内向上一级人民法院提起上诉。\n第十三条　人民法院裁定受理破产申请的，应当同时指定管理人。\n第十四条　人民法院应当自裁定受理破产申请之日起二十五日内通知已知债权人，并予以公告。\n通知和公告应当载明下列事项：\n（一）申请人、被申请人的名称或者姓名；\n（二）人民法院受理破产申请的时间；\n（三）申报债权的期限、地点和注意事项；\n（四）管理人的名称或者姓名及其处理事务的地址；\n（五）债务人的债务人或者财产持有人应当向管理人清偿债务或者交付财产的要求；\n（六）第一次债权人会议召开的时间和地点；\n（七）人民法院认为应当通知和公告的其他事项。\n第十五条　自人民法院受理破产申请的裁定送达债务人之日起至破产程序终结之日，债务人的有关人员承担下列义务：\n（一）妥善保管其占有和管理的财产、印章和账簿、文书等资料；\n（二）根据人民法院、管理人的要求进行工作，并如实回答询问；\n（三）列席债权人会议并如实回答债权人的询问；\n（四）未经人民法院许可，不得离开住所地；\n（五）不得新任其他企业的董事、监事、高级管理人员。\n前款所称有关人员，是指企业的法定代表人；经人民法院决定，可以包括企业的财务管理人员和其他经营管理人员。\n第十六条　人民法院受理破产申请后，债务人对个别债权人的债务清偿无效。\n第十七条　人民法院受理破产申请后，债务人的债务人或者财产持有人应当向管理人清偿债务或者交付财产。\n债务人的债务人或者财产持有人故意违反前款规定向债务人清偿债务或者交付财产，使债权人受到损失的，不免除其清偿债务或者交付财产的义务。\n第十八条　人民法院受理破产申请后，管理人对破产申请受理前成立而债务人和对方当事人均未履行完毕的合同有权决定解除或者继续履行，并通知对方当事人。管理人自破产申请受理之日起二个月内未通知对方当事人，或者自收到对方当事人催告之日起三十日内未答复的，视为解除合同。\n管理人决定继续履行合同的，对方当事人应当履行；但是，对方当事人有权要求管理人提供担保。管理人不提供担保的，视为解除合同。\n第十九条　人民法院受理破产申请后，有关债务人财产的保全措施应当解除，执行程序应当中止。\n第二十条　人民法院受理破产申请后，已经开始而尚未终结的有关债务人的民事诉讼或者仲裁应当中止；在管理人接管债务人的财产后，该诉讼或者仲裁继续进行。\n第二十一条　人民法院受理破产申请后，有关债务人的民事诉讼，只能向受理破产申请的人民法院提起。\n第三章　管理人\n第二十二条　管理人由人民法院指定。\n债权人会议认为管理人不能依法、公正执行职务或者有其他不能胜任职务情形的，可以申请人民法院予以更换。\n指定管理人和确定管理人报酬的办法，由最高人民法院规定。\n第二十三条　管理人依照本法规定执行职务，向人民法院报告工作，并接受债权人会议和债权人委员会的监督。\n管理人应当列席债权人会议，向债权人会议报告职务执行情况，并回答询问。\n第二十四条　管理人可以由有关部门、机构的人员组成的清算组或者依法设立的律师事务所、会计师事务所、破产清算事务所等社会中介机构担任。\n人民法院根据债务人的实际情况，可以在征询有关社会中介机构的意见后，指定该机构具备相关专业知识并取得执业资格的人员担任管理人。\n有下列情形之一的，不得担任管理人：\n（一）因故意犯罪受过刑事处罚；\n（二）曾被吊销相关专业执业证书；\n（三）与本案有利害关系；\n（四）人民法院认为不宜担任管理人的其他情形。\n个人担任管理人的，应当参加执业责任保险。\n第二十五条　管理人履行下列职责：\n（一）接管债务人的财产、印章和账簿、文书等资料；\n（二）调查债务人财产状况，制作财产状况报告；\n（三）决定债务人的内部管理事务；\n（四）决定债务人的日常开支和其他必要开支；\n（五）在第一次债权人会议召开之前，决定继续或者停止债务人的营业；\n（六）管理和处分债务人的财产；\n（七）代表债务人参加诉讼、仲裁或者其他法律程序；\n（八）提议召开债权人会议；\n（九）人民法院认为管理人应当履行的其他职责。\n本法对管理人的职责另有规定的，适用其规定。\n第二十六条　在第一次债权人会议召开之前，管理人决定继续或者停止债务人的营业或者有本法第六十九条规定行为之一的，应当经人民法院许可。\n第二十七条　管理人应当勤勉尽责，忠实执行职务。\n第二十八条　管理人经人民法院许可，可以聘用必要的工作人员。\n管理人的报酬由人民法院确定。债权人会议对管理人的报酬有异议的，有权向人民法院提出。\n第二十九条　管理人没有正当理由不得辞去职务。管理人辞去职务应当经人民法院许可。\n第四章　债务人财产\n第三十条　破产申请受理时属于债务人的全部财产，以及破产申请受理后至破产程序终结前债务人取得的财产，为债务人财产。\n第三十一条　人民法院受理破产申请前一年内，涉及债务人财产的下列行为，管理人有权请求人民法院予以撤销：\n（一）无偿转让财产的；\n（二）以明显不合理的价格进行交易的；\n（三）对没有财产担保的债务提供财产担保的；\n（四）对未到期的债务提前清偿的；\n（五）放弃债权的。\n第三十二条　人民法院受理破产申请前六个月内，债务人有本法第二条第一款规定的情形，仍对个别债权人进行清偿的，管理人有权请求人民法院予以撤销。但是，个别清偿使债务人财产受益的除外。\n第三十三条　涉及债务人财产的下列行为无效：\n（一）为逃避债务而隐匿、转移财产的；\n（二）虚构债务或者承认不真实的债务的。\n第三十四条　因本法第三十一条、第三十二条或者第三十三条规定的行为而取得的债务人的财产，管理人有权追回。\n第三十五条　人民法院受理破产申请后，债务人的出资人尚未完全履行出资义务的，管理人应当要求该出资人缴纳所认缴的出资，而不受出资期限的限制。\n第三十六条　债务人的董事、监事和高级管理人员利用职权从企业获取的非正常收入和侵占的企业财产，管理人应当追回。\n第三十七条　人民法院受理破产申请后，管理人可以通过清偿债务或者提供为债权人接受的担保，取回质物、留置物。\n前款规定的债务清偿或者替代担保，在质物或者留置物的价值低于被担保的债权额时，以该质物或者留置物当时的市场价值为限。\n第三十八条　人民法院受理破产申请后，债务人占有的不属于债务人的财产，该财产的权利人可以通过管理人取回。但是，本法另有规定的除外。\n第三十九条　人民法院受理破产申请时，出卖人已将买卖标的物向作为买受人的债务人发运，债务人尚未收到且未付清全部价款的，出卖人可以取回在运途中的标的物。但是，管理人可以支付全部价款，请求出卖人交付标的物。\n第四十条　债权人在破产申请受理前对债务人负有债务的，可以向管理人主张抵销。但是，有下列情形之一的，不得抵销：\n（一）债务人的债务人在破产申请受理后取得他人对债务人的债权的；\n（二）债权人已知债务人有不能清偿到期债务或者破产申请的事实，对债务人负担债务的；但是，债权人因为法律规定或者有破产申请一年前所发生的原因而负担债务的除外；\n（三）债务人的债务人已知债务人有不能清偿到期债务或者破产申请的事实，对债务人取得债权的；但是，债务人的债务人因为法律规定或者有破产申请一年前所发生的原因而取得债权的除外。\n第五章　破产费用和共益债务\n第四十一条　人民法院受理破产申请后发生的下列费用，为破产费用：\n（一）破产案件的诉讼费用；\n（二）管理、变价和分配债务人财产的费用；\n（三）管理人执行职务的费用、报酬和聘用工作人员的费用。\n第四十二条　人民法院受理破产申请后发生的下列债务，为共益债务：\n（一）因管理人或者债务人请求对方当事人履行双方均未履行完毕的合同所产生的债务；\n（二）债务人财产受无因管理所产生的债务；\n（三）因债务人不当得利所产生的债务；\n（四）为债务人继续营业而应支付的劳动报酬和社会保险费用以及由此产生的其他债务；\n（五）管理人或者相关人员执行职务致人损害所产生的债务；\n（六）债务人财产致人损害所产生的债务。\n第四十三条　破产费用和共益债务由债务人财产随时清偿。\n债务人财产不足以清偿所有破产费用和共益债务的，先行清偿破产费用。\n债务人财产不足以清偿所有破产费用或者共益债务的，按照比例清偿。\n债务人财产不足以清偿破产费用的，管理人应当提请人民法院终结破产程序。人民法院应当自收到请求之日起十五日内裁定终结破产程序，并予以公告。\n第六章　债权申报\n第四十四条　人民法院受理破产申请时对债务人享有债权的债权人，依照本法规定的程序行使权利。\n第四十五条　人民法院受理破产申请后，应当确定债权人申报债权的期限。债权申报期限自人民法院发布受理破产申请公告之日起计算，最短不得少于三十日，最长不得超过三个月。\n第四十六条　未到期的债权，在破产申请受理时视为到期。\n附利息的债权自破产申请受理时起停止计息。\n第四十七条　附条件、附期限的债权和诉讼、仲裁未决的债权，债权人可以申报。\n第四十八条　债权人应当在人民法院确定的债权申报期限内向管理人申报债权。\n债务人所欠职工的工资和医疗、伤残补助、抚恤费用，所欠的应当划入职工个人账户的基本养老保险、基本医疗保险费用，以及法律、行政法规规定应当支付给职工的补偿金，不必申报，由管理人调查后列出清单并予以公示。职工对清单记载有异议的，可以要求管理人更正；管理人不予更正的，职工可以向人民法院提起诉讼。\n第四十九条　债权人申报债权时，应当书面说明债权的数额和有无财产担保，并提交有关证据。申报的债权是连带债权的，应当说明。\n第五十条　连带债权人可以由其中一人代表全体连带债权人申报债权，也可以共同申报债权。\n第五十一条　债务人的保证人或者其他连带债务人已经代替债务人清偿债务的，以其对债务人的求偿权申报债权。\n债务人的保证人或者其他连带债务人尚未代替债务人清偿债务的，以其对债务人的将来求偿权申报债权。但是，债权人已经向管理人申报全部债权的除外。\n第五十二条　连带债务人数人被裁定适用本法规定的程序的，其债权人有权就全部债权分别在各破产案件中申报债权。\n第五十三条　管理人或者债务人依照本法规定解除合同的，对方当事人以因合同解除所产生的损害赔偿请求权申报债权。\n第五十四条　债务人是委托合同的委托人，被裁定适用本法规定的程序，受托人不知该事实，继续处理委托事务的，受托人以由此产生的请求权申报债权。\n第五十五条　债务人是票据的出票人，被裁定适用本法规定的程序，该票据的付款人继续付款或者承兑的，付款人以由此产生的请求权申报债权。\n第五十六条　在人民法院确定的债权申报期限内，债权人未申报债权的，可以在破产财产最后分配前补充申报；但是，此前已进行的分配，不再对其补充分配。为审查和确认补充申报债权的费用，由补充申报人承担。\n债权人未依照本法规定申报债权的，不得依照本法规定的程序行使权利。\n第五十七条　管理人收到债权申报材料后，应当登记造册，对申报的债权进行审查，并编制债权表。\n债权表和债权申报材料由管理人保存，供利害关系人查阅。\n第五十八条　依照本法第五十七条规定编制的债权表，应当提交第一次债权人会议核查。\n债务人、债权人对债权表记载的债权无异议的，由人民法院裁定确认。\n债务人、债权人对债权表记载的债权有异议的，可以向受理破产申请的人民法院提起诉讼。\n第七章　债权人会议\n第一节　一般规定\n第五十九条　依法申报债权的债权人为债权人会议的成员，有权参加债权人会议，享有表决权。\n债权尚未确定的债权人，除人民法院能够为其行使表决权而临时确定债权额的外，不得行使表决权。\n对债务人的特定财产享有担保权的债权人，未放弃优先受偿权利的，对于本法第六十一条第一款第七项、第十项规定的事项不享有表决权。\n债权人可以委托代理人出席债权人会议，行使表决权。代理人出席债权人会议，应当向人民法院或者债权人会议主席提交债权人的授权委托书。\n债权人会议应当有债务人的职工和工会的代表参加，对有关事项发表意见。\n第六十条　债权人会议设主席一人，由人民法院从有表决权的债权人中指定。\n债权人会议主席主持债权人会议。\n第六十一条　债权人会议行使下列职权：\n（一）核查债权；\n（二）申请人民法院更换管理人，审查管理人的费用和报酬；\n（三）监督管理人；\n（四）选任和更换债权人委员会成员；\n（五）决定继续或者停止债务人的营业；\n（六）通过重整计划；\n（七）通过和解协议；\n（八）通过债务人财产的管理方案；\n（九）通过破产财产的变价方案；\n（十）通过破产财产的分配方案；\n（十一）人民法院认为应当由债权人会议行使的其他职权。\n债权人会议应当对所议事项的决议作成会议记录。\n第六十二条　第一次债权人会议由人民法院召集，自债权申报期限届满之日起十五日内召开。\n以后的债权人会议，在人民法院认为必要时，或者管理人、债权人委员会、占债权总额四分之一以上的债权人向债权人会议主席提议时召开。\n第六十三条　召开债权人会议，管理人应当提前十五日通知已知的债权人。\n第六十四条　债权人会议的决议，由出席会议的有表决权的债权人过半数通过，并且其所代表的债权额占无财产担保债权总额的二分之一以上。但是，本法另有规定的除外。\n债权人认为债权人会议的决议违反法律规定，损害其利益的，可以自债权人会议作出决议之日起十五日内，请求人民法院裁定撤销该决议，责令债权人会议依法重新作出决议。\n债权人会议的决议，对于全体债权人均有约束力。\n第六十五条　本法第六十一条第一款第八项、第九项所列事项，经债权人会议表决未通过的，由人民法院裁定。\n本法第六十一条第一款第十项所列事项，经债权人会议二次表决仍未通过的，由人民法院裁定。\n对前两款规定的裁定，人民法院可以在债权人会议上宣布或者另行通知债权人。\n第六十六条　债权人对人民法院依照本法第六十五条第一款作出的裁定不服的，债权额占无财产担保债权总额二分之一以上的债权人对人民法院依照本法第六十五条第二款作出的裁定不服的，可以自裁定宣布之日或者收到通知之日起十五日内向该人民法院申请复议。复议期间不停止裁定的执行。\n第二节　债权人委员会\n第六十七条　债权人会议可以决定设立债权人委员会。债权人委员会由债权人会议选任的债权人代表和一名债务人的职工代表或者工会代表组成。债权人委员会成员不得超过九人。\n债权人委员会成员应当经人民法院书面决定认可。\n第六十八条　债权人委员会行使下列职权：\n（一）监督债务人财产的管理和处分；\n（二）监督破产财产分配；\n（三）提议召开债权人会议；\n（四）债权人会议委托的其他职权。\n债权人委员会执行职务时，有权要求管理人、债务人的有关人员对其职权范围内的事务作出说明或者提供有关文件。\n管理人、债务人的有关人员违反本法规定拒绝接受监督的，债权人委员会有权就监督事项请求人民法院作出决定；人民法院应当在五日内作出决定。\n第六十九条　管理人实施下列行为，应当及时报告债权人委员会：\n（一）涉及土地、房屋等不动产权益的转让；\n（二）探矿权、采矿权、知识产权等财产权的转让；\n（三）全部库存或者营业的转让；\n（四）借款；\n（五）设定财产担保；\n（六）债权和有价证券的转让；\n（七）履行债务人和对方当事人均未履行完毕的合同；\n（八）放弃权利；\n（九）担保物的取回；\n（十）对债权人利益有重大影响的其他财产处分行为。\n未设立债权人委员会的，管理人实施前款规定的行为应当及时报告人民法院。\n第八章　重　　整\n第一节　重整申请和重整期间\n第七十条　债务人或者债权人可以依照本法规定，直接向人民法院申请对债务人进行重整。\n债权人申请对债务人进行破产清算的，在人民法院受理破产申请后、宣告债务人破产前，债务人或者出资额占债务人注册资本十分之一以上的出资人，可以向人民法院申请重整。\n第七十一条　人民法院经审查认为重整申请符合本法规定的，应当裁定债务人重整，并予以公告。\n第七十二条　自人民法院裁定债务人重整之日起至重整程序终止，为重整期间。\n第七十三条　在重整期间，经债务人申请，人民法院批准，债务人可以在管理人的监督下自行管理财产和营业事务。\n有前款规定情形的，依照本法规定已接管债务人财产和营业事务的管理人应当向债务人移交财产和营业事务，本法规定的管理人的职权由债务人行使。\n第七十四条　管理人负责管理财产和营业事务的，可以聘任债务人的经营管理人员负责营业事务。\n第七十五条　在重整期间，对债务人的特定财产享有的担保权暂停行使。但是，担保物有损坏或者价值明显减少的可能，足以危害担保权人权利的，担保权人可以向人民法院请求恢复行使担保权。\n在重整期间，债务人或者管理人为继续营业而借款的，可以为该借款设定担保。\n第七十六条　债务人合法占有的他人财产，该财产的权利人在重整期间要求取回的，应当符合事先约定的条件。\n第七十七条　在重整期间，债务人的出资人不得请求投资收益分配。\n在重整期间，债务人的董事、监事、高级管理人员不得向第三人转让其持有的债务人的股权。但是，经人民法院同意的除外。\n第七十八条　在重整期间，有下列情形之一的，经管理人或者利害关系人请求，人民法院应当裁定终止重整程序，并宣告债务人破产：\n（一）债务人的经营状况和财产状况继续恶化，缺乏挽救的可能性；\n（二）债务人有欺诈、恶意减少债务人财产或者其他显著不利于债权人的行为；\n（三）由于债务人的行为致使管理人无法执行职务。\n第二节　重整计划的制定和批准\n第七十九条　债务人或者管理人应当自人民法院裁定债务人重整之日起六个月内，同时向人民法院和债权人会议提交重整计划草案。\n前款规定的期限届满，经债务人或者管理人请求，有正当理由的，人民法院可以裁定延期三个月。\n债务人或者管理人未按期提出重整计划草案的，人民法院应当裁定终止重整程序，并宣告债务人破产。\n第八十条　债务人自行管理财产和营业事务的，由债务人制作重整计划草案。\n管理人负责管理财产和营业事务的，由管理人制作重整计划草案。\n第八十一条　重整计划草案应当包括下列内容：\n（一）债务人的经营方案；\n（二）债权分类；\n（三）债权调整方案；\n（四）债权受偿方案；\n（五）重整计划的执行期限；\n（六）重整计划执行的监督期限；\n（七）有利于债务人重整的其他方案。\n第八十二条　下列各类债权的债权人参加讨论重整计划草案的债权人会议，依照下列债权分类，分组对重整计划草案进行表决：\n（一）对债务人的特定财产享有担保权的债权；\n（二）债务人所欠职工的工资和医疗、伤残补助、抚恤费用，所欠的应当划入职工个人账户的基本养老保险、基本医疗保险费用，以及法律、行政法规规定应当支付给职工的补偿金；\n（三）债务人所欠税款；\n（四）普通债权。\n人民法院在必要时可以决定在普通债权组中设小额债权组对重整计划草案进行表决。\n第八十三条　重整计划不得规定减免债务人欠缴的本法第八十二条第一款第二项规定以外的社会保险费用；该项费用的债权人不参加重整计划草案的表决。\n第八十四条　人民法院应当自收到重整计划草案之日起三十日内召开债权人会议，对重整计划草案进行表决。\n出席会议的同一表决组的债权人过半数同意重整计划草案，并且其所代表的债权额占该组债权总额的三分之二以上的，即为该组通过重整计划草案。\n债务人或者管理人应当向债权人会议就重整计划草案作出说明，并回答询问。\n第八十五条　债务人的出资人代表可以列席讨论重整计划草案的债权人会议。\n重整计划草案涉及出资人权益调整事项的，应当设出资人组，对该事项进行表决。\n第八十六条　各表决组均通过重整计划草案时，重整计划即为通过。\n自重整计划通过之日起十日内，债务人或者管理人应当向人民法院提出批准重整计划的申请。人民法院经审查认为符合本法规定的，应当自收到申请之日起三十日内裁定批准，终止重整程序，并予以公告。\n第八十七条　部分表决组未通过重整计划草案的，债务人或者管理人可以同未通过重整计划草案的表决组协商。该表决组可以在协商后再表决一次。双方协商的结果不得损害其他表决组的利益。\n未通过重整计划草案的表决组拒绝再次表决或者再次表决仍未通过重整计划草案，但重整计划草案符合下列条件的，债务人或者管理人可以申请人民法院批准重整计划草案：\n（一）按照重整计划草案，本法第八十二条第一款第一项所列债权就该特定财产将获得全额清偿，其因延期清偿所受的损失将得到公平补偿，并且其担保权未受到实质性损害，或者该表决组已经通过重整计划草案；\n（二）按照重整计划草案，本法第八十二条第一款第二项、第三项所列债权将获得全额清偿，或者相应表决组已经通过重整计划草案；\n（三）按照重整计划草案，普通债权所获得的清偿比例，不低于其在重整计划草案被提请批准时依照破产清算程序所能获得的清偿比例，或者该表决组已经通过重整计划草案；\n（四）重整计划草案对出资人权益的调整公平、公正，或者出资人组已经通过重整计划草案；\n（五）重整计划草案公平对待同一表决组的成员，并且所规定的债权清偿顺序不违反本法第一百一十三条的规定；\n（六）债务人的经营方案具有可行性。\n人民法院经审查认为重整计划草案符合前款规定的，应当自收到申请之日起三十日内裁定批准，终止重整程序，并予以公告。\n第八十八条　重整计划草案未获得通过且未依照本法第八十七条的规定获得批准，或者已通过的重整计划未获得批准的，人民法院应当裁定终止重整程序，并宣告债务人破产。\n第三节　重整计划的执行\n第八十九条　重整计划由债务人负责执行。\n人民法院裁定批准重整计划后，已接管财产和营业事务的管理人应当向债务人移交财产和营业事务。\n第九十条　自人民法院裁定批准重整计划之日起，在重整计划规定的监督期内，由管理人监督重整计划的执行。\n在监督期内，债务人应当向管理人报告重整计划执行情况和债务人财务状况。\n第九十一条　监督期届满时，管理人应当向人民法院提交监督报告。自监督报告提交之日起，管理人的监督职责终止。\n管理人向人民法院提交的监督报告，重整计划的利害关系人有权查阅。\n经管理人申请，人民法院可以裁定延长重整计划执行的监督期限。\n第九十二条　经人民法院裁定批准的重整计划，对债务人和全体债权人均有约束力。\n债权人未依照本法规定申报债权的，在重整计划执行期间不得行使权利；在重整计划执行完毕后，可以按照重整计划规定的同类债权的清偿条件行使权利。\n债权人对债务人的保证人和其他连带债务人所享有的权利，不受重整计划的影响。\n第九十三条　债务人不能执行或者不执行重整计划的，人民法院经管理人或者利害关系人请求，应当裁定终止重整计划的执行，并宣告债务人破产。\n人民法院裁定终止重整计划执行的，债权人在重整计划中作出的债权调整的承诺失去效力。债权人因执行重整计划所受的清偿仍然有效，债权未受清偿的部分作为破产债权。\n前款规定的债权人，只有在其他同顺位债权人同自己所受的清偿达到同一比例时，才能继续接受分配。\n有本条第一款规定情形的，为重整计划的执行提供的担保继续有效。\n第九十四条　按照重整计划减免的债务，自重整计划执行完毕时起，债务人不再承担清偿责任。\n第九章　和　　解\n第九十五条　债务人可以依照本法规定，直接向人民法院申请和解；也可以在人民法院受理破产申请后、宣告债务人破产前，向人民法院申请和解。\n债务人申请和解，应当提出和解协议草案。\n第九十六条　人民法院经审查认为和解申请符合本法规定的，应当裁定和解，予以公告，并召集债权人会议讨论和解协议草案。\n对债务人的特定财产享有担保权的权利人，自人民法院裁定和解之日起可以行使权利。\n第九十七条　债权人会议通过和解协议的决议，由出席会议的有表决权的债权人过半数同意，并且其所代表的债权额占无财产担保债权总额的三分之二以上。\n第九十八条　债权人会议通过和解协议的，由人民法院裁定认可，终止和解程序，并予以公告。管理人应当向债务人移交财产和营业事务，并向人民法院提交执行职务的报告。\n第九十九条　和解协议草案经债权人会议表决未获得通过，或者已经债权人会议通过的和解协议未获得人民法院认可的，人民法院应当裁定终止和解程序，并宣告债务人破产。\n第一百条　经人民法院裁定认可的和解协议，对债务人和全体和解债权人均有约束力。\n和解债权人是指人民法院受理破产申请时对债务人享有无财产担保债权的人。\n和解债权人未依照本法规定申报债权的，在和解协议执行期间不得行使权利；在和解协议执行完毕后，可以按照和解协议规定的清偿条件行使权利。\n第一百零一条　和解债权人对债务人的保证人和其他连带债务人所享有的权利，不受和解协议的影响。\n第一百零二条　债务人应当按照和解协议规定的条件清偿债务。\n第一百零三条　因债务人的欺诈或者其他违法行为而成立的和解协议，人民法院应当裁定无效，并宣告债务人破产。\n有前款规定情形的，和解债权人因执行和解协议所受的清偿，在其他债权人所受清偿同等比例的范围内，不予返还。\n第一百零四条　债务人不能执行或者不执行和解协议的，人民法院经和解债权人请求，应当裁定终止和解协议的执行，并宣告债务人破产。\n人民法院裁定终止和解协议执行的，和解债权人在和解协议中作出的债权调整的承诺失去效力。和解债权人因执行和解协议所受的清偿仍然有效，和解债权未受清偿的部分作为破产债权。\n前款规定的债权人，只有在其他债权人同自己所受的清偿达到同一比例时，才能继续接受分配。\n有本条第一款规定情形的，为和解协议的执行提供的担保继续有效。\n第一百零五条　人民法院受理破产申请后，债务人与全体债权人就债权债务的处理自行达成协议的，可以请求人民法院裁定认可，并终结破产程序。\n第一百零六条　按照和解协议减免的债务，自和解协议执行完毕时起，债务人不再承担清偿责任。\n第十章　破产清算\n第一节　破产宣告\n第一百零七条　人民法院依照本法规定宣告债务人破产的，应当自裁定作出之日起五日内送达债务人和管理人，自裁定作出之日起十日内通知已知债权人，并予以公告。\n债务人被宣告破产后，债务人称为破产人，债务人财产称为破产财产，人民法院受理破产申请时对债务人享有的债权称为破产债权。\n第一百零八条　破产宣告前，有下列情形之一的，人民法院应当裁定终结破产程序，并予以公告：\n（一）第三人为债务人提供足额担保或者为债务人清偿全部到期债务的；\n（二）债务人已清偿全部到期债务的。\n第一百零九条　对破产人的特定财产享有担保权的权利人，对该特定财产享有优先受偿的权利。\n第一百一十条　享有本法第一百零九条规定权利的债权人行使优先受偿权利未能完全受偿的，其未受偿的债权作为普通债权；放弃优先受偿权利的，其债权作为普通债权。\n第二节　变价和分配\n第一百一十一条　管理人应当及时拟订破产财产变价方案，提交债权人会议讨论。\n管理人应当按照债权人会议通过的或者人民法院依照本法第六十五条第一款规定裁定的破产财产变价方案，适时变价出售破产财产。\n第一百一十二条　变价出售破产财产应当通过拍卖进行。但是，债权人会议另有决议的除外。\n破产企业可以全部或者部分变价出售。企业变价出售时，可以将其中的无形资产和其他财产单独变价出售。\n按照国家规定不能拍卖或者限制转让的财产，应当按照国家规定的方式处理。\n第一百一十三条　破产财产在优先清偿破产费用和共益债务后，依照下列顺序清偿：\n（一）破产人所欠职工的工资和医疗、伤残补助、抚恤费用，所欠的应当划入职工个人账户的基本养老保险、基本医疗保险费用，以及法律、行政法规规定应当支付给职工的补偿金；\n（二）破产人欠缴的除前项规定以外的社会保险费用和破产人所欠税款；\n（三）普通破产债权。\n破产财产不足以清偿同一顺序的清偿要求的，按照比例分配。\n破产企业的董事、监事和高级管理人员的工资按照该企业职工的平均工资计算。\n第一百一十四条　破产财产的分配应当以货币分配方式进行。但是，债权人会议另有决议的除外。\n第一百一十五条　管理人应当及时拟订破产财产分配方案，提交债权人会议讨论。\n破产财产分配方案应当载明下列事项：\n（一）参加破产财产分配的债权人名称或者姓名、住所；\n（二）参加破产财产分配的债权额；\n（三）可供分配的破产财产数额；\n（四）破产财产分配的顺序、比例及数额；\n（五）实施破产财产分配的方法。\n债权人会议通过破产财产分配方案后，由管理人将该方案提请人民法院裁定认可。\n第一百一十六条　破产财产分配方案经人民法院裁定认可后，由管理人执行。\n管理人按照破产财产分配方案实施多次分配的，应当公告本次分配的财产额和债权额。管理人实施最后分配的，应当在公告中指明，并载明本法第一百一十七条第二款规定的事项。\n第一百一十七条　对于附生效条件或者解除条件的债权，管理人应当将其分配额提存。\n管理人依照前款规定提存的分配额，在最后分配公告日，生效条件未成就或者解除条件成就的，应当分配给其他债权人；在最后分配公告日，生效条件成就或者解除条件未成就的，应当交付给债权人。\n第一百一十八条　债权人未受领的破产财产分配额，管理人应当提存。债权人自最后分配公告之日起满二个月仍不领取的，视为放弃受领分配的权利，管理人或者人民法院应当将提存的分配额分配给其他债权人。\n第一百一十九条　破产财产分配时，对于诉讼或者仲裁未决的债权，管理人应当将其分配额提存。自破产程序终结之日起满二年仍不能受领分配的，人民法院应当将提存的分配额分配给其他债权人。\n第三节　破产程序的终结\n第一百二十条　破产人无财产可供分配的，管理人应当请求人民法院裁定终结破产程序。\n管理人在最后分配完结后，应当及时向人民法院提交破产财产分配报告，并提请人民法院裁定终结破产程序。\n人民法院应当自收到管理人终结破产程序的请求之日起十五日内作出是否终结破产程序的裁定。裁定终结的，应当予以公告。\n第一百二十一条　管理人应当自破产程序终结之日起十日内，持人民法院终结破产程序的裁定，向破产人的原登记机关办理注销登记。\n第一百二十二条　管理人于办理注销登记完毕的次日终止执行职务。但是，存在诉讼或者仲裁未决情况的除外。\n第一百二十三条　自破产程序依照本法第四十三条第四款或者第一百二十条的规定终结之日起二年内，有下列情形之一的，债权人可以请求人民法院按照破产财产分配方案进行追加分配：\n（一）发现有依照本法第三十一条、第三十二条、第三十三条、第三十六条规定应当追回的财产的；\n（二）发现破产人有应当供分配的其他财产的。\n有前款规定情形，但财产数量不足以支付分配费用的，不再进行追加分配，由人民法院将其上交国库。\n第一百二十四条　破产人的保证人和其他连带债务人，在破产程序终结后，对债权人依照破产清算程序未受清偿的债权，依法继续承担清偿责任。\n第十一章　法律责任\n第一百二十五条　企业董事、监事或者高级管理人员违反忠实义务、勤勉义务，致使所在企业破产的，依法承担民事责任。\n有前款规定情形的人员，自破产程序终结之日起三年内不得担任任何企业的董事、监事、高级管理人员。\n第一百二十六条　有义务列席债权人会议的债务人的有关人员，经人民法院传唤，无正当理由拒不列席债权人会议的，人民法院可以拘传，并依法处以罚款。债务人的有关人员违反本法规定，拒不陈述、回答，或者作虚假陈述、回答的，人民法院可以依法处以罚款。\n第一百二十七条　债务人违反本法规定，拒不向人民法院提交或者提交不真实的财产状况说明、债务清册、债权清册、有关财务会计报告以及职工工资的支付情况和社会保险费用的缴纳情况的，人民法院可以对直接责任人员依法处以罚款。\n债务人违反本法规定，拒不向管理人移交财产、印章和账簿、文书等资料的，或者伪造、销毁有关财产证据材料而使财产状况不明的，人民法院可以对直接责任人员依法处以罚款。\n第一百二十八条　债务人有本法第三十一条、第三十二条、第三十三条规定的行为，损害债权人利益的，债务人的法定代表人和其他直接责任人员依法承担赔偿责任。\n第一百二十九条　债务人的有关人员违反本法规定，擅自离开住所地的，人民法院可以予以训诫、拘留，可以依法并处罚款。\n第一百三十条　管理人未依照本法规定勤勉尽责，忠实执行职务的，人民法院可以依法处以罚款；给债权人、债务人或者第三人造成损失的，依法承担赔偿责任。\n第一百三十一条　违反本法规定，构成犯罪的，依法追究刑事责任。\n第十二章　附　　则\n第一百三十二条　本法施行后，破产人在本法公布之日前所欠职工的工资和医疗、伤残补助、抚恤费用，所欠的应当划入职工个人账户的基本养老保险、基本医疗保险费用，以及法律、行政法规规定应当支付给职工的补偿金，依照本法第一百一十三条的规定清偿后不足以清偿的部分，以本法第一百零九条规定的特定财产优先于对该特定财产享有担保权的权利人受偿。\n第一百三十三条　在本法施行前国务院规定的期限和范围内的国有企业实施破产的特殊事宜，按照国务院有关规定办理。\n第一百三十四条　商业银行、证券公司、保险公司等金融机构有本法第二条规定情形的，国务院金融监督管理机构可以向人民法院提出对该金融机构进行重整或者破产清算的申请。国务院金融监督管理机构依法对出现重大经营风险的金融机构采取接管、托管等措施的，可以向人民法院申请中止以该金融机构为被告或者被执行人的民事诉讼程序或者执行程序。\n金融机构实施破产的，国务院可以依据本法和其他有关法律的规定制定实施办法。\n第一百三十五条　其他法律规定企业法人以外的组织的清算，属于破产清算的，参照适用本法规定的程序。\n第一百三十六条　本法自2007年6月1日起施行，《中华人民共和国企业破产法（试行）》同时废止。",
    "source": "npc"
  },
  {
    "title": "中华人民共和国合伙企业法",
    "law_type": "法律",
    "publish_office": "全国人民代表大会常务委员会",
    "publish_date": "2006-08-27",
    "effective_date": "2007-06-01",
    "status": "现行有效",
    "bbbs": "2c909fdd678bf17901678bf63dce034d",
    "url": "https://flk.npc.gov.cn/detail2.html?2c909fdd678bf17901678bf63dce034d",
    "content": "中华人民共和国合伙企业法\n（1997年2月23日第八届全国人民代表大会常务委员会第二十四次会议通过　2006年8月27日第十届全国人民代表大会常务委员会第二十三次会议修订）\n目　　录\n第一章　总　　则\n第二章　普通合伙企业\n第一节　合伙企业设立\n第二节　合伙企业财产\n第三节　合伙事务执行\n第四节　合伙企业与第三人关系\n第五节　入伙、退伙\n第六节　特殊的普通合伙企业\n第三章　有限合伙企业\n第四章　合伙企业解散、清算\n第五章　法律责任\n第六章　附　　则\n第一章　总　　则\n第一条　为了规范合伙企业的行为，保护合伙企业及其合伙人、债权人的合法权益，维护社会经济秩序，促进社会主义市场经济的发展，制定本法。\n第二条　本法所称合伙企业，是指自然人、法人和其他组织依照本法在中国境内设立的普通合伙企业和有限合伙企业。\n普通合伙企业由普通合伙人组成，合伙人对合伙企业债务承担无限连带责任。本法对普通合伙人承担责任的形式有特别规定的，从其规定。\n有限合伙企业由普通合伙人和有限合伙人组成，普通合伙人对合伙企业债务承担无限连带责任，有限合伙人以其认缴的出资额为限对合伙企业债务承担责任。\n第三条　国有独资公司、国有企业、上市公司以及公益性的事业单位、社会团体不得成为普通合伙人。\n第四条　合伙协议依法由全体合伙人协商一致、以书面形式订立。\n第五条　订立合伙协议、设立合伙企业，应当遵循自愿、平等、公平、诚实信用原则。\n第六条　合伙企业的生产经营所得和其他所得，按照国家有关税收规定，由合伙人分别缴纳所得税。\n第七条　合伙企业及其合伙人必须遵守法律、行政法规，遵守社会公德、商业道德，承担社会责任。\n第八条　合伙企业及其合伙人的合法财产及其权益受法律保护。\n第九条　申请设立合伙企业，应当向企业登记机关提交登记申请书、合伙协议书、合伙人身份证明等文件。\n合伙企业的经营范围中有属于法律、行政法规规定在登记前须经批准的项目的，该项经营业务应当依法经过批准，并在登记时提交批准文件。\n第十条　申请人提交的登记申请材料齐全、符合法定形式，企业登记机关能够当场登记的，应予当场登记，发给营业执照。\n除前款规定情形外，企业登记机关应当自受理申请之日起二十日内，作出是否登记的决定。予以登记的，发给营业执照；不予登记的，应当给予书面答复，并说明理由。\n第十一条　合伙企业的营业执照签发日期，为合伙企业成立日期。\n合伙企业领取营业执照前，合伙人不得以合伙企业名义从事合伙业务。\n第十二条　合伙企业设立分支机构，应当向分支机构所在地的企业登记机关申请登记，领取营业执照。\n第十三条　合伙企业登记事项发生变更的，执行合伙事务的合伙人应当自作出变更决定或者发生变更事由之日起十五日内，向企业登记机关申请办理变更登记。\n第二章　普通合伙企业\n第一节　合伙企业设立\n第十四条　设立合伙企业，应当具备下列条件：\n（一）有二个以上合伙人。合伙人为自然人的，应当具有完全民事行为能力；\n（二）有书面合伙协议；\n（三）有合伙人认缴或者实际缴付的出资；\n（四）有合伙企业的名称和生产经营场所；\n（五）法律、行政法规规定的其他条件。\n第十五条　合伙企业名称中应当标明“普通合伙”字样。\n第十六条　合伙人可以用货币、实物、知识产权、土地使用权或者其他财产权利出资，也可以用劳务出资。\n合伙人以实物、知识产权、土地使用权或者其他财产权利出资，需要评估作价的，可以由全体合伙人协商确定，也可以由全体合伙人委托法定评估机构评估。\n合伙人以劳务出资的，其评估办法由全体合伙人协商确定，并在合伙协议中载明。\n第十七条　合伙人应当按照合伙协议约定的出资方式、数额和缴付期限，履行出资义务。\n以非货币财产出资的，依照法律、行政法规的规定，需要办理财产权转移手续的，应当依法办理。\n第十八条　合伙协议应当载明下列事项：\n（一）合伙企业的名称和主要经营场所的地点；\n（二）合伙目的和合伙经营范围；\n（三）合伙人的姓名或者名称、住所；\n（四）合伙人的出资方式、数额和缴付期限；\n（五）利润分配、亏损分担方式；\n（六）合伙事务的执行；\n（七）入伙与退伙；\n（八）争议解决办法；\n（九）合伙企业的解散与清算；\n（十）违约责任。\n第十九条　合伙协议经全体合伙人签名、盖章后生效。合伙人按照合伙协议享有权利，履行义务。\n修改或者补充合伙协议，应当经全体合伙人一致同意；但是，合伙协议另有约定的除外。\n合伙协议未约定或者约定不明确的事项，由合伙人协商决定；协商不成的，依照本法和其他有关法律、行政法规的规定处理。\n第二节　合伙企业财产\n第二十条　合伙人的出资、以合伙企业名义取得的收益和依法取得的其他财产，均为合伙企业的财产。\n第二十一条　合伙人在合伙企业清算前，不得请求分割合伙企业的财产；但是，本法另有规定的除外。\n合伙人在合伙企业清算前私自转移或者处分合伙企业财产的，合伙企业不得以此对抗善意第三人。\n第二十二条　除合伙协议另有约定外，合伙人向合伙人以外的人转让其在合伙企业中的全部或者部分财产份额时，须经其他合伙人一致同意。\n合伙人之间转让在合伙企业中的全部或者部分财产份额时，应当通知其他合伙人。\n第二十三条　合伙人向合伙人以外的人转让其在合伙企业中的财产份额的，在同等条件下，其他合伙人有优先购买权；但是，合伙协议另有约定的除外。\n第二十四条　合伙人以外的人依法受让合伙人在合伙企业中的财产份额的，经修改合伙协议即成为合伙企业的合伙人，依照本法和修改后的合伙协议享有权利，履行义务。\n第二十五条　合伙人以其在合伙企业中的财产份额出质的，须经其他合伙人一致同意；未经其他合伙人一致同意，其行为无效，由此给善意第三人造成损失的，由行为人依法承担赔偿责任。\n第三节　合伙事务执行\n第二十六条　合伙人对执行合伙事务享有同等的权利。\n按照合伙协议的约定或者经全体合伙人决定，可以委托一个或者数个合伙人对外代表合伙企业，执行合伙事务。\n作为合伙人的法人、其他组织执行合伙事务的，由其委派的代表执行。\n第二十七条　依照本法第二十六条第二款规定委托一个或者数个合伙人执行合伙事务的，其他合伙人不再执行合伙事务。\n不执行合伙事务的合伙人有权监督执行事务合伙人执行合伙事务的情况。\n第二十八条　由一个或者数个合伙人执行合伙事务的，执行事务合伙人应当定期向其他合伙人报告事务执行情况以及合伙企业的经营和财务状况，其执行合伙事务所产生的收益归合伙企业，所产生的费用和亏损由合伙企业承担。\n合伙人为了解合伙企业的经营状况和财务状况，有权查阅合伙企业会计账簿等财务资料。\n第二十九条　合伙人分别执行合伙事务的，执行事务合伙人可以对其他合伙人执行的事务提出异议。提出异议时，应当暂停该项事务的执行。如果发生争议，依照本法第三十条规定作出决定。\n受委托执行合伙事务的合伙人不按照合伙协议或者全体合伙人的决定执行事务的，其他合伙人可以决定撤销该委托。\n第三十条　合伙人对合伙企业有关事项作出决议，按照合伙协议约定的表决办法办理。合伙协议未约定或者约定不明确的，实行合伙人一人一票并经全体合伙人过半数通过的表决办法。\n本法对合伙企业的表决办法另有规定的，从其规定。\n第三十一条　除合伙协议另有约定外，合伙企业的下列事项应当经全体合伙人一致同意：\n（一）改变合伙企业的名称；\n（二）改变合伙企业的经营范围、主要经营场所的地点；\n（三）处分合伙企业的不动产；\n（四）转让或者处分合伙企业的知识产权和其他财产权利；\n（五）以合伙企业名义为他人提供担保；\n（六）聘任合伙人以外的人担任合伙企业的经营管理人员。\n第三十二条　合伙人不得自营或者同他人合作经营与本合伙企业相竞争的业务。\n除合伙协议另有约定或者经全体合伙人一致同意外，合伙人不得同本合伙企业进行交易。\n合伙人不得从事损害本合伙企业利益的活动。\n第三十三条　合伙企业的利润分配、亏损分担，按照合伙协议的约定办理；合伙协议未约定或者约定不明确的，由合伙人协商决定；协商不成的，由合伙人按照实缴出资比例分配、分担；无法确定出资比例的，由合伙人平均分配、分担。\n合伙协议不得约定将全部利润分配给部分合伙人或者由部分合伙人承担全部亏损。\n第三十四条　合伙人按照合伙协议的约定或者经全体合伙人决定，可以增加或者减少对合伙企业的出资。\n第三十五条　被聘任的合伙企业的经营管理人员应当在合伙企业授权范围内履行职务。\n被聘任的合伙企业的经营管理人员，超越合伙企业授权范围履行职务，或者在履行职务过程中因故意或者重大过失给合伙企业造成损失的，依法承担赔偿责任。\n第三十六条　合伙企业应当依照法律、行政法规的规定建立企业财务、会计制度。\n第四节　合伙企业与第三人关系\n第三十七条　合伙企业对合伙人执行合伙事务以及对外代表合伙企业权利的限制，不得对抗善意第三人。\n第三十八条　合伙企业对其债务，应先以其全部财产进行清偿。\n第三十九条　合伙企业不能清偿到期债务的，合伙人承担无限连带责任。\n第四十条　合伙人由于承担无限连带责任，清偿数额超过本法第三十三条第一款规定的其亏损分担比例的，有权向其他合伙人追偿。\n第四十一条　合伙人发生与合伙企业无关的债务，相关债权人不得以其债权抵销其对合伙企业的债务；也不得代位行使合伙人在合伙企业中的权利。\n第四十二条　合伙人的自有财产不足清偿其与合伙企业无关的债务的，该合伙人可以以其从合伙企业中分取的收益用于清偿；债权人也可以依法请求人民法院强制执行该合伙人在合伙企业中的财产份额用于清偿。\n人民法院强制执行合伙人的财产份额时，应当通知全体合伙人，其他合伙人有优先购买权；其他合伙人未购买，又不同意将该财产份额转让给他人的，依照本法第五十一条的规定为该合伙人办理退伙结算，或者办理削减该合伙人相应财产份额的结算。\n第五节　入伙、退伙\n第四十三条　新合伙人入伙，除合伙协议另有约定外，应当经全体合伙人一致同意，并依法订立书面入伙协议。\n订立入伙协议时，原合伙人应当向新合伙人如实告知原合伙企业的经营状况和财务状况。\n第四十四条　入伙的新合伙人与原合伙人享有同等权利，承担同等责任。入伙协议另有约定的，从其约定。\n新合伙人对入伙前合伙企业的债务承担无限连带责任。\n第四十五条　合伙协议约定合伙期限的，在合伙企业存续期间，有下列情形之一的，合伙人可以退伙：\n（一）合伙协议约定的退伙事由出现；\n（二）经全体合伙人一致同意；\n（三）发生合伙人难以继续参加合伙的事由；\n（四）其他合伙人严重违反合伙协议约定的义务。\n第四十六条　合伙协议未约定合伙期限的，合伙人在不给合伙企业事务执行造成不利影响的情况下，可以退伙，但应当提前三十日通知其他合伙人。\n第四十七条　合伙人违反本法第四十五条、第四十六条的规定退伙的，应当赔偿由此给合伙企业造成的损失。\n第四十八条　合伙人有下列情形之一的，当然退伙：\n（一）作为合伙人的自然人死亡或者被依法宣告死亡；\n（二）个人丧失偿债能力；\n（三）作为合伙人的法人或者其他组织依法被吊销营业执照、责令关闭、撤销，或者被宣告破产；\n（四）法律规定或者合伙协议约定合伙人必须具有相关资格而丧失该资格；\n（五）合伙人在合伙企业中的全部财产份额被人民法院强制执行。\n合伙人被依法认定为无民事行为能力人或者限制民事行为能力人的，经其他合伙人一致同意，可以依法转为有限合伙人，普通合伙企业依法转为有限合伙企业。其他合伙人未能一致同意的，该无民事行为能力或者限制民事行为能力的合伙人退伙。\n退伙事由实际发生之日为退伙生效日。\n第四十九条　合伙人有下列情形之一的，经其他合伙人一致同意，可以决议将其除名：\n（一）未履行出资义务；\n（二）因故意或者重大过失给合伙企业造成损失；\n（三）执行合伙事务时有不正当行为；\n（四）发生合伙协议约定的事由。\n对合伙人的除名决议应当书面通知被除名人。被除名人接到除名通知之日，除名生效，被除名人退伙。\n被除名人对除名决议有异议的，可以自接到除名通知之日起三十日内，向人民法院起诉。\n第五十条　合伙人死亡或者被依法宣告死亡的，对该合伙人在合伙企业中的财产份额享有合法继承权的继承人，按照合伙协议的约定或者经全体合伙人一致同意，从继承开始之日起，取得该合伙企业的合伙人资格。\n有下列情形之一的，合伙企业应当向合伙人的继承人退还被继承合伙人的财产份额：\n（一）继承人不愿意成为合伙人；\n（二）法律规定或者合伙协议约定合伙人必须具有相关资格，而该继承人未取得该资格；\n（三）合伙协议约定不能成为合伙人的其他情形。\n合伙人的继承人为无民事行为能力人或者限制民事行为能力人的，经全体合伙人一致同意，可以依法成为有限合伙人，普通合伙企业依法转为有限合伙企业。全体合伙人未能一致同意的，合伙企业应当将被继承合伙人的财产份额退还该继承人。\n第五十一条　合伙人退伙，其他合伙人应当与该退伙人按照退伙时的合伙企业财产状况进行结算，退还退伙人的财产份额。退伙人对给合伙企业造成的损失负有赔偿责任的，相应扣减其应当赔偿的数额。\n退伙时有未了结的合伙企业事务的，待该事务了结后进行结算。\n第五十二条　退伙人在合伙企业中财产份额的退还办法，由合伙协议约定或者由全体合伙人决定，可以退还货币，也可以退还实物。\n第五十三条　退伙人对基于其退伙前的原因发生的合伙企业债务，承担无限连带责任。\n第五十四条　合伙人退伙时，合伙企业财产少于合伙企业债务的，退伙人应当依照本法第三十三条第一款的规定分担亏损。\n第六节　特殊的普通合伙企业\n第五十五条　以专业知识和专门技能为客户提供有偿服务的专业服务机构，可以设立为特殊的普通合伙企业。\n特殊的普通合伙企业是指合伙人依照本法第五十七条的规定承担责任的普通合伙企业。\n特殊的普通合伙企业适用本节规定；本节未作规定的，适用本章第一节至第五节的规定。\n第五十六条　特殊的普通合伙企业名称中应当标明“特殊普通合伙”字样。\n第五十七条　一个合伙人或者数个合伙人在执业活动中因故意或者重大过失造成合伙企业债务的，应当承担无限责任或者无限连带责任，其他合伙人以其在合伙企业中的财产份额为限承担责任。\n合伙人在执业活动中非因故意或者重大过失造成的合伙企业债务以及合伙企业的其他债务，由全体合伙人承担无限连带责任。\n第五十八条　合伙人执业活动中因故意或者重大过失造成的合伙企业债务，以合伙企业财产对外承担责任后，该合伙人应当按照合伙协议的约定对给合伙企业造成的损失承担赔偿责任。\n第五十九条　特殊的普通合伙企业应当建立执业风险基金、办理职业保险。\n执业风险基金用于偿付合伙人执业活动造成的债务。执业风险基金应当单独立户管理。具体管理办法由国务院规定。\n第三章　有限合伙企业\n第六十条　有限合伙企业及其合伙人适用本章规定；本章未作规定的，适用本法第二章第一节至第五节关于普通合伙企业及其合伙人的规定。\n第六十一条　有限合伙企业由二个以上五十个以下合伙人设立；但是，法律另有规定的除外。\n有限合伙企业至少应当有一个普通合伙人。\n第六十二条　有限合伙企业名称中应当标明“有限合伙”字样。\n第六十三条　合伙协议除符合本法第十八条的规定外，还应当载明下列事项：\n（一）普通合伙人和有限合伙人的姓名或者名称、住所；\n（二）执行事务合伙人应具备的条件和选择程序；\n（三）执行事务合伙人权限与违约处理办法；\n（四）执行事务合伙人的除名条件和更换程序；\n（五）有限合伙人入伙、退伙的条件、程序以及相关责任；\n（六）有限合伙人和普通合伙人相互转变程序。\n第六十四条　有限合伙人可以用货币、实物、知识产权、土地使用权或者其他财产权利作价出资。\n有限合伙人不得以劳务出资。\n第六十五条　有限合伙人应当按照合伙协议的约定按期足额缴纳出资；未按期足额缴纳的，应当承担补缴义务，并对其他合伙人承担违约责任。\n第六十六条　有限合伙企业登记事项中应当载明有限合伙人的姓名或者名称及认缴的出资数额。\n第六十七条　有限合伙企业由普通合伙人执行合伙事务。执行事务合伙人可以要求在合伙协议中确定执行事务的报酬及报酬提取方式。\n第六十八条　有限合伙人不执行合伙事务，不得对外代表有限合伙企业。\n有限合伙人的下列行为，不视为执行合伙事务：\n（一）参与决定普通合伙人入伙、退伙；\n（二）对企业的经营管理提出建议；\n（三）参与选择承办有限合伙企业审计业务的会计师事务所；\n（四）获取经审计的有限合伙企业财务会计报告；\n（五）对涉及自身利益的情况，查阅有限合伙企业财务会计账簿等财务资料；\n（六）在有限合伙企业中的利益受到侵害时，向有责任的合伙人主张权利或者提起诉讼；\n（七）执行事务合伙人怠于行使权利时，督促其行使权利或者为了本企业的利益以自己的名义提起诉讼；\n（八）依法为本企业提供担保。\n第六十九条　有限合伙企业不得将全部利润分配给部分合伙人；但是，合伙协议另有约定的除外。\n第七十条　有限合伙人可以同本有限合伙企业进行交易；但是，合伙协议另有约定的除外。\n第七十一条　有限合伙人可以自营或者同他人合作经营与本有限合伙企业相竞争的业务；但是，合伙协议另有约定的除外。\n第七十二条　有限合伙人可以将其在有限合伙企业中的财产份额出质；但是，合伙协议另有约定的除外。\n第七十三条　有限合伙人可以按照合伙协议的约定向合伙人以外的人转让其在有限合伙企业中的财产份额，但应当提前三十日通知其他合伙人。\n第七十四条　有限合伙人的自有财产不足清偿其与合伙企业无关的债务的，该合伙人可以以其从有限合伙企业中分取的收益用于清偿；债权人也可以依法请求人民法院强制执行该合伙人在有限合伙企业中的财产份额用于清偿。\n人民法院强制执行有限合伙人的财产份额时，应当通知全体合伙人。在同等条件下，其他合伙人有优先购买权。\n第七十五条　有限合伙企业仅剩有限合伙人的，应当解散；有限合伙企业仅剩普通合伙人的，转为普通合伙企业。\n第七十六条　第三人有理由相信有限合伙人为普通合伙人并与其交易的，该有限合伙人对该笔交易承担与普通合伙人同样的责任。\n有限合伙人未经授权以有限合伙企业名义与他人进行交易，给有限合伙企业或者其他合伙人造成损失的，该有限合伙人应当承担赔偿责任。\n第七十七条　新入伙的有限合伙人对入伙前有限合伙企业的债务，以其认缴的出资额为限承担责任。\n第七十八条　有限合伙人有本法第四十八条第一款第一项、第三项至第五项所列情形之一的，当然退伙。\n第七十九条　作为有限合伙人的自然人在有限合伙企业存续期间丧失民事行为能力的，其他合伙人不得因此要求其退伙。\n第八十条　作为有限合伙人的自然人死亡、被依法宣告死亡或者作为有限合伙人的法人及其他组织终止时，其继承人或者权利承受人可以依法取得该有限合伙人在有限合伙企业中的资格。\n第八十一条　有限合伙人退伙后，对基于其退伙前的原因发生的有限合伙企业债务，以其退伙时从有限合伙企业中取回的财产承担责任。\n第八十二条　除合伙协议另有约定外，普通合伙人转变为有限合伙人，或者有限合伙人转变为普通合伙人，应当经全体合伙人一致同意。\n第八十三条　有限合伙人转变为普通合伙人的，对其作为有限合伙人期间有限合伙企业发生的债务承担无限连带责任。\n第八十四条　普通合伙人转变为有限合伙人的，对其作为普通合伙人期间合伙企业发生的债务承担无限连带责任。\n第四章　合伙企业解散、清算\n第八十五条　合伙企业有下列情形之一的，应当解散：\n（一）合伙期限届满，合伙人决定不再经营；\n（二）合伙协议约定的解散事由出现；\n（三）全体合伙人决定解散；\n（四）合伙人已不具备法定人数满三十天；\n（五）合伙协议约定的合伙目的已经实现或者无法实现；\n（六）依法被吊销营业执照、责令关闭或者被撤销；\n（七）法律、行政法规规定的其他原因。\n第八十六条　合伙企业解散，应当由清算人进行清算。\n清算人由全体合伙人担任；经全体合伙人过半数同意，可以自合伙企业解散事由出现后十五日内指定一个或者数个合伙人，或者委托第三人，担任清算人。\n自合伙企业解散事由出现之日起十五日内未确定清算人的，合伙人或者其他利害关系人可以申请人民法院指定清算人。\n第八十七条　清算人在清算期间执行下列事务：\n（一）清理合伙企业财产，分别编制资产负债表和财产清单；\n（二）处理与清算有关的合伙企业未了结事务；\n（三）清缴所欠税款；\n（四）清理债权、债务；\n（五）处理合伙企业清偿债务后的剩余财产；\n（六）代表合伙企业参加诉讼或者仲裁活动。\n第八十八条　清算人自被确定之日起十日内将合伙企业解散事项通知债权人，并于六十日内在报纸上公告。债权人应当自接到通知书之日起三十日内，未接到通知书的自公告之日起四十五日内，向清算人申报债权。\n债权人申报债权，应当说明债权的有关事项，并提供证明材料。清算人应当对债权进行登记。\n清算期间，合伙企业存续，但不得开展与清算无关的经营活动。\n第八十九条　合伙企业财产在支付清算费用和职工工资、社会保险费用、法定补偿金以及缴纳所欠税款、清偿债务后的剩余财产，依照本法第三十三条第一款的规定进行分配。\n第九十条　清算结束，清算人应当编制清算报告，经全体合伙人签名、盖章后，在十五日内向企业登记机关报送清算报告，申请办理合伙企业注销登记。\n第九十一条　合伙企业注销后，原普通合伙人对合伙企业存续期间的债务仍应承担无限连带责任。\n第九十二条　合伙企业不能清偿到期债务的，债权人可以依法向人民法院提出破产清算申请，也可以要求普通合伙人清偿。\n合伙企业依法被宣告破产的，普通合伙人对合伙企业债务仍应承担无限连带责任。\n第五章　法律责任\n第九十三条　违反本法规定，提交虚假文件或者采取其他欺骗手段，取得合伙企业登记的，由企业登记机关责令改正，处以五千元以上五万元以下的罚款；情节严重的，撤销企业登记，并处以五万元以上二十万元以下的罚款。\n第九十四条　违反本法规定，合伙企业未在其名称中标明“普通合伙”、“特殊普通合伙”或者“有限合伙”字样的，由企业登记机关责令限期改正，处以二千元以上一万元以下的罚款。\n第九十五条　违反本法规定，未领取营业执照，而以合伙企业或者合伙企业分支机构名义从事合伙业务的，由企业登记机关责令停止，处以五千元以上五万元以下的罚款。\n合伙企业登记事项发生变更时，未依照本法规定办理变更登记的，由企业登记机关责令限期登记；逾期不登记的，处以二千元以上二万元以下的罚款。\n合伙企业登记事项发生变更，执行合伙事务的合伙人未按期申请办理变更登记的，应当赔偿由此给合伙企业、其他合伙人或者善意第三人造成的损失。\n第九十六条　合伙人执行合伙事务，或者合伙企业从业人员利用职务上的便利，将应当归合伙企业的利益据为己有的，或者采取其他手段侵占合伙企业财产的，应当将该利益和财产退还合伙企业；给合伙企业或者其他合伙人造成损失的，依法承担赔偿责任。\n第九十七条　合伙人对本法规定或者合伙协议约定必须经全体合伙人一致同意始得执行的事务擅自处理，给合伙企业或者其他合伙人造成损失的，依法承担赔偿责任。\n第九十八条　不具有事务执行权的合伙人擅自执行合伙事务，给合伙企业或者其他合伙人造成损失的，依法承担赔偿责任。\n第九十九条　合伙人违反本法规定或者合伙协议的约定，从事与本合伙企业相竞争的业务或者与本合伙企业进行交易的，该收益归合伙企业所有；给合伙企业或者其他合伙人造成损失的，依法承担赔偿责任。\n第一百条　清算人未依照本法规定向企业登记机关报送清算报告，或者报送清算报告隐瞒重要事实，或者有重大遗漏的，由企业登记机关责令改正。由此产生的费用和损失，由清算人承担和赔偿。\n第一百零一条　清算人执行清算事务，牟取非法收入或者侵占合伙企业财产的，应当将该收入和侵占的财产退还合伙企业；给合伙企业或者其他合伙人造成损失的，依法承担赔偿责任。\n第一百零二条　清算人违反本法规定，隐匿、转移合伙企业财产，对资产负债表或者财产清单作虚假记载，或者在未清偿债务前分配财产，损害债权人利益的，依法承担赔偿责任。\n第一百零三条　合伙人违反合伙协议的，应当依法承担违约责任。\n合伙人履行合伙协议发生争议的，合伙人可以通过协商或者调解解决。不愿通过协商、调解解决或者协商、调解不成的，可以按照合伙协议约定的仲裁条款或者事后达成的书面仲裁协议，向仲裁机构申请仲裁。合伙协议中未订立仲裁条款，事后又没有达成书面仲裁协议的，可以向人民法院起诉。\n第一百零四条　有关行政管理机关的工作人员违反本法规定，滥用职权、徇私舞弊、收受贿赂、侵害合伙企业合法权益的，依法给予行政处分。\n第一百零五条　违反本法规定，构成犯罪的，依法追究刑事责任。\n第一百零六条　违反本法规定，应当承担民事赔偿责任和缴纳罚款、罚金，其财产不足以同时支付的，先承担民事赔偿责任。\n第六章　附　　则\n第一百零七条　非企业专业服务机构依据有关法律采取合伙制的，其合伙人承担责任的形式可以适用本法关于特殊的普通合伙企业合伙人承担责任的规定。\n第一百零八条　外国企业或者个人在中国境内设立合伙企业的管理办法由国务院规定。\n第一百零九条　本法自2007年6月1日起施行。",
    "source": "npc"
  }
]